Workbook

Sheet Centralizator facultate
A2: Facultate: | B2: Științe Agricole, Industrie Alimentară și Protecția Medului
D3: Cd doc Prof Conf Lect/Șl Asist | E3: Cd doc: 500 Prof: 350 Conf: 300 Lect/Șl: 250 Asistent 200 | K3: Atentie! Plafon maxim! | L3: Atentie! Plafon maxim! | M3: Atentie! Plafon maxim! | P3: Atentie! Plafon maxim! | Q3: Atentie! Plafon maxim! | R3: Atentie! Plafon maxim! | S3: Atentie! Plafon maxim! | T3: Atentie! Plafon maxim! | U3: Atentie! Plafon maxim! | X3: Atentie! Plafon maxim! | Y3: Atentie! Plafon maxim! | AC3: Galben = OK Rosu = ATENTIE | AD3: Galben = OK Rosu = ATENTIE
A4: Nr. crt. | B4: Numele și prenumele | C4: Cod Departament | D4: Grad didactic la 01.01.2019 | E4: Punctaj de referinta cf grad didactic | F4: I1 | G4: I2 | H4: I3 | I4: I4 | J4: I5 | K4: I6 | L4: I7 | M4: I8 | N4: I9 | O4: I10 | P4: I11 | Q4: I12 | R4: I13 | S4: I14 | T4: I15 | U4: I16 | V4: I17 | W4: I18 | X4: I19 | Y4: I20 | Z4: TOTAL | AA4: Punctaj centralizator individual semnat | AB4: Punctaj centralizator facultate | AC4: Diferente TOTAL - Centralizator individual | AD4: Diferente TOTAL - Centralizator facultate
A5: 1 | B5: ANTOFIE Maria Mihaela | C5: FSAA2 | D5: Conferenţiar | E5: 300 | G5: 250 | H5: 400 | K5: 240 | L5: 48 | N5: 166.46 | S5: 200 | T5: 100 | Y5: 30 | Z5: =SUM(F5:Y5) -> 1434.46 | AA5: 1434.46 | AB5: 1434.46 | AC5: =Z5-AA5 -> 0 | AD5: =Z5-AB5 -> 0
A6: 2 | B6: ANTONIE Iuliana | C6: FSAA2 | D6: Şef lucrări | E6: 250 | H6: 200 | N6: 105.89 | U6: 50 | Y6: 40 | Z6: =SUM(F6:Y6) -> 395.89 | AA6: 395.89 | AB6: 395.89 | AC6: =Z6-AA6 -> 0 | AD6: =Z6-AB6 -> 0
A7: 3 | B7: BARBU Constantin Horia | C7: FSAA2 | D7: Profesor | E7: 350 | N7: 332.32 | Y7: 20 | Z7: =SUM(F7:Y7) -> 352.32 | AA7: 352.32 | AB7: 352.32 | AC7: =Z7-AA7 -> 0 | AD7: =Z7-AB7 -> 0
A8: 4 | B8: BARBU Ion | C8: FSAA2 | D8: Şef lucrări | E8: 250 | N8: 12.5 | Z8: =SUM(F8:Y8) -> 12.5 | AA8: 12.5 | AB8: 12.5 | AC8: =Z8-AA8 -> 0 | AD8: =Z8-AB8 -> 0
A9: 5 | B9: BLAJ Robert | C9: FSAA2 | D9: Conferenţiar | E9: 300 | H9: 300 | N9: 152.14 | Y9: 20 | Z9: =SUM(F9:Y9) -> 472.14 | AA9: 472.14 | AB9: 472.14 | AC9: =Z9-AA9 -> 0 | AD9: =Z9-AB9 -> 0
A10: 6 | B10: BRATU Iulian Alexandru | C10: FSAA2 | D10: Şef lucrări | E10: 250 | I10: 50 | J10: 70 | L10: 300 | N10: 73.75 | Y10: 20 | Z10: =SUM(F10:Y10) -> 513.75 | AA10: 513.75 | AB10: 513.75 | AC10: =Z10-AA10 -> 0 | AD10: =Z10-AB10 -> 0
A11: 7 | B11: CĂPĂŢÂNĂ Ciprian | C11: FSAA2 | D11: Ş.l. | E11: 250 | L11: 270 | Z11: =SUM(F11:Y11) -> 270 | AA11: 270 | AB11: 270 | AC11: =Z11-AA11 -> 0 | AD11: =Z11-AB11 -> 0
A12: 8 | B12: CĂRĂTUŞ Mirela Aurora | C12: FSAA2 | D12: Conferenţiar | E12: 300 | H12: 707 | N12: 276.5 | Y12: 20 | Z12: =SUM(F12:Y12) -> 1003.5 | AA12: 1003.5 | AB12: 1003.5 | AC12: =Z12-AA12 -> 0 | AD12: =Z12-AB12 -> 0
A13: 9 | B13: CREŢU Carmen Monica | C13: FSAA2 | D13: Conf. | E13: 300 | L13: 200 | N13: 38.34 | T13: 100 | Y13: 20 | Z13: =SUM(F13:Y13) -> 358.34 | AA13: 358.34 | AB13: 358.34 | AC13: =Z13-AA13 -> 0 | AD13: =Z13-AB13 -> 0
A14: 10 | B14: CRISTEA Ramona | C14: FSAA2 | D14: Ș.l. | E14: 250 | N14: 48.32 | Y14: 40 | Z14: =SUM(F14:Y14) -> 88.32 | AA14: 88.32 | AB14: 88.32 | AC14: =Z14-AA14 -> 0 | AD14: =Z14-AB14 -> 0
A15: 11 | B15: DANCIU Cristina Anca | C15: FSAA2 | D15: Ş.l. | E15: 250 | L15: 300 | Z15: =SUM(F15:Y15) -> 300 | AA15: 300 | AB15: 300 | AC15: =Z15-AA15 -> 0 | AD15: =Z15-AB15 -> 0
A16: 12 | B16: DRĂGHICI Olga | C16: FSAA2 | D16: Ş.l. | E16: 250 | G16: 291.67 | L16: 300 | N16: 187.5 | O16: 33.33 | T16: 75 | Z16: =SUM(F16:Y16) -> 887.5 | AA16: 887.5 | AB16: 887.5 | AC16: =Z16-AA16 -> 0 | AD16: =Z16-AB16 -> 0
A17: 13 | B17: DUMITRU Mariana Lenuţa | C17: FSAA2 | D17: Conferenţiar | E17: 300 | H17: 200 | Z17: =SUM(F17:Y17) -> 200 | AA17: 200 | AB17: 200 | AC17: =Z17-AA17 -> 0 | AD17: =Z17-AB17 -> 0
A18: 14 | B18: GASPAR Eniko | C18: FSAA2 | D18: Şef lucrări | E18: 250 | Y18: 20 | Z18: =SUM(F18:Y18) -> 20 | AA18: 20 | AB18: 20 | AC18: =Z18-AA18 -> 0 | AD18: =Z18-AB18 -> 0
A19: 15 | B19: GEORGESCU Cecilia | C19: FSAA2 | D19: Conf. | E19: 300 | F19: 562.5 | H19: 100 | J19: 8.75 | N19: 1004.39 | S19: 150 | T19: 200 | U19: 50 | Y19: 48 | Z19: =SUM(F19:Y19) -> 2123.64 | AA19: 2123.64 | AB19: 2123.64 | AC19: =Z19-AA19 -> 0 | AD19: =Z19-AB19 -> 0
A20: 16 | B20: IAGĂRU Pompilica | C20: FSAA2 | D20: Şef lucrări | E20: 250 | G20: 125 | H20: 40 | N20: 61.25 | T20: 75 | Y20: 20 | Z20: =SUM(F20:Y20) -> 321.25 | AA20: 321.25 | AB20: 321.25 | AC20: =Z20-AA20 -> 0 | AD20: =Z20-AB20 -> 0
A21: 17 | B21: IAGĂRU Romulus | C21: FSAA2 | D21: Profesor | E21: 350 | G21: 125 | H21: 40 | J21: 35 | N21: 57.5 | S21: 50 | T21: 125 | Y21: 20 | Z21: =SUM(F21:Y21) -> 452.5 | AA21: 452.5 | AB21: 452.5 | AC21: =Z21-AA21 -> 0 | AD21: =Z21-AB21 -> 0
A22: 18 | B22: IANCU Maria Lidia | C22: FSAA2 | D22: Ş.l. | E22: 250 | H22: 200 | L22: 300 | N22: 362.5 | T22: 25 | Y22: 20 | Z22: =SUM(F22:Y22) -> 907.5 | AA22: 907.5 | AB22: 907.5 | AC22: =Z22-AA22 -> 0 | AD22: =Z22-AB22 -> 0
A23: 19 | B23: KETNEY Otto | C23: FSAA2 | D23: Ş.l. | E23: 250 | N23: 630.43 | T23: 200 | Y23: 10 | Z23: =SUM(F23:Y23) -> 840.43 | AA23: 840.43 | AB23: 840.43 | AC23: =Z23-AA23 -> 0 | AD23: =Z23-AB23 -> 0
A24: 20 | B24: LENGYEL Ecaterina | C24: FSAA2 | D24: Ş.l. | E24: 250 | H24: 50 | J24: 14 | N24: 399.32 | Y24: 40 | Z24: =SUM(F24:Y24) -> 503.32 | AA24: 503.32 | AB24: 503.32 | AC24: =Z24-AA24 -> 0 | AD24: =Z24-AB24 -> 0
A25: 21 | B25: MIRONESCU Ion Dan | C25: FSAA2 | D25: Conf. | E25: 300 | K25: 37.5 | N25: 57.5 | T25: 200 | W25: 100 | Y25: 20 | Z25: =SUM(F25:Y25) -> 415 | AA25: 415 | AB25: 415 | AC25: =Z25-AA25 -> 0 | AD25: =Z25-AB25 -> 0
A26: 22 | B26: MIRONESCU Monica | C26: FSAA2 | D26: Conf. | E26: 300 | J26: 8.75 | N26: 545.51 | S26: 200 | T26: 200 | V26: 110 | W26: 400 | Y26: 58 | Z26: =SUM(F26:Y26) -> 1522.26 | AA26: 1522.26 | AB26: 1522.26 | AC26: =Z26-AA26 -> 0 | AD26: =Z26-AB26 -> 0
A27: 23 | B27: MOISE George | C27: FSAA2 | D27: Ş.l. | E27: 250 | H27: 200 | N27: 250 | U27: 50 | Y27: 40 | Z27: =SUM(F27:Y27) -> 540 | AA27: 540 | AB27: 540 | AC27: =Z27-AA27 -> 0 | AD27: =Z27-AB27 -> 0
A28: 24 | B28: MOISE Maria Cristina | C28: FSAA2 | D28: Şef lucrări | E28: 250 | H28: 725 | N28: 215 | U28: 50 | Y28: 40 | Z28: =SUM(F28:Y28) -> 1030 | AA28: 1030 | AB28: 1030 | AC28: =Z28-AA28 -> 0 | AD28: =Z28-AB28 -> 0
A29: 25 | B29: OANCEA Simona Rodica | C29: FSAA2 | D29: Prof. | E29: 500 | G29: 725 | H29: 418.18 | N29: 1622.57 | O29: 33.33 | S29: 100 | W29: 300 | Z29: =SUM(F29:Y29) -> 3199.08 | AA29: 3199.08 | AB29: 3199.08 | AC29: =Z29-AA29 -> 0 | AD29: =Z29-AB29 -> 0
A30: 26 | B30: OGNEAN Claudia Felicia | C30: FSAA2 | D30: Ş.l. | E30: 250 | N30: 176.67 | T30: 25 | Y30: 40 | Z30: =SUM(F30:Y30) -> 241.67 | AA30: 241.67 | AB30: 241.67 | AC30: =Z30-AA30 -> 0 | AD30: =Z30-AB30 -> 0
A31: 27 | B31: OGNEAN Mihai | C31: FSAA2 | D31: Ş.l. | E31: 250 | N31: 176.67 | T31: 50 | W31: 63.5 | Y31: 40 | Z31: =SUM(F31:Y31) -> 330.17 | AA31: 330.17 | AB31: 330.17 | AC31: =Z31-AA31 -> 0 | AD31: =Z31-AB31 -> 0
A32: 28 | B32: PĂCALĂ Mariana Liliana | C32: FSAA2 | D32: Ş.l. | E32: 250 | L32: 155 | N32: 51.66 | T32: 50 | Z32: =SUM(F32:Y32) -> 256.66 | AA32: 256.66 | AB32: 256.66 | AC32: =Z32-AA32 -> 0 | AD32: =Z32-AB32 -> 0
A33: 29 | B33: PĂŞCĂNUŢ Ioan | C33: FSAA2 | D33: Şef lucrări | E33: 250 | Y33: 20 | Z33: =SUM(F33:Y33) -> 20 | AA33: 20 | AB33: 20 | AC33: =Z33-AA33 -> 0 | AD33: =Z33-AB33 -> 0
A34: 30 | B34: POP Mihai Radu | C34: FSAA2 | D34: Şef lucrări | E34: 250 | N34: 21.37 | Y34: 20 | Z34: =SUM(F34:Y34) -> 41.37 | AA34: 41.37 | AB34: 41.37 | AC34: =Z34-AA34 -> 0 | AD34: =Z34-AB34 -> 0
A35: 31 | B35: ŞANDRU Daniela Maria | C35: FSAA2 | D35: Asist. | E35: 200 | J35: 140 | N35: 28.75 | Y35: 20 | Z35: =SUM(F35:Y35) -> 188.75 | AA35: 188.75 | AB35: 188.75 | AC35: =Z35-AA35 -> 0 | AD35: =Z35-AB35 -> 0
A36: 32 | B36: SAVA Camelia | C36: FSAA2 | D36: Profesor | E36: 350 | H36: 200 | L36: 170 | M36: 50 | N36: 140.47 | S36: 200 | T36: 125 | U36: 10 | Y36: 30 | Z36: =SUM(F36:Y36) -> 925.47 | AA36: 925.47 | AB36: 925.47 | AC36: =Z36-AA36 -> 0 | AD36: =Z36-AB36 -> 0
A37: 33 | B37: SAVATIE Mircea Benvenuto | C37: FSAA2 | D37: Şef lucrări | E37: 250 | Y37: 20 | Z37: =SUM(F37:Y37) -> 20 | AA37: 20 | AB37: 20 | AC37: =Z37-AA37 -> 0 | AD37: =Z37-AB37 -> 0
A38: 34 | B38: SIMTION Daniela Maria | C38: FSAA2 | D38: Şef lucrări | E38: 250 | H38: 400 | N38: 130 | Z38: =SUM(F38:Y38) -> 530 | AA38: 530 | AB38: 530 | AC38: =Z38-AA38 -> 0 | AD38: =Z38-AB38 -> 0
A39: 35 | B39: ŞIPOŞ Anca Sorina | C39: FSAA2 | D39: Prof. | E39: 350 | F39: 2333.33 | I39: 25 | L39: 290 | N39: 100 | T39: 75 | Z39: =SUM(F39:Y39) -> 2823.33 | AA39: 2823.33 | AB39: 2823.33 | AC39: =Z39-AA39 -> 0 | AD39: =Z39-AB39 -> 0
A40: 36 | B40: SPÂNU Simona Mariana | C40: FSAA2 | D40: Şef lucrări | E40: 250 | I40: 50 | K40: 15.75 | L40: 9 | N40: 142.5 | T40: 200 | Y40: 20 | Z40: =SUM(F40:Y40) -> 437.25 | AA40: 437.25 | AB40: 437.25 | AC40: =Z40-AA40 -> 0 | AD40: =Z40-AB40 -> 0
A41: 37 | B41: TIŢA Mihaela Adriana | C41: FSAA2 | D41: Prof. | E41: 350 | F41: 375 | H41: 300 | J41: 315 | K41: 378 | N41: 98.75 | S41: 150 | T41: 200 | Y41: 60 | Z41: =SUM(F41:Y41) -> 1876.75 | AA41: 1876.75 | AB41: 1876.75 | AC41: =Z41-AA41 -> 0 | AD41: =Z41-AB41 -> 0
A42: 38 | B42: TIŢA Ovidiu | C42: FSAA2 | D42: Prof. | E42: 500 | F42: 562.5 | H42: 100 | J42: 87.5 | N42: 344.37 | S42: 200 | T42: 175 | Y42: 36.66 | Z42: =SUM(F42:Y42) -> 1506.03 | AA42: 1506.03 | AB42: 1506.03 | AC42: =Z42-AA42 -> 0 | AD42: =Z42-AB42 -> 0
A43: 39 | B43: TULBURE Anca | C43: FSAA2 | D43: Ş.l. | E43: 250 | L43: 300 | Z43: =SUM(F43:Y43) -> 300 | AA43: 300 | AB43: 300 | AC43: =Z43-AA43 -> 0 | AD43: =Z43-AB43 -> 0
A44: 40 | B44: TURTUREANU Adrian | C44: FSAA2 | D44: Conf. | E44: 300 | Z44: =SUM(F44:Y44) -> 0 | AA44: 0 | AB44: 0 | AC44: =Z44-AA44 -> 0 | AD44: =Z44-AB44 -> 0
A45: 41 | B45: VĂDUVA Mihai | C45: FSAA2 | D45: Ş.l. | E45: 250 | L45: 270 | Z45: =SUM(F45:Y45) -> 270 | AA45: 270 | AB45: 270 | AC45: =Z45-AA45 -> 0 | AD45: =Z45-AB45 -> 0
A46: 42 | B46: VECERDEA (PAVEL) Petronela Bianca | C46: FSAA2 | D46: Şef lucrări | E46: 250 | N46: 791.7 | Y46: 20 | Z46: =SUM(F46:Y46) -> 811.7 | AA46: 811.7 | AB46: 811.7 | AC46: =Z46-AA46 -> 0 | AD46: =Z46-AB46 -> 0
A47: TOTAL | E47: =SUM(E5:E46) -> 11900 | F47: =SUM(F5:F46) -> 3833.33 | G47: =SUM(G5:G46) -> 1516.67 | H47: =SUM(H5:H46) -> 4580.18 | I47: =SUM(I5:I46) -> 125 | J47: =SUM(J5:J46) -> 679 | K47: =SUM(K5:K46) -> 671.25 | L47: =SUM(L5:L46) -> 2912 | ... Y47: =SUM(Y5:Y46) -> 872.66 | Z47: =SUM(F47:Y47) -> 28742.85
A48: TOTAL din baza (I1 ...I20) | F48: =I.1!P61 -> 3833.33 | G48: =I.2!P61 -> 1516.67 | H48: =I.3!N58 -> 4580.18 | I48: =I.4!M60 -> 125 | J48: =I.5!M61 -> 679 | K48: =I.6!J62 -> 671.25 | L48: =I.7!J63 -> 2912 | M48: =I.8!I61 -> 50 | N48: =I.9!H560 -> 8802.6 | O48: =I.10!F29 -> 66.66 | P48: =I.11!F28 -> 0 | Q48: =I.12!H60 -> 0 | R48: =I.13!H61 -> 0 | S48: =I.14!G61 -> 1250 | T48: =I.15!G69 -> 2200 | U48: =I.16!I59 -> 210 | V48: ='I. 17.'!J63 -> 110 | W48: ='I. 18'!J64 -> 863.5 | X48: =I.19!K57 -> 0 | Y48: =I.20!H63 -> 872.66 | Z48: =SUM(F48:Y48) -> 28742.85
A49: Diferenta total-total baza | F49: =F47-F48 -> 0 | G49: =G47-G48 -> 0 | H49: =H47-H48 -> 0 | I49: =I47-I48 -> 0 | J49: =J47-J48 -> 0 | K49: =K47-K48 -> 0 | L49: =L47-L48 -> 0 | M49: =M47-M48 -> 0 | ... Y49: =Y47-Y48 -> 0 | Z49: =SUM(F49:Y49) -> 0 | AA49: Galben = OK Rosu = ATENTIE
B51: Numar cadre didactice centralizator facultate: | D51: 42
B52: Numar cadre didactice verficate: | D52: =COUNTA(D5:D46) -> 42
B53: Diferenta: | D53: =D51-D52 -> 0 | E53: Galben = OK Rosu = ATENTIE

Sheet I.1
A2: I.1 - Articol în revistă WoS: SCIS, SSCI situată în ”zona rosie” / Q1, ”zona galbenă” / Q2, respectiv AHCI > 5 ani
A4: Articole încadrate “document type” ca “Article” sau „Review” în reviste cotate WoS (Web of Science) - SCIE - Science Citation Index Expanded şi SSCI - Social Sciences Citation Index), din ”zona roşie”/Q1, şi ”zona galbenă”/Q2 în conformitate cu Listele UEFISCDI a revistelor încadrate pe subdomenii ştiinţifice, respectiv în reviste AHCI - Arts & Humanities Citation Index cu o vechime de cel puţin 5 ani în Web of Science Core Collection, în conformitate cu Lista UEFISCDI a revistelor indexate in AHCI.
A5: Articolul trebuie publicat în anul de raportare şi să fie vizibil în Web of Science Core Collection din platforma www.webofknowledge.com
A6: Listele de referință UEFISCDI sunt cele din anul anterior raportării și sunt disponibile pe site-ul https://uefiscdi.ro/scientometrie-reviste. În cazul în care o revistă este încadrată în mai multe subdomenii, se ia în calcul încadrarea cea mai favorabilă.
A7: Articolul trebuie să conţină menţiunea afilierii la ULBS a declarantului.
A8: * Punctaje de referință: • Articol în zona roşie / Q1 = 1500 de puncte • Articol in zona galbenă / Q2 = 1000 de puncte • Articol in AHCI > 5 ani: 1200 puncte Punctajul se împarte la numărul de autori cu afiliere la instituţiile de învăţământ şi cercetare din România, inclusiv la doctoranzi / studenţi. Punctajul NU se împarte cu autorii din străinătate sau cu autorii din mediul de afaceri (pentru acești autori se menţionează în paranteză instituţia de proveniență).
A10: Titlul articolului | B10: Numele și prenumele autorilor (afilierea) | C10: Cod departament | D10: Titlul revistei | E10: Volum | F10: Număr | G10: ISSN revistă | H10: Link către articol pe site - ul revistei | I10: DOI articol (Digital object identifier) | J10: WOS Accession Number | K10: Paginile articolului (de la … până la …) | L10: Anul publicării | M10: Tipul revistei (zona rosie/Q1; zona galbena/Q2; AHCI>5ani) | N10: Factor de impact revistă | O10: Punctaj de referință* | P10: Punctaj individual | Q10: Numele și prenumele Declarant
A11: Bilberry (Vaccinium myrtillus L.) Extracts Comparative Analysis Regarding Their Phytonutrient Profiles, Antioxidant Capacity along with the In Vivo Rescue Effects Tested on a Drosophila melanogaster High-Sugar Diet Model | B11: Andreea-Adriana Neamtu-University of Oradea, Rita Szoke-Kovacs, Emoke Mihok, University of Debrecen, Cecilia Georgescu, “Lucian Blaga” University of Sibiu, Violeta Turcus, Neli Kinga Olah, “Vasile Goldis” Western University of Arad, Adina Frum, Ovidiu Tita, “Lucian Blaga” University of Sibiu, Carmen Neamtu, “Vasile Goldis” Western University of Arad, Zsombor Szoke-Kovacs, University of Debrecen, Zoltan Cziaky, Agricultural and Molecular Research and Service Institute, University of Nyiregyhaza and Endre Mathe, University of Debrecen and “Vasile Goldis” Western University of Arad | C11: FSAA2 | D11: Antioxidants | E11: 9 | F11: 11 | G11: ISSN: eISSN: 2076-3921 | H11: Antioxidants | Free Full-Text | Bilberry (Vaccinium myrtillus L.) Extracts Comparative Analysis Regarding Their Phytonutrient Profiles, Antioxidant Capacity along with the In Vivo Rescue Effects Tested on a Drosophila melanogaster High-Sugar Diet Model (mdpi.com) | I11: doi:10.3390/antiox9111067 | J11: WOS:000592780600001 | K11: 1-33 | L11: 2020 | M11: Q1 | N11: 5.014 | O11: 1500 | P11: 187.5 | Q11: Georgescu Cecilia
A12: Use of Yoghurt Enhanced with Volatile Plant Oils Encapsulated in Sodium Alginate to Increase the Human Body's Immunity in the Present Fight Against Stress | B12: Tita Ovidiu, Constantinescu Maria Adelina, Tita Mihaela Adriana, Georgescu Cecilia, “Lucian Blaga” University of Sibiu | C12: FSAA2 | D12: INTERNATIONAL JOURNAL OF ENVIRONMENTAL RESEARCH AND PUBLIC HEALTH | E12: 17 | F12: 20 | G12: ISSN: eISSN: 1660-4601 | H12: https://www.mdpi.com/1660-4601/17/20/7588 | I12: 10.3390/ijerph17207588 | J12: WOS:000585597700001 | K12: 1-17 | L12: 2020 | M12: Q1 | N12: 2.849 | O12: 1500 | P12: 375 | Q12: Georgescu Cecilia
A13: Sustainable Method Using Filtering Techniques for a Fermentation Process State Estimation | B13: Anca Sipos | C13: FSAA2 | D13: Sustainability | E13: 12 | F13: 17 | G13: 2071-1050 | H13: https://www.mdpi.com/2071-1050/12/17/7105 | I13: https://doi.org/10.3390/su12177105 | J13: WOS:000570331900001 | K13: 7105-7119 | L13: 44074 | M13: Q2 | N13: 2.576 | O13: 1000 | P13: 1000 | Q13: Sipos Anca
A14: A Knowledge-Based System as a Sustainable Software Application for the Supervision and Intelligent Control of an Alcoholic Fermentation Process | B14: Anca Sipos | C14: FSAA2 | D14: Sustainability | E14: 12 | F14: 23 | G14: 2071-1050 | H14: https://www.mdpi.com/2071-1050/12/23/10205 | I14: https://doi.org/10.3390/su122310205 | J14: WOS:000597489300001 | K14: 10205-10221 | L14: 7 Decembrie 2020 | M14: Q2 | N14: 2.576 | O14: 1000 | P14: 1000 | Q14: Sipos Anca
A15: Using Neural Networks to Obtain Indirect Information about the State Variables in an Alcoholic Fermentation Process | B15: Anca Sipos, Adrian Florea, Maria Arsin and Ugo Fiore | C15: FSAA2 | D15: Processes | E15: 9 | F15: 1 | H15: https://www.mdpi.com/2227-9717/9/1/74 | I15: https://doi.org/10.3390/pr9010074 | J15: WOS:000610732300001 | K15: 74-92 | L15: 31 Decembrie 2020 | M15: Q2 | N15: 2.753 | O15: 1000 | P15: 333.33 | Q15: Sipos Anca
A16: Use of Yoghurt Enhanced with Volatile Plant Oils Encapsulated in Sodium Alginate to Increase the Human Body’s Immunity in the Present Fight Against Stres | B16: Ovidiu Tita, Maria Adelina Constantinescu, Mihaela Adriana Tita, Cecilia Georgescu-ULBS | C16: FSAA2 | D16: Int. J. Environ. Res. Public Health | E16: 17 | F16: 20 | G16: 1660-4601 | H16: https://www.mdpi.com/1660-4601/17/20/7588 | I16: doi:10.3390/ijerph17207588, | J16: WOS:000585597700001 | K16: 1-17 | L16: 2020 | M16: Q1 | N16: 2849 | O16: 1500 | P16: 375 | Q16: Tita Mihaela
A17: Bilberry (Vaccinium myrtillus L.) Extracts Comparative Analysis Regarding Their Phytonutrient Profiles, Antioxidant Capacity along with the In Vivo Rescue Effects Tested on a Drosophila melanogaster High-Sugar Diet Model | B17: Andreea-Adriana Neamtu -University of Oradea, Romania; Rita Szoke-Kovacs - University of Debrecen, Hungary; Emoke Mihok - University of Debrecen, Hungary; Cecilia Georgescu - “Lucian Blaga” University of Sibiu, Romania; Violeta Turcus - “Vasile Goldis” Western University of Arad, Romania; Neli Kinga Olah - Faculty of Pharmacy, “Vasile Goldis” Western University of Arad, Romania; Adina Frum - “Lucian Blaga” University of Sibiu, Romania; Ovidiu Tita - “Lucian Blaga” University of Sibiu, Romania; Carmen Neamtu - “Vasile Goldis” Western University of Arad, Romania; Zsombor Szoke-Kovacs - University of Debrecen, Hungary; Zoltan Cziaky - University of Nyiregyhaza, Hungary; Endre Mathe -University of Debrecen, Hungary | C17: FSAA2 | D17: Antioxidants | E17: 9 | F17: 11 | G17: (ISSN 2076-3921 | H17: https://www.mdpi.com/2076-3921/9/11/1067 | I17: https://doi.org/10.3390/antiox9111067 | J17: WOS:000592780600001 | K17: 1-33 | L17: 2020 | M17: Q1 | N17: 5.014 | O17: 1500 | P17: 187.5 | Q17: Tita Ovidiu
A18: Use of Yoghurt Enhanced with Volatile Plant Oils Encapsulated in Sodium Alginate to Increase the Human Body’s Immunity in the Present Fight Against Stress | B18: Ovidiu Tița- “Lucian Blaga” University of Sibiu, 550012 Sibiu, Romania; Maria Adelina Constantinescu - “Lucian Blaga” University of Sibiu, 550012 Sibiu, Romania; Mihaela Adriana Tița - “Lucian Blaga” University of Sibiu, 550012 Sibiu, Romania;Cecilia Georgescu - “Lucian Blaga” University of Sibiu, 550012 Sibiu, Romania; | C18: FSAA2 | D18: International Journal of Environmental Research and Public Health | E18: 17 | F18: 20 | H18: https://www.mdpi.com/1660-4601/17/20/7588 | I18: https://doi.org/10.3390/ijerph17207588 | J18: WOS:000585597700001 | L18: 2020 | M18: Q1 | N18: 2.849 | O18: 1500 | P18: 375 | Q18: Tita Ovidiu
A61: TOTAL | P61: =SUM(P11:P60) -> 3833.33
A63: Informațiile incomplete / incorecte vor conduce la neluarea în calcul a indicatorului respectiv

Sheet I.2
A2: I.2- Articol în revistă cotată WoS: SCIS, SSCI – „zona gri”/ Q3, Q4 şi respectiv AHCI < 5 ani, conform listelor UEFISCDI
A4: Articole încadrate “document type” ca “Article” sau „Review” în reviste cotate WoS TR - Web of Science Thomson Reuters (SCIE - Science Citation Index Expanded şi SSCI - Social Sciences Citation Index, din ”zona gri”/ Q3, Q4, în conformitate cu Lista UEFISCDI a revistelor încadrate pe subdomenii ştiinţifice, respectiv în reviste AHCI - Arts & Humanities Citation Index cu o vechime mai mică de 5 ani în Web of Science Core Collection.
A5: Articolul trebuie publicat în anul de raportare şi să fie vizibil în Web of Science Core Collection din platforma www.webofknowledge.com
A6: Listele de referință UEFISCDI sunt cele din anul anterior raportării și sunt disponibile pe site-ul https://uefiscdi.ro/scientometrie-reviste. În cazul în care o revistă este încadrată în mai multe subdomenii, se ia în calcul încadrarea cea mai favorabilă.
A7: Articolul trebuie să conţină menţiunea afilierii la ULBS a declarantului.
A8: * Punctaje de referință: • Articol = 500 de puncte Punctajul se împarte la numărul de autori cu afiliere la instituţiile de învăţământ şi cercetare din România, inclusiv la doctoranzi / studenţi. Punctajul NU se împarte cu autorii din străinătate sau cu autorii din mediul de afaceri (pentru acești autori se menţionează în paranteză instituţia de proveniență).
A10: Titlul articolului | B10: Numele și prenumele autorilor (afilierea) | C10: Cod departament | D10: Titlul revistei | E10: Volum | F10: Număr | G10: ISSN revistă | H10: Link către articol pe site - ul revistei | I10: DOI articol (Digital object identifier) | J10: WOS Accession Number | K10: Paginile articolului (de la … până la …) | L10: Anul publicării | M10: Tipul revistei zona gri /Q3, Q4; AHCI<5ani) | N10: Factor de impact | O10: Punctaj de referință* | P10: Punctaj individual | Q10: Numele și prenumele Declarant
A11: Lovastatin effects on indirect somatic embryogenesis of petunia | B11: Antofie MM (ULBS) Mitoi ME (IBB) | C11: FSAA2 | D11: ROMANIAN BIOTECHNOLOGICAL LETTERS | E11: 25 | F11: 5 | G11: 1224-5984 | H11: https://www.e-repository.org/rbl/vol.25/iss.5/4.pdf | I11: 10.25083/rbl/25.5/1886.1891 | J11: WOS:000571493000004 | K11: 1886-1891 | L11: 2020 | M11: Q4 | N11: 0.765 | O11: 500 | P11: =O11/2 -> 250 | Q11: Antofie Mihaela
A12: AN ENZYME-ENHANCED EXTRACTION OF ANTHOCYANINS FROM RED CABBAGE AND THEIR THERMAL DEGRADATION KINETICS | B12: Tecucianu A-C, Drăghici O., Oancea S. | D12: Acta Alimentaria | E12: 49 | F12: 2 | G12: 0139-3006 | H12: https://akjournals.com/view/journals/066/49/2/article-p204.xml | I12: doi.org/10.1556/066.2020.49.2.10 | J12: WOS:000590169700010 | K12: 204–213 | L12: 2020 | M12: Q4 | N12: 0.547 | O12: 500 | P12: 166.67 | Q12: Draghici Olga
A13: Effects of roselle extract on the oxidative stability of hempseed oil | B13: Simona oancea – olga Drăghici – mirabela Perju – FranciSc V. DulF | D13: Journal of Food and Nutrition Research | E13: 59 | F13: 2 | G13: 1336-8672 | H13: http://www.vup.sk/en/download.php?bulID=2058 | J13: WOS:000541970600002 | K13: 98-107 | L13: 2020 | M13: Q4 | N13: 0.756 | O13: 500 | P13: =O13/4 -> 125 | Q13: Draghici Olga
A14: Sustainable resource management, the source of production integration, biodiversity conservation and socio-cultural values in grasway ecosystems. | B14: Iagăru, P. (ULB), Mărcuță, L. (USAMV), Iagăru, R. (ULB), & Mărcuță, A. (USAMV) | C14: FSAA2 | D14: ROMANIAN BIOTECHNOLOGICAL LETTERS, | E14: 25 | F14: (5), | G14: 1984-1991. | H14: https://www.rombio.org/vol.25/iss.5/publications.html | I14: 10.25083/rbl/25.5/1984.1991 | K14: 1984-1991 | L14: (2020). | M14: Q3 | N14: 0.823 | O14: 500 | P14: =O14/4 -> 125 | Q14: Iagaru Pompilica
A15: Sustainable resource management, the source of production integration, biodiversity conservation and socio-cultural values in grasway ecosystems. | B15: Iagăru, P. (ULB), Mărcuță, L. (USAMV), Iagăru, R. (ULB), & Mărcuță, A. (USAMV) | C15: FSAA2 | D15: ROMANIAN BIOTECHNOLOGICAL LETTERS, | E15: 25 | F15: (5), | G15: 1984-1991. | H15: https://www.rombio.org/vol.25/iss.5/publications.html | I15: 10.25083/rbl/25.5/1984.1991 | K15: 1984-1991 | L15: (2020). | M15: Q3 | N15: 0.823 | O15: 500 | P15: =O15/4 -> 125 | Q15: Iagaru Romulus
A16: Development of ultrasonic extracts with strong antioxidant properties from red onion wastes | B16: Oancea Simona, Radu M., Olosutean H. | C16: FSAA2 | D16: Rom. Biotech. Lett. | E16: 25 | F16: 2 | G16: 1224-5984 | H16: https://www.e-repository.org/rbl/vol.25/iss.2/2.pdf | I16: 10.25083/rbl/25.2/1320.1327 | J16: 539565000002 | K16: 1320-1327 | L16: 2020 | M16: Q4 | N16: 0.765 | O16: 500 | P16: =O16/3 -> 166.66667 | Q16: Oancea Simona
A17: Influence of enzyme-aided extraction and ultrasonication on phenolics content and antioxidant activity of Paeonia officinalis L. petals | B17: Oancea Simona, Perju M., Olosutean H. | C17: FSAA2 | D17: J. Serb. Chem. Soc. | E17: 85 | F17: 7 | G17: ISSN 0352-5139 (Print), ISSN 1820-7421 (Online) | H17: https://www.shd-pub.org.rs/index.php/JSCS/article/view/8545/950 | I17: 10.2298/JSC190807120O | J17: 550645700002 | K17: 845-856 | L17: 2020 | M17: Q4 | N17: 1.097 | O17: 500 | P17: =O17/3 -> 166.66667 | Q17: Oancea Simona
A18: Effects of roselle extract on the oxidative stability of hempseed oil | B18: Oancea Simona, Drăghici O., Perju M., Dulf F.V. | C18: FSAA2 | D18: J. Food Nutr. Res. | E18: 59 | F18: 2 | G18: 1336-8672. | H18: https://www.vup.sk/en/index.php?mainID=2&navID=34&version=2&volume=59&article=2180 | J18: 541970600002 | K18: 98-107 | L18: 2020 | M18: Q4 | N18: 0.756 | O18: 500 | P18: =O18/4 -> 125 | Q18: Oancea Simona
A19: An enzyme-enhanced extraction of anthocyanins from red cabbage and their thermal degradation kinetics | B19: Tecucianu A.C., Drăghici O., Oancea Simona | C19: FSAA2 | D19: Acta Alimentaria | E19: 49 | F19: 2 | G19: 0139-3006 | H19: https://akjournals.com/view/journals/066/49/2/article-p204.xml | I19: 10.1556/066.2020.49.2.10 | J19: 590169700010 | K19: 204-213 | L19: 2020 | M19: Q4 | N19: 0.458 | O19: 500 | P19: =O19/3 -> 166.66667 | Q19: Oancea Simona
A20: The impact of anthropogenic activities to the level of some POPs residues in bovine milk from several farms in Romania | B20: Stegarus D.I., Ionete R.E., Oancea Simona, Lengyel E., Frum A. | C20: FSAA2 | D20: Studia Universitatis Babes-Bolyai Chemia | E20: 65 | F20: 4 | G20: 1224-7154 | H20: http://chem.ubbcluj.ro/~studiachemia/issues/chemia2020_4/13Stegarus_159_176.pdf | I20: 10.24193/subbchem.2020.4.13 | J20: 601368800013 | K20: 159-176 | L20: 2020 | M20: Q4 | N20: 0.494 | O20: 500 | P20: =O20/5 -> 100 | Q20: Oancea Simona
A61: TOTAL | P61: =SUM(P11:P60) -> 1516.67
A63: Informațiile incomplete / incorecte vor conduce la neluarea în calcul a indicatorului respectiv

Sheet I.3
A2: I.3 - Articol în revistă din bazele de date Master Journal List (inclusiv Emerging Sources Citation Index - ESCI) şi articol în revistă indexată SCOPUS.
A4: Articole publicate în reviste din bazele de date: Master Journal List , inclusiv in Emerging Sources Citation Index (http://mjl.clarivate.com); SCOPUS (https://www.scopus.com/);
A5: Se consideră doar articole care au încadrarea “document type”: “article” sau “review”
A6: Articolul trebuie publicat în anul de raportare şi să fie vizibil pe platforma www.webofknowledge.com şi / sau pe platforma https://www.scopus.com/
A7: Articolul trebuie să conţină menţiunea afilierii la ULBS a declarantului.
A8: * Punctaje de referință: • Articol = 200 de puncte Punctajul se împarte la numărul de autori cu afiliere la instituţiile de învăţământ şi cercetare din România, inclusiv la doctoranzi / studenţi. Punctajul NU se împarte cu autorii din străinătate sau cu autorii din mediul de afaceri (pentru acești autori se menţionează în paranteză instituţia de proveniență).
A10: Titlul articolului | B10: Numele și prenumele autorilor (afilierea) | C10: Cod departament | D10: Titlul revistei | E10: Volum | F10: Număr | G10: ISSN-ul revistei | H10: Link către articol pe site - ul revistei | I10: DOI articol (Digital object identifier) | J10: WOS Accession Number | K10: Paginile articolului (de la … până la …) | L10: Anul publicării | M10: Punctaj de referință* | N10: Punctaj individual | O10: Numele și prenumele Declarant
A11: DEFINING INDICATORS FOR INVESTIGATING TRADITIONAL HOME-GARDENS IN ROMANIA | B11: Antofie MM (ULBS) | C11: FSAA2 | D11: SCIENTIFIC PAPERS-SERIES MANAGEMENT ECONOMIC ENGINEERING IN AGRICULTURE AND RURAL DEVELOPMENT | E11: 20 | F11: 4 | G11: 2284-7995 | H11: http://www.managementjournal.usamv.ro/pdf/vol.20_4/Art4.pdf | J11: WOS:000598213900004 | K11: 31-37 | L11: 2020 | M11: 200 | N11: 200 | O11: Antofie Mihaela
A12: INDICATORS FOR INVESTIGATING TRADITIONAL HOME-GARDENS IN ROMANIA - CROPS DIVERSITY IN MOSNA COMMUNE, SIBIU COUNTY | B12: Antofie MM, Sava C (ULBS) | C12: FSAA2 | D12: SCIENTIFIC PAPERS-SERIES MANAGEMENT ECONOMIC ENGINEERING IN AGRICULTURE AND RURAL DEVELOPMENT | E12: 20 | F12: 4 | G12: 2284-7995 | H12: http://managementjournal.usamv.ro/pdf/vol.20_4/Art5.pdf | J12: WOS:000598213900005 | K12: 39-47 | L12: 2020 | M12: 200 | N12: =M12/2 -> 100 | O12: Antofie Mihaela
A13: INDICATORS FOR INVESTIGATING TRADITIONAL HOME-GARDENS IN ROMANIA-VINEYRADS, FRUIT TREES AND CULTIVATED SHRUBS DIVERSITY IN MOȘNA COMMUNE, SIBIU COUNTY | B13: Antofie MM, Sava C (ULBS) | C13: FSAA2 | D13: SCIENTIFIC PAPERS-SERIES MANAGEMENT ECONOMIC ENGINEERING IN AGRICULTURE AND RURAL DEVELOPMENT | E13: 20 | F13: 4 | G13: 2284-7995 | H13: http://managementjournal.usamv.ro/pdf/vol.20_4/Art6.pdf | J13: WOS:000598213900006 | K13: 49-56 | L13: 200 | M13: 200 | N13: =M13/2 -> 100 | O13: Antofie Mihaela
A14: THE IMPORTANCE OF THE MELLIFEROUS FLORA FOR THE BEEKEEPING IN GURA RÂULUI COUNTRYSIDE AREA (SIBIU COUNTY), ROMANIA | B14: Antonie Iuliana | C14: FSAA2 | D14: SCIENTIFIC PAPERS-SERIES MANAGEMENT ECONOMIC ENGINEERING IN AGRICULTURE AND RURAL DEVELOPMENT | E14: 20 | F14: 4 | G14: 2284-7995 | H14: http://managementjournal.usamv.ro/pdf/vol.20_4/Art7.pdf | J14: WOS:000598213900007 | K14: 57-63 | L14: 2020 | M14: 200 | N14: 200 | O14: Antonie Iuliana
A15: Integrated control of damages and diseases within the forest ecosystem “miercurea sibiului” (Sibiu, romania) in the conditions of the year 2019 | B15: Stanca-Moise Cristina, Blaj R. | C15: FSAA | D15: Studia Universitatis Vasile Goldis Arad, Seria Stiintele Vietii | E15: 30 | F15: 3 | G15: ISSN: 15842363 | I15: https://www.scopus.com/record/display.uri?eid=2-s2.0-85097296954&origin=resultslist&sort=plf-f&src=s&st1=Stanc%c4%83+Moise&st2=Cristina&nlo=1&nlr=20&nls=count-f&sid=f45579bd40d782c3d8046c814a427337&sot=anl&sdt=aut&sl=43&s=AU-ID%28%22Stanc%c4%83-Moise%2c+Cristina%22+57191645933%29&relpos=0&citeCnt=0&searchTerm= | J15: Scopus | K15: 149-155 | L15: 2020 | M15: 200 | N15: 100 | O15: Blaj Robert
A16: NEW RESEARCH ON THE EVOLUTION OF Lymantria monacha L. (LEPIDOPTERA, LYMANTRIIDAE) IN THE CONDITIONS OF THE YEAR 2019 AND THE CONTROL OF THE PEST POPULATION WITHIN THE MIERCUREA SIBIULUI FOREST RANGE (ROMANIA) | B16: Cristina STANCĂ-MOISE, Robert BLAJ | C16: FSAA | D16: Muzeul Olteniei Craiova. Oltenia. Studii şi comunicări. Ştiinţele Naturii | E16: 36 | F16: 2 | G16: ISSN 1454-6914 | H16: http://olteniastudiisicomunicaristiintelenaturii.ro/v36_2.html | I16: http://olteniastudiisicomunicaristiintelenaturii.ro/cont/36_2/III.%20ANIMAL%20BIOLOGY%20III.a.%20INVERTEBRATES%20VARIOUS/12Moise.pdf | J16: ZOOR | K16: 84-90 | L16: 2020 | M16: 200 | N16: 100 | O16: Blaj Robert
A17: CONTROL OF THE Hylobius abietis L. (COLEOPTERA: CURCULIONIDAE) PEST DURING 2010-2019, WITHIN THE MIERCUREA SIBIULUI FOREST DISTRICT | B17: Cristina STANCĂ-MOISE, Robert BLAJ | C17: FSAA | D17: Muzeul Olteniei Craiova. Oltenia. Studii şi comunicări. Ştiinţele Naturii | E17: 36 | F17: 1 | G17: ISSN 1454-6914 | H17: http://olteniastudiisicomunicaristiintelenaturii.ro/v36_2.html | I17: http://olteniastudiisicomunicaristiintelenaturii.ro/cont/36_1/III.%20ANIMAL%20BIOLOGY%20III.a.%20INVERTEBRATES%20VARIOUS/9StancaMoise.pdf | J17: ZOOR | K17: 73-77 | L17: 2020 | M17: 200 | N17: 100 | O17: Blaj Robert
A18: THE MAIN CHARACTERISTICS OF AGRICULTURE AND RURAL DEVELOPMENT IN THE CENTRAL REGION OF ROMANIA | B18: Cărătuș Stanciu Mirela | C18: FSAA2 | D18: Scientific Papers-Series Management Economic Engineering in Agriculture and Rural Development | E18: 20 | F18: 4 | G18: 2284-7995 | H18: http://managementjournal.usamv.ro/pdf/vol.20_4/Art17.pdf | J18: 598213900017 | K18: 131-138 | L18: 2020 | M18: 200 | N18: 200 | O18: Caratus Mirela
A19: RESEARCH REGARDING YOUNGER CONSUMERS ATTITUDE, IN RELATION WITH SHEEP MEAT CONSUMPTION | B19: Cărătuș Stanciu Mirela | C19: FSAA2 | D19: Scientific Papers-Series Management Economic Engineering in Agriculture and Rural Development | E19: 20 | F19: 4 | G19: 2284-7995 | H19: http://managementjournal.usamv.ro/pdf/vol.20_4/Art16.pdf | J19: 598213900016 | K19: 125-130 | L19: 2020 | M19: 200 | N19: 200 | O19: Caratus Mirela
A20: TRENDS AND CHANGES IN TOURIST FLOW IN ROMANIA IN THE PERIOD 2009-2018 | B20: Popescu Agatha, Hontuș Adelaida Cristina, Cărătuș Stanciu Mirela | C20: FSAA2 | D20: Scientific Papers-Series Management Economic Engineering in Agriculture and Rural Development | E20: 20 | F20: 1 | G20: 2284-7995 | H20: http://managementjournal.usamv.ro/pdf/vol.20_1/Art56.pdf | J20: 521743100056 | K20: 425-436 | L20: 2020 | M20: 200 | N20: 67 | O20: Caratus Mirela
A21: RESEARCH REGARDING CONSUMERS ATTITUDE, IN RELATION WITH POULTRY MEAT PURCHASE AND CONSUMPTION. CASE STUDY SIBIU, ROMANIA | B21: Cărătuș Stanciu Mirela | C21: FSAA2 | D21: Scientific Papers-Series Management Economic Engineering in Agriculture and Rural Development | E21: 20 | F21: 1 | G21: 2284-7995 | H21: http://managementjournal.usamv.ro/pdf/vol.20_1/Art17.pdf | J21: 521743100017 | K21: 125-130 | L21: 2020 | M21: 200 | N21: 200 | O21: Caratus Mirela
A22: RESEARCH ON GROWTH INDICATORS IN ABERDEEN ANGUS YOUTH CATTLE, ACCORDING TO DIFFERENT INFLUENCING FACTORS | B22: I. T.GOCIMAN, G.E.MĂRGINEAN, S. BĂRĂITĂREANU, Mirela Aurora CĂRĂTUȘ, Livia VIDU | C22: FSAA2 | D22: Scientific Papers. Series D. Animal Science | F22: 2 | G22: 2285-5750 | H22: http://animalsciencejournal.usamv.ro/pdf/2020/issue_1/Art46.pdf | J22: 574608500046 | K22: 319-324 | L22: 2020 | M22: 200 | N22: 40 | O22: Caratus Mirela
A23: STUDY ON A BETTER MANAGEMENT IN A MODERN FARM USING DIFFERENT FUELS FOR TRACTOR ENGINES | B23: Dumitru Mariana | C23: FSAA2 | D23: Lucrări Ştiinţifice Management AGRICOL | E23: Scientific Papers Series Management, Economic Engineering in Agriculture and Rural Development | F23: Vol. 20, Issue 4 | G23: PRINT ISSN 2284-7995, E-ISSN 2285-3952 | H23: http://managementjournal.usamv.ro/pdf/vol.20_4/Art.21.pdf | I23: - | J23: 503074300011 | K23: 161-164 | L23: 2020 | M23: 200 | N23: 200 | O23: Dumitru Mariana
A24: DEVELOPMENT AND ANALYSIS OF FRUIT BEVERAGES WITH ANTIOXIDANT PROPERTIES | B24: Solomatina E.A., Solomatin N.M., Michurinsk State Agr Univ Russia, Sorokopudov V.N., Sorokopudova O.A., Russian State Agr Univ, Hort & Landscape Engn, Russia Myachikova N.I., Frum A., Belogorode State University, Russia, Georgescu C. Lucian Blaga University of Sibiu | C24: FSAA2 | D24: Scientific Study & Research Chemistry & Chemical Engineering, Biotechnology, Food Industry | E24: 21 | F24: 4 | G24: ISSN 1582-540X | H24: http://pubs.ub.ro/?pg=revues&rev=cscc6&num=202004&vol=4&aid=5195 | I24: CSCC6202004V04S01A0010 | J24: WOS:000596118000010 | K24: 555-561 | L24: 2020 | M24: 200 | N24: 100 | O24: Georgescu Cecilia
A25: THE RELATIONSHIP BETWEEN DEMOGRAPHY AND THE DEVELOPMENT OF SMART CITY. CASE STUDY-BUCHAREST. | B25: MARCUTA, L. (USAMV), MARCUTA, A. (USAMV), IAGARU, P.(ULB), IAGARU, R.(ULB), & DIMEN, L. (UAB) | C25: FSAA2 | D25: Scientific Papers: Management, Economic Engineering in Agriculture & Rural Development | E25: 20 | F25: 1 | G25: 2284-7995 / 2285-3952 | H25: http://managementjournal.usamv.ro/index.php/scientific-papers/85-vol-20-issue-1?start=60 | K25: 235-239 | L25: (2020). | M25: 200 | N25: =M25/5 -> 40 | O25: Iagaru Pompilica
A26: THE RELATIONSHIP BETWEEN DEMOGRAPHY AND THE DEVELOPMENT OF SMART CITY. CASE STUDY-BUCHAREST. | B26: MARCUTA, L. (USAMV), MARCUTA, A. (USAMV), IAGARU, P.(ULB), IAGARU, R.(ULB), & DIMEN, L. (UAB) | C26: FSAA2 | D26: Scientific Papers: Management, Economic Engineering in Agriculture & Rural Development | E26: 20 | F26: 1 | G26: 2284-7995 / 2285-3952 | H26: http://managementjournal.usamv.ro/index.php/scientific-papers/85-vol-20-issue-1?start=60 | K26: 235-239 | L26: (2020). | M26: 200 | N26: =M26/5 -> 40 | O26: Iagaru Romulus
A27: Differences Of The Physicochemical Indicators Of Beverages Wild Elderflower (Sambucus Nigra) From Teleajen Valley, Romania, According To The Used Technology | B27: Iancu Maria Lidia | C27: FSAA2 | D27: CARPATHIAN JOURNAL OF FOOD SCIENCE AND TECHNOLOGY | E27: 12 | F27: 3 | G27: Print: ISSN 2066-6845 Online ISSN-L 2344-5459 ISSN-L 2066-6845 | H27: http://chimie-biologie.ubm.ro/carpathian_journal/Vol_12(3)_2020.pdf | I27: https://doi.org/10.34302/crpjfst/2020.12.3.16 | J27: WOS:000579506300016 | K27: 192-200 | L27: 2020 | M27: 200 | N27: 200 | O27: Iancu Maria
A28: Advanced identification and quantification of pesticide residues in vegetables by GC-ToFMS technique | B28: Diana Ionela Stegarus, Roxana Elena Ionete, Ecaterina Lengyel, Marius Gheorghe Miricioiu, | C28: FSAA2 | D28: Rev. Chimie | E28: 71 | F28: 4 | G28: 2668-8212 | H28: https://revistadechimie.ro/pdf/23%20STEGARUS%204%2020.pdf | I28: https://doi.org/10.37358/RC.20.4.8060, | J28: https://www.scopus.com/authid/detail.uri?authorId=14043732700 | K28: 220-229 | L28: 2020 | M28: 200 | N28: 50 | O28: Lengyel Ecaterina
A29: USE OF THE CROP CIRCLE ACS-430 DEVICE FOR IDENTIFYING THE NDVI GREEN INDEX IN A CORN CULTURE IN SIBIU COUNTY, ROMANIA | B29: Moise George | C29: FSAA | D29: Muzeul Olteniei Craiova. Oltenia. Studii şi comunicări. Ştiinţele Naturii | E29: 36 | F29: 2 | G29: ISSN 1454-6914 | H29: http://olteniastudiisicomunicaristiintelenaturii.ro/v36_2.html | I29: http://olteniastudiisicomunicaristiintelenaturii.ro/cont/36_1/III.%20ANIMAL%20BIOLOGY%20III.a.%20INVERTEBRATES%20VARIOUS/9StancaMoise.pdf | J29: ZOOR | K29: 57-62 | L29: 2020 | M29: 200 | N29: 200 | O29: Moise George
A30: MONITORING AND CONTROL OF THE DEFOLIATOR POPULATION Lymantria monacha (L., 1758) WITHIN THE FORESTRY FIELD RASINARI (SIBIU, ROMANIA). | B30: Stanca-Moise Cristina, BRERETON Tom | C30: FSAA | D30: Analele Universitatii din Oradea Fascicula Biologie | E30: 27 | F30: 1 | G30: ISSN:1224-5119 | H30: https://www.bioresearch.ro/2020-1/027-031-AUOFB.27.1.2020-STANCA-MOISE.C.-Monitoring.and.control.pdf | I30: https://apps.webofknowledge.com/full_record.do?product=UA&search_mode=GeneralSearch&qid=1&SID=C6kumWLc1BlEpwHfUok&page=1&doc=1 | J30: ZOOR15611077348 | K30: 27-31 | L30: 2020 | M30: 200 | N30: 200 | O30: Moise Cristina
A31: YIELD POTENTIAL AND STABILITY OF SOME SPRING BARLEY VARIETIES AND LINES | B31: Russu, FM; Porumb, I; Urda, CA ; Filip, E; Stanca-Moise, C; Varadi, A; Vasilescu, L; Petcu, E. | C31: FSAA | D31: SCIENTIFIC PAPERS-SERIES MANAGEMENT ECONOMIC ENGINEERING IN AGRICULTURE AND RURAL DEVELOPMENT | E31: 20 | F31: 1 | G31: ISSN: 2284-7995 | H31: http://managementjournal.usamv.ro/pdf/vol.20_1/Art65.pdf | I31: https://apps.webofknowledge.com/full_record.do?product=UA&search_mode=GeneralSearch&qid=1&SID=C6kumWLc1BlEpwHfUok&page=1&doc=2 | J31: WOS:000521743100065 | K31: 533-538 | L31: 2020 | M31: 200 | N31: 25 | O31: Moise Cristina
A32: Integrated control of damages and diseases within the forest ecosystem “miercurea sibiului” (Sibiu, romania) in the conditions of the year 2019 | B32: Stanca-Moise Cristina, Blaj R. | C32: FSAA | D32: Studia Universitatis Vasile Goldis Arad, Seria Stiintele Vietii | E32: 30 | F32: 3 | G32: ISSN: 15842363 | I32: https://www.scopus.com/record/display.uri?eid=2-s2.0-85097296954&origin=resultslist&sort=plf-f&src=s&st1=Stanc%c4%83+Moise&st2=Cristina&nlo=1&nlr=20&nls=count-f&sid=f45579bd40d782c3d8046c814a427337&sot=anl&sdt=aut&sl=43&s=AU-ID%28%22Stanc%c4%83-Moise%2c+Cristina%22+57191645933%29&relpos=0&citeCnt=0&searchTerm= | J32: Scopus | K32: 149-155 | L32: 2020 | M32: 200 | N32: 100 | O32: Moise Cristina
A33: FOREST AND AGRICULTURAL ECOSYSTEMS PESTS (LEPIDOPTERA), PRESERVED IN THE ENTOMOLOGICAL COLLECTIONS OF THE NATURAL HISTORY MUSEUM IN SIBIU (ROMANIA) | B33: Cristina STANCĂ-MOISE | C33: FSAA | D33: Analele Universitatii din Oradea Fascicula Biologie | E33: 27 | F33: 2 | G33: ISSN: 1224-5119 | H33: https://www.bioresearch.ro/2020-2.html | I33: https://www.bioresearch.ro/2020-2/224-232-AUOFB.27.2.2020-STANCA-MOISE.C-Forest.and.agricultural.pdf | J33: ZOOR | K33: 224-232 | L33: 2020 | M33: 200 | N33: 200 | O33: Moise Cristina
A34: NEW RESEARCH ON THE EVOLUTION OF Lymantria monacha L. (LEPIDOPTERA, LYMANTRIIDAE) IN THE CONDITIONS OF THE YEAR 2019 AND THE CONTROL OF THE PEST POPULATION WITHIN THE MIERCUREA SIBIULUI FOREST RANGE (ROMANIA) | B34: Cristina STANCĂ-MOISE, Robert BLAJ | C34: FSAA | D34: Muzeul Olteniei Craiova. Oltenia. Studii şi comunicări. Ştiinţele Naturii | E34: 36 | F34: 2 | G34: ISSN 1454-6914 | H34: http://olteniastudiisicomunicaristiintelenaturii.ro/v36_2.html | I34: http://olteniastudiisicomunicaristiintelenaturii.ro/cont/36_2/III.%20ANIMAL%20BIOLOGY%20III.a.%20INVERTEBRATES%20VARIOUS/12Moise.pdf | J34: ZOOR | K34: 84-90 | L34: 2020 | M34: 200 | N34: 100 | O34: Moise Cristina
A35: CONTROL OF THE Hylobius abietis L. (COLEOPTERA: CURCULIONIDAE) PEST DURING 2010-2019, WITHIN THE MIERCUREA SIBIULUI FOREST DISTRICT | B35: Cristina STANCĂ-MOISE, Robert BLAJ | C35: FSAA | D35: Muzeul Olteniei Craiova. Oltenia. Studii şi comunicări. Ştiinţele Naturii | E35: 36 | F35: 1 | G35: ISSN 1454-6914 | H35: http://olteniastudiisicomunicaristiintelenaturii.ro/v36_2.html | I35: http://olteniastudiisicomunicaristiintelenaturii.ro/cont/36_1/III.%20ANIMAL%20BIOLOGY%20III.a.%20INVERTEBRATES%20VARIOUS/9StancaMoise.pdf | J35: ZOOR | K35: 73-77 | L35: 2020 | M35: 200 | N35: 100 | O35: Moise Cristina
A36: Immunostimulatory potential of natural compounds and extracts: a review | B36: Stroe A.C., Oancea Simona | C36: FSAA2 | D36: Current Nutrition & Food Science | E36: 16 | F36: 4 | G36: ISSN: 2212-3881 (Online); ISSN: 1573-4013 (Print). | H36: https://www.eurekaselect.com/170390/article | I36: 10.2174/1573401315666190301154200 | J36: WOS:000550991000003 | K36: 444-454 | L36: 2020 | M36: 200 | N36: =M36/2 -> 100 | O36: Oancea Simona
A37: Thermochemical decomposition of sewage sludge - An eco-friendly solution for a sustainable energy future by using wastes | B37: Zaharioiu A., Bucura F., Ionete E.I., Ionete R.E., Ebrasu D., Sandru C., Marin F., Oancea Simona, Niculescu V., Miricioiu M.G., Constantinescu M. | C37: FSAA2 | D37: Rev. Chim. | E37: 71 | F37: 10 | G37: 0034-7752 | H37: https://revistadechimie.ro/pdf/17%20ZAHAROIU%2010%2020.pdf | I37: 10.37358/RC.20.10.8361 | J37: https://www.scopus.com/authid/detail.uri?authorId=6603658504 | K37: 171–181 | L37: 2020 | M37: 200 | N37: 18.18 | O37: Oancea Simona
A38: A historical perspective of food and medicinal uses of antioxidants from natural sources | B38: Tecucianu A.C., Oancea Simona | C38: FSAA2 | D38: Acta Musei Brukenthal | E38: 15 | F38: 3 | G38: 1842-2691 | H38: http://www.brukenthalmuseum.ro/pdf/BAM/BAM%20XV3.pdf | I38: https://www.scopus.com/sources.uri | J38: http://www.brukenthalmuseum.ro/publicatii_en/01.htm | K38: 511-524 | L38: 2020 | M38: 200 | N38: =M38/2 -> 100 | O38: Oancea Simona
A39: An overview on edible mushrooms with health benefits and applications in the food industry | B39: Popa-Vecerdea F.M., Oancea Simona | C39: FSAA2 | D39: Acta Musei Brukenthal | E39: 15 | F39: 3 | G39: 1842-2691 | H39: http://www.brukenthalmuseum.ro/pdf/BAM/BAM%20XV3.pdf | I39: https://www.scopus.com/sources.uri | J39: http://www.brukenthalmuseum.ro/publicatii_en/01.htm | K39: 525-536 | L39: 2020 | M39: 200 | N39: =M39/2 -> 100 | O39: Oancea Simona
A40: Influence of enzymatic and ultrasonic extraction on phenolics content and antioxidant activity of Hibiscus sabdariffa L. flowers | B40: Oancea Simona, Perju M. | C40: FSAA2 | D40: Bulgarian Chemical Communications | E40: 52 | F40: D | G40: 0324-1130 | H40: http://www.bcc.bas.bg/ | I40: https://www.scopus.com/sources.uri | K40: 25-29 | L40: 2020 | M40: 200 | N40: =M40/2 -> 100 | O40: Oancea Simona
A41: INDICATORS FOR INVESTIGATING TRADITIONAL HOME-GARDENS IN ROMANIA - CROPS DIVERSITY IN MOSNA COMMUNE, SIBIU COUNTY | B41: Antofie MM, Sava C (ULBS) | C41: FSAA2 | D41: SCIENTIFIC PAPERS-SERIES MANAGEMENT ECONOMIC ENGINEERING IN AGRICULTURE AND RURAL DEVELOPMENT | E41: 20 | F41: 4 | G41: 2284-7995 | H41: http://managementjournal.usamv.ro/pdf/vol.20_4/Art5.pdf | J41: WOS:000598213900005 | K41: 39-47 | L41: 2020 | M41: 200 | N41: =M41/2 -> 100 | O41: Sava Camelia
A42: INDICATORS FOR INVESTIGATING TRADITIONAL HOME-GARDENS IN ROMANIA-VINEYRADS, FRUIT TREES AND CULTIVATED SHRUBS DIVERSITY IN MOȘNA COMMUNE, SIBIU COUNTY | B42: Antofie MM, Sava C (ULBS) | C42: FSAA2 | D42: SCIENTIFIC PAPERS-SERIES MANAGEMENT ECONOMIC ENGINEERING IN AGRICULTURE AND RURAL DEVELOPMENT | E42: 20 | F42: 4 | G42: 2284-7995 | H42: http://managementjournal.usamv.ro/pdf/vol.20_4/Art6.pdf | J42: WOS:000598213900006 | K42: 49-56 | L42: 200 | M42: 200 | N42: =M42/2 -> 100 | O42: Sava Camelia
A43: How To Use Production Functions Characteristics Of Economic Processes In Agriculture. Physical (Technical) Functions, | B43: Simtion Daniela | C43: FSAA2 | D43: Scientific Papers Series Management, Economic Engineering in Agriculture and Rural Development, | E43: Vol. 20, | F43: Issue 4, | G43: ISSN 2284-7995, 2020, | H43: http://managementjournal.usamv.ro/pdf/vol.20_4/Art56.pdf, | J43: 000598213900056 | K43: 487-490 | L43: 2020 | M43: 200 | N43: 200 | O43: Simtion Daniela
A44: Legal Tax Evasion Through Stock Exchange Games, | B44: Simtion Daniela | C44: FSAA2 | D44: Scientific Papers Series Management, Economic Engineering in Agriculture and Rural Development, | E44: Vol. 20, | F44: Issue 4, | G44: ISSN 2284-7995, 2020, | H44: http://managementjournal.usamv.ro/pdf/vol.20_4/Art57.pdf | J44: 000598213900057 | K44: 491-494 | L44: 2020 | M44: 200 | N44: 200 | O44: Simtion Daniela
A45: Biological active compounds from native food sources for fermented dairy products | B45: Mihaela TIŢA (ULBS),Cristina POPOVICI(Technical University of Moldova, Republica Moldova, Loreta TAMOŠAITIENE( Klaipeda State University of Applied Sciences, Lithuania), Vijole Bradauskiene ( Klaipeda State University of Applied Sciences, Lithuania) | C45: FSAA2 | D45: Ukrainian Food Journal | E45: 9 | F45: 1 | G45: 2304-974X | H45: http://ufj.ho.ua/Archiv/UKRAINIAN%20FOOD%20JOURNAL%202020%20V.9%20Is.1.pdf | I45: DOI:10.24263/2304-974X-2020-9-1-4 | J45: WOS:000528264700002 | K45: p.36-46. | L45: 2020 | M45: 200 | N45: 200 | O45: Tita Mihaela
A46: Effect of chufa flour addition on characteristics of yoghurt quality | B46: Ovidiu Tița, Cristina Popovici, Loreta Tamošaitienė, Vijole Bradauskiene, Mihaela Adriana Tita, | C46: FSAA2 | D46: Ukrainian Food Journal | E46: 9 | F46: 3 | G46: 2304-974X | H46: http://www.ufj.ho.ua/Archiv/UKRAINIAN%20FOOD%20JOURNAL%202020%20V.9%20Is.3.pdf#page=128 | I46: DOI:10.24263/2304-974X-2020-9-3-11 | J46: WOS:000590975900009 | K46: 624-635 | L46: 2020 | M46: 200 | N46: 100 | O46: Tita Mihaela
A47: Effect of chufa flour addition on characteristics of yoghurt quality | B47: Ovidiu Tița- Lucian Blaga University of Sibiu, Sibiu, Romania; Cristina Popovici- Technical University of Moldova, Chisinau, Moldova; Loreta Tamošaitienė - Klaipeda State University of Applied Sciences, Klaipeda, Lithuania; Vijole Bradauskiene- Kaunas University of Technologie, Food Institute, Kaunas, Lithuania; Mihaela Adriana Tița - Lucian Blaga University of Sibiu, Sibiu, Romania | C47: FSAA2 | D47: Ukrainian Food Journal | E47: 9 | F47: 3 | G47: ISSN 2313–5891 (Online) ISSN 2304–974X (Print) | H47: http://www.ufj.ho.ua/Archiv/UKRAINIAN%20FOOD%20JOURNAL%202020%20V.9%20Is.3.pdf#page=128 | I47: DOI: 10.24263/2304- 974X-2020-9-3-11 | K47: 624-635 | L47: 2020 | M47: 200 | N47: 100 | O47: Tita Ovidiu
A58: TOTAL | N58: =SUM(N11:N57) -> 4580.18
A60: Informațiile incomplete / incorecte vor conduce la neluarea în calcul a indicatorului respectiv

Sheet I.4
A2: I.4 - Articol în volum de conferinţă (proceedings) indexat Conference Proceeding Citation Index - CPCI; alte tipuri de publicaţii din WoS
A4: Pentru anul raportării, dacă volumul conferinţei nu a fost încă indexat, pot fi raportate lucrări doar dacă se face dovada indexării volumelor anterioare ale conferinţei (cel puțin una din ultimele două ediții ale conferinței trebuie să fie vizibile WoS).
A5: La acest indicator se punctează şi articolele în reviste indexate WoS sau în reviste din baza de date Master Journal List care nu se încadrează in document type ca „article” sau „review”.
A6: Articolul trebuie să conţină menţiunea afilierii la ULBS a declarantului.
A7: * Punctaje de referință: • Articol = 100 de puncte Punctajul se împarte la numărul de autori cu afiliere la instituţiile de învăţământ şi cercetare din România, inclusiv la doctoranzi / studenţi. Punctajul NU se împarte cu autorii din străinătate sau cu autorii din mediul de afaceri (pentru acești autori se menţionează în paranteză instituţia de proveniență).
A9: Titlul articolului | B9: Tipul articolulului (articol, abstract, book review, letter, etc.) | C9: Numele și prenumele autorilor (afilierea) | D9: Cod Departament | E9: Titlul conferinței / Titlul volumului / Titlul revistei | F9: ISSN / ISBN | G9: Paginile articolului (de la … pana la …) | H9: DOI articol (Digital object identifier) | I9: WOS Accession Number | J9: Site www al conferinței | K9: Anul publicării | L9: Punctaj de referință* | M9: Punctaj individual | N9: Numele și prenumele Declarant
A10: PUBLIC OPINION AND PUBLIC FOREST MANAGEMENT POLICIES IN THE CONTEXT OF COVID-19 | B10: Articol | C10: Bratu I.A. (Univ."Lucian Blaga"), Dincă L. (INCDS) | D10: FSAA2 | E10: Review of Management and Economic Engineering | J10: http://conference.rmee.org/ | K10: 2020 | L10: 100 | M10: 50 | N10: Bratu Alexandru
A12: Overcoming the barriers of consignment stock policy implementation in a manufacturing company | B12: articol | C12: M. Faur, A. Sipos, C. Bungau and C.I. Gherghea | D12: FSAA2 | E12: Annual Session of Scientific Papers - IMT Oradea 2020, IOP Conf. Series: Materials Science and Engineering | F12: - | G12: - | H12: 10.1088/1757-899X/898/1/012026 | I12: - | J12: https://imt.uoradea.ro/conference/Proceedings_2020.pdf, https://iopscience.iop.org/issue/1757-899X/898/1 | K12: 2020 | L12: 100 | M12: =100/4 -> 25 | N12: Sipos Anca
A13: Balneary Tourism, a Chance for Sustainable Regional Development | B13: ULBS | C13: Nicula V. (ULBS), Spânu Simona (ULBS) | D13: FSAA2 | E13: Organizations and Performance in a Complex World | F13: ISBN 978-3-030-50676-6 | G13: 205-216 | H13: https://www.springer.com/gp/book/9783030506759 | J13: www.iecs | K13: 2020 | L13: 100 | M13: 50 | N13: Spanu Simona
A60: TOTAL | M60: =SUM(M10:M59) -> 125
A62: Informațiile incomplete / incorecte vor conduce la neluarea în calcul a indicatorului respectiv

Sheet I.5
A2: I.5 - Publicaţii BDI şi publicaţii ERIH PLUS
A4: Se raportează articolele şi recenziile publicate in reviste indexate BDI – baze de date internaţionale, inclusiv revistele indexate ERIH PLUS (https://dbh.nsd.uib.no/publiseringskanaler/erihplus/).
A5: Se raportează doar articolele şi recenziile, nu şi rezumatele.
A6: Nu se raportează articole de tip Conference Paper.
A7: * Punctaje de referință: • Articol = 70 de puncte • Recenzie = 25 de puncte Punctajul se împarte la numărul de autori cu afiliere la instituţiile de învăţământ şi cercetare din România, inclusiv la doctoranzi / studenţi. Punctajul NU se împarte cu autorii din străinătate sau cu autorii din mediul de afaceri (pentru acești autori se menţionează în paranteză instituţia de proveniență).
A9: Titlul articolului | B9: Numele și prenumele autorilor (afilierea) | C9: Cod Departament | D9: Titlul revistei | E9: Volumul | F9: Numarul | G9: ISSN / ISBN | H9: Anul publicării | I9: Paginile articolului (de la … până la …) | J9: Baza de date în care este indexată revista | K9: Link către articol | L9: Punctaj de referință* | M9: Punctaj individual | N9: Numele și prenumele Declarant
A10: Assessment of the Distribution and Characteristics of the Oldest Forest Stand from the Romanian's Western Plain. | B10: Dincă L. (INCDS), Bratu I.A. (Univ."Lucian Blaga") | C10: FSAA2 | D10: Bulletin of the University of Agricultural Sciences & Veterinary Medicine Cluj-Napoca. Animal Science & Biotechnologies | E10: 77 | F10: 2 | G10: 1843-5246 | H10: 2020 | I10: 9-14 | J10: EBSCO, CABI | K10: http://journals.usamvcluj.ro/index.php/agriculture/article/view/13917 | L10: 70 | M10: 35 | N10: Bratu Alexandru
A11: Contributions to the Characterization of Forest Soils from Calarasi County | B11: Dincă L. (INCDS), Bratu I.A. (Univ."Lucian Blaga") | C11: FSAA2 | D11: JOURNAL of Horticulture, Forestry and Biotechnology | E11: 24 | F11: 1 | G11: 2066-1797 | H11: 2020 | I11: 46-49 | J11: IndexCopernicus, CABI | K11: https://drive.google.com/file/d/11xMACfg7Qp4rueZkbcwL70dtmC0hQIwR/view?usp=sharing | L11: 70 | M11: 35 | N11: Bratu Alexandru
A12: Study of awareness of food labeling among consumers in North-West Russia | B12: Mark Shamtsyan, Boris Kolesnikov, Mikhail Pushkarev - SIT-Russia, Liviu Gaceu, Oana Bianca Oprea Universitatea Transilvania din Brasov, Iulia Iatco rep Moldova, Dumitru Mnerie, Gabriela Mnerie Timisoara, Ovidiu Tita, Mihaela Tita, Cecilia Georgescu, Monica Mironescu, -ULBS, Stefan Stefanov and Stanka Damianova, Bulgaria | C12: FSAA2 | D12: E3S Web of Conf. International Scientific Conference on Biotechnology and Food Technology (BFT-2020) | E12: 215 | G12: eISSN: 2267-1242 | H12: 2020 | I12: 1-8 | J12: - Google Scholar - EDP Sciences database | K12: 10.1051/e3sconf/202021501002 | L12: 70 | M12: 8.75 | N12: Georgescu Cecilia
A13: STRATEGIC MANAGEMENT OF SUSTAINABLE VALORIZATION OF ENDOGENIC RESOURCES IN GUȘOENI COMMUNE, VÂLCEA COUNTY. | B13: Nicolae, Concioiu (UCV); Romulus, Iagăru (ULB) | C13: FSAA2 | D13: Annals of the University of Craiova, Economic Sciences Series | E13: 20 | F13: 2 | G13: 1223-365X | H13: 2020 | I13: 63-70 | J13: RePEC, EBSCO, DOAJ and CEEOL | K13: http://feaa.ucv.ro/annals/v1_2020/006.pdf | L13: 70 | M13: =L13/2 -> 35 | N13: Iagaru Romulus
A14: Identification and quantification of total polyphenols in musts and aromatic and semiaromatic wines | B14: Ioana Rebenciuc, Ecaterina Lengyel, Diana Ionela Stegăruș, Petru Alexe, Anamaria Călugăr | C14: FSAA2 | D14: AAB BIOFLUX | E14: 12 | F14: 3 | G14: 2067-6352 | H14: 2020 | I14: 106-111 | J14: CABI, PROQUEST | K14: http://www.aab.bioflux.com.ro/docs/2020.106-111.pdf | L14: 70 | M14: 14 | N14: Lengyel Ecaterina
A15: Study of awareness of food labeling among consumers in North-West Russia | B15: Mark Shamtsyan, Boris Kolesnikov, Mikhail Pushkarev - SIT-Russia, Liviu Gaceu, Oana Bianca Oprea Universitatea Transilvania din Brasov, Iulia Iatco rep Moldova, Dumitru Mnerie, Gabriela Mnerie Timisoara, Ovidiu Tita, Mihaela Tita, Cecilia Georgescu, Monica Mironescu, -ULBS, Stefan Stefanov and Stanka Damianova, Bulgaria | C15: FSSA2 | D15: E3S Web of Conf. Volume 215, 2020 International Scientific Conference on Biotechnology and Food Technology (BFT-2020) | E15: 215 | G15: eISSN: 2267-1242 | H15: 2020 | K15: 10.1051/e3sconf/202021501002 | L15: 70 | M15: 8.75 | N15: Mironescu Monica
A16: MANAGEMENT OF URINARY TRACT INFECTIONS | B16: Magda PANAITESCU , Daniela Maria ȘANDRU Universidad ”Latina” de Panama, Rep. de Panama, “Lucian Blaga” University of Sibiu, Romania, | C16: FSAA2 | D16: Management of Sustainable Development Sibiu, Romania, | E16: 12 | F16: 1 | G16: 2247 – 0220 | H16: Iunie 2020 | I16: 33-35 | J16: BDI | K16: https://msdjournal.org/wp-content/uploads/vol12issue1-5.pdf | L16: 70 | M16: 70 | N16: Sandru Daniela
A17: THE ANTIBACTERIAL POTENTIAL OF ESSENTIAL OILS ON PROPIONIBACTERIUM GRANULOSUM STRAINS | B17: Șandru, Daniela Maria and Panaitescu, Magda “Lucian Blaga” University of Sibiu, Romania, Universidad ”Latina” de Panama, Rep. de Panama, | C17: FSAA2 | D17: Management of Sustainable Development Sibiu, Romania, | E17: 12 | F17: 2 | G17: 2247 – 0220 | H17: Decembrie 2020 | I17: 21-24 | J17: BDI | K17: https://msdjournal.org/wp-content/uploads/vol12issue2-3.pdf | L17: 70 | M17: 70 | N17: Sandru Daniela
A18: Research on the evolution of sensory and physico-chemical characteristics of butter with the addition of mint and peppermint | B18: Mihaela Adriana Tiţa (ULBS), Butoi Laurenţiu(Liceul Tehnologic de Industrie Alimentara Sibiu) | C18: FSAA2 | D18: Management of Sustainable Development | E18: Volume 12 | F18: No. 1 | G18: 2247-0220 | H18: 2020 | I18: 19-20 | J18: EBSCO, Google Scholar, Index Copernicus , J-Gate, ResearchGate, | K18: http://rosita.ro/jeat/archive/1_2019.pdf | L18: 70 | M18: 70 | N18: Tita Mihaela
A19: MARKETING ASPECTS OF YOGHURT ENHANCEDWITH TAPIOCA | B19: 4. Moga, Valentina Mădălina (High Schoolof Food Industry), Tița, Mihaela Adriana (ULBS) | C19: FSAA2 | D19: Management of Sustainable Development | E19: Vol.12 | F19: No.2 | G19: 2247 – 0220 | H19: 2020 | I19: 12-20 | J19: EBSCO, Google Scholar, Index Copernicus , J-Gate, ResearchGate, | L19: 70 | M19: 70 | N19: Tita Mihaela
A20: Studies on the implementation of an innovative "fatty" dairy product with bioactive components | B20: M. Păunoiu (SC.Boromir SA), M. Tiţa (ULBS), | C20: FSAA2 | D20: Journal of EcoAgriTourism | E20: Vol. 16 | F20: No.2 | G20: 1844-8577 | H20: 2020 | I20: 56-63 | J20: CNCSIS cod 910 , CAB Abstracts , Global Health, Jeat. | K20: 1. http://rosita.ro/jeat/archive/2_2020.pdf | L20: 70 | M20: 70 | N20: Tita Mihaela
A21: M. Tiţa, O.Popa | B21: M. Tiţa (ULBS), O.Popa (ULBS) | C21: FSAA2 | D21: Journal of EcoAgriTourism | E21: Vol. 16 | F21: No.2 | G21: 1844-8577 | H21: 2020 | I21: 64-71 | J21: CNCSIS cod 910 , CAB Abstracts , Global Health, Jeat. | K21: 1. http://rosita.ro/jeat/archive/2_2020.pdf | L21: 70 | M21: 35 | N21: Tita Mihaela
A22: Biochemical approaches for goat milk yogurt production | B22: Cristina POPOVICI(TechnicalUniversityofMoldova, Chisinau), Mihaela Adriana TIȚA (ULBS), Anatolii CARTASEV (ScientificandPracticalInstituteofHorticultureandFoodTechnology, Chisinau), Vladislav RESITCA (ScientificandPracticalInstituteofHorticultureandFoodTechnology, Chisinau), Nina BOGDAN (ScientificandPracticalInstituteofHorticultureandFoodTechnology, Chisinau), Olga MIGALATIEV(ScientificandPracticalInstituteofHorticultureandFoodTechnology, Chisinau) | C22: FSAA2 | D22: Scientific Bulletin. Series F. Biotechnologies | E22: Vol. XXIV | F22: No.2 | G22: ISSN 2285-1364 | H22: 2020 | I22: 49-50 | J22: INDEX COPERNICUS, CABI, DOAJ, GOOGLE SCHOLAR, SCIPIO | K22: http://biotechnologyjournal.usamv.ro/pdf/2020/issue_2/Art6.pdf | L22: 70 | M22: 70 | N22: Tita Mihaela
A23: Ensuring sustainability in dairy processing for a circular economy | B23: Tita Ovidiu | C23: FSAA2 | D23: Journal of EcoAgriTourism | E23: 16 | F23: 2 | G23: ISNB:1844-8577 | H23: 2020 | I23: 72-76 | J23: CAB Abstracts, Global Health | K23: http://rosita.ro/jeat/archive/2_2020.pdf | L23: 70 | M23: 70 | N23: Tita Ovidiu
A24: Study of the chemical composition and antioxidant activity of some varieties of young red wines from different vineyards in southern Romania | B24: Onache Petronela Anca – INCDBH Stefanesti, Arges; Sumedrea Dorin Ioan - INCDBH Stefanesti, Arges; Tita Ovidiu – Universitatea “Lucian Blaga” Sibiu; Nicolescu Eugen – VITIS SA Babadag | C24: FSAA2 | D24: Scientific Papers. Series B, Horticulture. | E24: LXIV | F24: 1 | G24: Print ISSN 2285-5653, CD-ROM ISSN 2285-5661, Online ISSN 2286-1580, ISSN-L 2285-5653 | H24: 2020 | I24: 307-315 | J24: Web of Science Core Collection (Emerging Sources Citation Index - THOMSON REUTERS), CABI, INDEX COPERNICUS, CNCSIS B+ , Ulrich's Periodicals Directory, Google Scholar, PBN (Polish Scholarly Bibliography), Scipio, Scientific Indexing Service, OCLC (WorldCat), Research bible | K24: http://horticulturejournal.usamv.ro/pdf/2020/issue_1/Art46.pdf | L24: 70 | M24: 17.5 | N24: Tita Ovidiu
A61: TOTAL | M61: =SUM(M10:M60) -> 679
A63: Informațiile incomplete / incorecte vor conduce la neluarea în calcul a indicatorului respectiv

Sheet I.6
A2: I6 - Cărţi ştiinţifice de autor şi capitole publicate la edituri internaţionale de prestigiu și edituri internaționale (sau traduse pentru domeniul Filologie şi Teologie, sau traducere de text dramatic și carte de autor pentru domeniul Artele spectacolului).
A4: Se va verifica existenţa volumului fizic / CD electronic prin depunerea unui exemplar al cărţii la departament, respectiv prin existenţa în mediul on-line.
A5: Lista editurilor internationale de prestigiu se regaseste pe site-ul Serviciului CD: http://cercetare.ulbsibiu.ro/siepas.html. O editură este considerată internaţională dacă ISBN-ul este din străinătate şi cartea este publicată într-o limbă de circulaţie internaţională. Editurile din Republica Moldova sunt considerate edituri naţionale, indiferent de limba în care sunt publicate cărţile.
A6: În această categorie intră automat şi cărţile / capitolele de cărţi indexate în TR şi respectiv Scopus. Nu se acceptă ȋn această categorie volumele de conferință (Proceedings).
A7: Plafoane maxime anuale, pentru publicarea în edituri internaţionale de prestigiu: • 1500 puncte / declarant, indiferent de numărul de cărţi declarate Plafoane maxime anual, cerinţe cumulative pentru publicarea în edituri internaţionale: • 1500 puncte / declarant, indiferent de numărul de cărţi declarate • 1500 puncte / carte, indiferent de numărul de declaranţi
A8: * Punctaje de referință: • 10 puncte / pagină, pentru carte nouă publicată în edituri internaţionale de prestigiu (lista este disponibilă pe site-ul CD) • 3,5 puncte / pagină, pentru cărţi noi publicate la alte edituri internaţionale • 2,5 puncte per pagina re-editări • 1,5 puncte per pagină traducere, pentru domeniul Filologie şi Teologie • 0,5 puncte / pagină, pentru traducere de text dramatic și carte științifică de autor pentru domeniul Artele spectacolului
A9: Punctajul se alocă numai pentru capitolele care precizează contribuţia declarantului, împărţindu-se la numărul co-autorilor din ţară. Pentru co-autorii din străinătate se menţionează în paranteză instituţia. În cazul în care contribuţia individuală nu poate fi identificată, se împarte punctajul total rezultat pentru carte / capitol, la numărul autorilor din ţară. Pentru autorii din străinătate se menţionează în paranteză instituţia
A11: Titlul cărții | B11: Numele și prenumele autorilor | C11: Cod Departament | D11: Editura (se precizează în paranteză dacă este vorba de editură de prestigiu) | E11: ISBN-ul cărții | F11: Anul publicării | G11: Luna publicării | H11: Nr. pag. | I11: Punctaj de referință* | J11: Punctaj individual | K11: Numele și prenumele Declarant
A12: GENETICALLY MODIFIED AND IRRADIATED FOOD: CONTROVERSIAL ISSUES: FACTS VERSUS PERCEPTIONS | B12: Mathe E. (HU, Debretin Univ.), Antofie MM | C12: FSAA2 | D12: ACADEMIC PRESS LTD-ELSEVIER SCIENCE LTD, 125 LONDON WALL, LONDON EC2Y 5AS, ENGLAND | E12: 978-0-12-817241-4; 978-0-12-817240-7 | F12: 2020 | G12: ian. | H12: 24 | I12: 240 | J12: 240 | K12: Antofie Mihaela
A13: Capitol "Improving the Training Methods for Designers of Flexible Production Cells in Factories of the Future" in: Boosting Collaborative Networks 4.0 | B13: Mironescu I., Crăciunean DC., Florea A., Bondrea I. | C13: FSAA2 | D13: SpringerLink | E13: 978-3-030-62412-5 | F13: 2020 | G13: Nov | H13: 15 | I13: =H13*10 -> 150 | J13: =I13/4 -> 37.5 | K13: Mironescu Ion
A14: IMPROVING THE CONSISTENCY OF COW'S MILK YOGURT By adding tapioca powder | B14: Moga Valentina Madalina, Mihaela-Adriana Tita, | C14: FSAA2 | D14: https://www.lap-publishing.com/catalog/details/store/tr/book/978-620-3-19796-9/improving-the-consistency-of-cow-s-milk-yogurt?search=tita%20miahela | E14: ISBN 978-620-3-19796-9 | F14: 2020 | G14: decembrie | H14: 216 | I14: 756 | J14: 378 | K14: Tita Mihaela
A15: Destination Management and Marketing: Breakthroughs in Research and Practice, Cap. 68 - Ways to Promoting Rural, Cultural and Gastronomical Tourism in Mărginimea Sibiului (pages 1206-1214) | B15: Nicula V., Spânu Simona | C15: FSAA2 | D15: IGI-Global https://www.igi-global.com/chapter/ways-to-promoting-rural-cultural-and-gastronomical-tourism-in-mrginimea-sibiului/251105 | E15: DOI: 10.4018/978-1-7998-2469-5.ch068 | F15: 2020 | H15: 9 | I15: 31.5 | J15: 15.75 | K15: Spanu Simona
A62: TOTAL | J62: =SUM(J12:J61) -> 671.25
A64: Informațiile incomplete / incorecte vor conduce la neluarea în calcul a indicatorului respectiv

Sheet I.7
A2: I7 - Cărţi ştiinţifice de autor şi capitole publicate la edituri naționale (sau traduse pentru domeniul Filologie şi Teologie, sau traducere de text dramatic și carte de autor pentru domeniul Artele spectacolului).
A4: Se va verifica existenţa volumului fizic / CD electronic prin depunerea unui exemplar al cărţii la departament şi respectiv prin existenţa cărţii în Depozitul electronic al Bibliotecii Naţionale şi al Bibliotecii Centrale Universitare (BCU);
A5: Nu se acceptă ȋn această categorie suport de curs, ȋndrumar de laborator sau alte cărți cu caracter didactic; nu se acceptă ȋn această categorie volumele de conferință (Proceedings).
A6: Cărţile / capitolele de carte raportate la acest indicator nu pot fi raportate şi pe SIEPAS – componenta didactică
A7: Nu se acceptă reeditări mai devreme de 3 ani
A8: Plafoane maxime anual, cerinţe cumulative: • 300 puncte / declarant, indiferent de numărul de cărţi declarate și • 400 puncte / carte, indiferent de numărul de declaranţi.
A9: * Punctaje de referință: • 2 puncte / pagină, pentru cărţi noi • 0,5 puncte / pagină, pentru reeditări • 0,3 puncte / pagina pentru traduceri, pentru domeniul Filologie şi Teologie • 0,5 puncte / pagină, pentru traducere de text dramatic și carte științifică de autor pentru domeniul Artele spectacolului
A10: Punctajul se alocă numai pentru capitolele care precizează contribuţia declarantului, împărţindu-se la numărul co-autorilor din ţară. Pentru co-autorii din străinătate se menţionează în paranteză instituţia. În cazul în care contribuţia individuală nu poate fi identificată, se împarte punctajul total rezultat pentru carte / capitol, la numărul autorilor din ţară. Pentru autorii din străinătate se menţionează în paranteză instituţia
A12: Titlul cărții | B12: Numele și prenumele autorilor | C12: Cod Departament | D12: Editura | E12: ISBN-ul cărții | F12: Anul publicării | G12: Luna publicării | H12: Nr. pag. | I12: Punctaj de referință* | J12: Punctaj individual | K12: Numele și prenumele Declarant
A13: TRATAT DE BIOTEHNOLOGIE GENERALĂ, VOUMUL I: SECOLUL XXI - SECOLUL BIOTEHNOLOGIEI | B13: Antofie MM | C13: FSAA2 | D13: ULBS | E13: 978-606-12-1817-2 | F13: 2020 | G13: Dec | H13: 24 | I13: 48 | J13: 48 | K13: Antofie Mihaela
A14: Managementul ecosistemelor forestiere cu plop tremurător și mesteacăn. Oportunități de valorizare. | B14: Bratu Iulian Alexandru | C14: FSAA2 | D14: Editura Universitară, București | E14: 978-606-28-1204-1 | F14: 2020 | G14: 12 | H14: 212 | I14: =H14*2 -> 424 | J14: 300 | K14: Bratu Alexandru
A15: Operații unitare în industria alimentară, Volumul 1. Fenomene de transfer | B15: Ciprian Capatana, Mihai Văduva | C15: FSAA2 | D15: Editura ULBS | E15: 978-606-12-1810-3 | F15: 2020 | G15: decembrie | H15: 270 | I15: 540 | J15: 270 | K15: Capatana Ciprian
A16: Protecția anticorozivă a metalelor și aliajelor | B16: Crețu C.M. | C16: FSAA2 | D16: Editura Universității Lucian Blaga din Sibiu | E16: 978-606-12-1746-5 | F16: 2020 | G16: mai | H16: 100 | I16: 200 | J16: 200 | K16: Cretu Monica
A17: Elemente de Didactica disciplinelor de Inginerie alimentară | B17: Danciu Cristina-Anca | C17: FSAA2 | D17: Editura Universității Lucian Blaga din Sibiu | E17: 978-606-12-1776-2 | F17: 2020 | G17: 44501 | H17: 194 | I17: 388 | J17: 300 | K17: Danciu Cristina
A18: Organoleptica | B18: Iancu Maria Lidia | C18: FSAA2 | D18: Editura Performantica (acreditată CNCSIS), Iași | E18: ISBN: 978-606-685-723-9 | F18: 2020 | G18: septembrie | H18: 208 | I18: 416 | J18: 300 | K18: Iancu Maria
A19: Procese suport ale sistemului de management al calității și siguranței alimentului în industria fermentativă | B19: Mariana Liliana PĂCALĂ, Lucica BRUDIU | C19: FSAA2 | D19: Editura Universităţii „Lucian Blaga“ din Sibiu | E19: 978-606-12-1821-9 | F19: 2020 | G19: decembrie | H19: 155 | I19: 310 | J19: 155 | K19: Pacala Mariana
A20: TRATAT DE BIOTEHNOLOGIE GENERALĂ, VOUMUL I: SECOLUL XXI - SECOLUL BIOTEHNOLOGIEI | B20: Cachita CD, Sava C | C20: FSAA2 | D20: ULBS | E20: 978-606-12-1817-2 | F20: 2020 | G20: Dec | H20: 170 | I20: 340 | J20: =I20/2 -> 170 | K20: Sava Camelia
A21: Matlab-Simulink : Interfeţe grafice - exemple și aplicaţii Exemple și aplicaţii în ingineria produselor alimentare | B21: Şipoş Anca | C21: FSAA2 | D21: Editura Universităţii "Lucian Blaga" din Sibiu | E21: 978-606-12-1804-2 | F21: 2020 | G21: decembrie | H21: 145 | I21: =145*2 -> 290 | J21: 290 | K21: Sipos Anca
A22: Abordări și studii de caz relevante privind managementul organizațiilor din România, în contextul pandemiei COVID-19 / Cap. Strategii de marketing pentru produsele apicole ecologice valorificate în cadrul parteneriatului ”Apii-delicii hunedorene”, pag. 213-221 | B22: Nicula V., Spânu Simona | C22: FSAA2 | D22: ProUniversitaria | E22: 978-606-26-1244-3 | F22: 2020 | G22: dec. | H22: 9 | I22: 18 | J22: 9 | K22: Spanu Simona
A23: Tehnologia fabricării turtei dulci | B23: Tulbure Anca | C23: FSAA2 | D23: Editura Universității Lucian Blaga din Sibiu | E23: 978-606-12-1775-5 | F23: 2020 | G23: decembrie | H23: 241 | I23: 482 | J23: 300 | K23: Tulbure Anca
A24: Operații unitare în industraia alimentară, Vol.1, Fenomene de Transfer | B24: Ciprian Căpățână Mihai Văduva | C24: FSAA2 | D24: Editura Universităţii „Lucian Blaga” din Sibiu | E24: 978-606-12-1810-3 978-606-12-1811-0 | F24: 2020 | G24: decembrie | H24: 270 | I24: 540 | J24: 270 | K24: Vaduva Mihai
A25: ECHIPAMENTE PENTRU MĂRIREA CAPACITĂȚII DE PRODUCȚIE ÎN INDUSTRIA CĂRNII | B25: Drăghici Olga | C25: FSAA2 | D25: Ed. Univ. ”L.Blaga” din Sibiu | E25: 9786061218387 | F25: 2020 | G25: dec | H25: 150 | I25: 300 | J25: =I25 -> 300 | K25: Draghici Olga
A63: TOTAL | J63: =SUM(J13:J62) -> 2912
A65: Informațiile incomplete / incorecte vor conduce la neluarea în calcul a indicatorului respectiv

Sheet I.8
A2: I8 - Editor volum ştiinţific (carte, volum conferinţă, îngrijitor colecţie ...)
A4: Decizia privind caracterul ştiinţific al publicaţiei se ia la nivel de departament.
A5: Un volum / o carte este considerată internaţională / naţională dacă ISBN-ul este din străinătate, ȋntr-o limbă de circulație internațională, respectiv din ţară.
A6: Conferința este internațională dacă îndeplineşte cumulativ următoarele criterii: (a) are vizibilitate internaţională, dovedită printr-o pagina web de prezentare într-o limbă străină de circulaţie internaţională (engleză, franceză, germană sau spaniolă); (b) peste 50% dintre membrii incluşi în comitetul ştiinţific au afiliere instituţională în străinătate, conform listei comitetului ştiinţific de pe pagina web a conferinţei; (c) programul ştiinţific, precum şi proceedings-urile sau rezumatele sunt publicate în format tipărit sau electronic într-o limbă străină de circulaţie internaţională; (d) lucrările conferinţei sunt desfăşurate exclusiv într-o limbă străină de circulaţie internaţională; (e) minim 25% dintre participanţi sau minim 25 participanţi cu lucrări înscrise au afiliere instituţională în străinătate, conform programului ştiinţific de pe pagina web a conferinţei. Conferinţa care nu îndeplineşte criteriile minimale pentru a fi încadrată astfel are statutul de conferinţă naţională. Criterii pentru conferinţa naţională, cel puţin: pagina web; program ştiinţific; comitet stiintific; volum al conferintei. Nu se iau în calcul volumele manifestărilor ştiinţifice studenţeşti, care se raportează la componenta didactică a SIEPAS.
A7: Nu se ia în calcul calitatea de editor revistă / volum revistă care se raportează la I14.
A8: * Punctaje de referință: Volume științifice publicate în străinătate, la o editură de prestigiu internațional (lista diponibilă pe site-ul http://cercetare.ulbsibiu.ro): • 750 puncte (nu se acceptă volume ale conferinţelor) Se împarte punctajul la numărul editorilor din țară. Plafoane maxime anual, cerinţe cumulative: • 750 puncte / declarant, indiferent de numărul de volume editate • 750 puncte / volum, indiferent de numărul de declaranţi Volume științifice / volume ale conferinţelor (proceedings) • Volum ştiinţific publicat în străinătate sau volum (Proceedings) conferinţă internaţională = 200 puncte • Volum ştiinţific publicat în ţară sau volum conferinţă naţională = 100 puncte Se împarte punctajul la numărul editorilor din țară. Plafoane maxime anual, cerinţe cumulative: • 200 puncte / declarant, indiferent de numarul de volume editate • 200 puncte / volum, indiferent de numărul de declaranţi
A10: Titlul volumului științific / Titlul volumului conferinței | B10: Numele și prenumele editorilor din țară | C10: Cod Departament | D10: Editura / Conferința | E10: ISBN-ul cărții | F10: Anul publicării | G10: Link editură / link conferință | H10: Punctaj total de referință* | I10: Punctaj individual | J10: Numele și prenumele Declarant
A11: TRATAT DE BIOTEHNOLOGIE GENERALĂ, VOUMUL I: SECOLUL XXI - SECOLUL BIOTEHNOLOGIEI | B11: Cachita CD, Sava C | C11: FSAA2 | D11: ULBS | E11: 978-606-12-1817-2 | F11: 2020 | H11: 100 | I11: 50 | J11: Sava Camelia
A61: TOTAL | I61: =SUM(I11:I60) -> 50
A63: Informațiile incomplete / incorecte vor conduce la neluarea în calcul a indicatorului respectiv

Sheet I.9
A2: I9 - Citări
A4: Auto-citările (citări în articole ale oricăruia dintre autori) se exclud.
A5: Citarile în teze de doctorat / lucrări de disertaţie / lucrări de licenţă susţinute în România se exclud.
A6: * Punctaje de referință: • Citare în WoS TR şi SCOPUS = 50 puncte. • Citare în alte baze date, sau în cărţi = 15 puncte Punctajul se împarte la numărul de autori cu afiliere la instituţiile de învăţământ şi cercetare din România, inclusiv la doctoranzi / studenţi; pentru autorii din străinătate sau autorii din mediul de afaceri, se menţionează în paranteză instituţia.
A8: Numele și prenumele autorilor lucrării citate (se menționează în paranteză afilierea) | B8: Cod departament | C8: Lucrarea citată (titlu) | D8: Publicația în care este citată lucrarea (autori, titlu, revistă ...) | E8: Link către publicația în care este citată lucrarea | F8: Baza de date în care este citată lucrarea (WoS / SCOPUS / altă bază de date sau carte) | G8: Punctaj de referință* | H8: Punctaj individual | I8: Numele și prenumele Declarant
A9: Antofie MM | B9: FSAA2 | C9: Current political commitments’ challenges for ex situ conservation of plant genetic resources for food and agriculture | D9: AKINBOBOYE, T., ADETOLA, B., & AGBELUSI, E. (2020). DIVERSITY AND STATUS OF FAUNA SPECIES IN THE ZOOS OF SOUTHWEST NIGERIA. Ethiopian Journal of Environmental Studies & Management, 13(4), 476-485. | E9: https://ejesm.org/wp-content/uploads/2020/08/ejesm.v13i4.8.pdf | F9: Google academic | G9: 15 | H9: 15 | I9: Antofie Mihaela
A10: Antofie MM, Mitoi ME | B10: FSAA2 | C10: Lovastatin effects on indirect somatic embryogenesis of petunia | D10: Tang, L. P., Zhang, X. S., & Su, Y. H. (2020). Regulation of cell reprogramming by auxin during somatic embryogenesis. aBIOTECH, 1-9. | E10: https://link.springer.com/article/10.1007/s42994-020-00029-8 | F10: Google academic, Mendeley | G10: 15 | H10: 7.5 | I10: Antofie Mihaela
A11: Antofie MM, Pop M, Sand C, Ciotea G, Iagrăru P | B11: FSAA2 | C11: Data sheet model for developing a red list regarding crop landraces in Romania | D11: Mir, R. A., Sharma, A., & Mahajan, R. (2020). 13 Crop Landraces: Present Threats and Opportunities for Conservation. Rediscovery of Genetic and Genomic Resources for Future Food Security, 335. | E11: https://link.springer.com/chapter/10.1007/978-981-15-0156-2_13 | F11: Google academic, Mendeley | G11: 15 | H11: 3.75 | I11: Antofie Mihaela
A12: Antofie MM, Barbu I, Sand CS, Blaj R | B12: FSAA2 | C12: Traditional orchards in Romania: case study Fântânele, Sibiu County. | D12: Žarnovičan, H., Kanka, R., Kollár, J., Vyskupová, M., Sivecká, A., Tichá, A., ... & Kršiaková, D. (2020). Traditional orchard Management in the Western Carpathians (Slovakia): evolution between 1955 and 2015. Biologia, 1-12. | E12: https://link.springer.com/article/10.2478/s11756-020-00434-w | F12: WoS | G12: 50 | H12: =G12/4 -> 12.5 | I12: Antofie Mihaela
A13: R. Khaliq, O. Tita, M.M. Antofie, C. Sava | B13: FSAA2 | C13: Industrial application of psyllium: An overview | D13: Franco, E. A. N., Sanches-Silva, A., Ribeiro-Santos, R., & de Melo, N. R. (2020). Psyllium (Plantago ovata Forsk): From evidence of health benefits to its food application. Trends in Food Science & Technology, 96, 166-175. | E13: https://www.sciencedirect.com/science/article/pii/S092422441830791X?casa_token=QKG3kYzfnqkAAAAA:0jYS8SDK4dzsgUT5BTJYw96E2lKWRTfVXkFb-urvHTaN9kMCe7MkgU9kcui-Phu84WCCflvU0A | F13: WoS | G13: 50 | H13: 16.66 | I13: Antofie Mihaela
A14: R. Khaliq, O. Tita, M.M. Antofie, C. Sava | B14: FSAA2 | C14: Industrial application of psyllium: An overview | D14: James M. Cowley*, Lina Herliana, Natalie S. Betts, and Rachel A. Burton, 2020, Cellular debris, not mucilage polysaccharides, dominate extracts of Plantago ovata and Plantago lanceolata calli grown in vitro, BioRixv doi: https://doi.org/10.1101/2020.06.15.153395 | E14: https://www.biorxiv.org/content/10.1101/2020.06.15.153395v2.full.pdf | F14: Googlescholar | G14: 15 | H14: =G14/3 -> 5 | I14: Antofie Mihaela
A15: R. Khaliq, O. Tita, M.M. Antofie, C. Sava | B15: FSAA2 | C15: Industrial application of psyllium: An overview | D15: Shah, A. R., Sharma, P., Longvah, T., Gour, V. S., Kothari, S. L., Shah, Y. R., & Ganie, S. A. (2020). Nutritional Composition and Health Benefits of Psyllium (Plantago ovata) Husk and Seed. Nutrition Today, 55(6), 313-321. | E15: https://journals.lww.com/nutritiontodayonline/Abstract/2020/11000/Nutritional_Composition_and_Health_Benefits_of.11.aspx | F15: Googlescholar | G15: 15 | H15: =G15/3 -> 5 | I15: Antofie Mihaela
A16: R. Khaliq, O. Tita, M.M. Antofie, C. Sava | B16: FSAA2 | C16: Industrial application of psyllium: An overview | D16: Sabzehzari, M., Hoveidamanesh, S., Modarresi, M., & Mohammadi, V. (2020). Morphological, anatomical, physiological, and cytological studies in diploid and tetraploid plants of Ispaghul (Plantago ovata Forsk.). Genetic Resources and Crop Evolution, 67(1), 129-137. | E16: https://link.springer.com/article/10.1007/s10722-019-00846-x | F16: Wos | G16: 50 | H16: 16.67 | I16: Antofie Mihaela
A17: Sava Sand, C., Antofie, M.-M. | B17: FSAA2 | C17: The conservation of plant genetic resources for food and agriculture: consumers' perspectives analysis in Sibiu Agri-Food markets | D17: Stanciu Cărătuș, M, THE MAIN CHARACTERISTICS OF AGRICULTURE AND RURAL DEVELOPMENT IN THE CENTRAL REGION OF ROMANIA, 2020, Scientific Papers Series Management, Economic Engineering in Agriculture and Rural Development Vol. 20, Issue 4, 131-138 | E17: http://managementjournal.usamv.ro/pdf/vol.20_4/Art17.pdf | F17: Wos | G17: 50 | H17: =G17/2 -> 25 | I17: Antofie Mihaela
A18: Sava Sand, C., Antofie, M.-M. | B18: FSAA2 | C18: The conservation of plant genetic resources for food and agriculture: the conservation of plant genetic resources for food and agriculture: sellers' perspectives analysis from Sibiu's agri-food markets | D18: Stanciu Cărătuș, M, THE MAIN CHARACTERISTICS OF AGRICULTURE AND RURAL DEVELOPMENT IN THE CENTRAL REGION OF ROMANIA, 2020, Scientific Papers Series Management, Economic Engineering in Agriculture and Rural Development Vol. 20, Issue 4, 131-138 | E18: http://managementjournal.usamv.ro/pdf/vol.20_4/Art17.pdf | F18: Wos | G18: 50 | H18: =G18/2 -> 25 | I18: Antofie Mihaela
A19: Sava Sand, C., Antofie, M.-M. | B19: FSAA2 | C19: THE CONSERVATION OF PLANT GENETIC RESOURCES FOR FOOD AND AGRICULTURE: CONSUMERS' PERSPECTIVES ANALYSIS IN SIBIU AGRI-FOOD MARKETS | D19: Stanciu Cărătuș Mirela, RESEARCH REGARDING YOUNGER CONSUMERS ATTITUDE, IN RELATION WITH SHEEP MEAT CONSUMPTION, SCIENTIFIC PAPERS-SERIES MANAGEMENT ECONOMIC ENGINEERING IN AGRICULTURE AND RURAL DEVELOPMENT, Volume: 20 Issue: 4 P.125-130, 2020 | E19: http://managementjournal.usamv.ro/pdf/vol.20_4/Art16.pdf | F19: WOS | G19: 50 | H19: 25 | I19: Antofie Mihaela
A20: Maria Mihaela ANTOFIE, Camelia SAVA SAND | B20: FSAA2 | C20: STANDARD CHARACTERIZATION OF RED ONION LANDRACES ‘DE BUZĂU’ AND ‘DE TURDA’ , Scientific Papers Series Management, Economic Engineering in Agriculture and Rural Development Vol. 17, Issue 4, 2017 | D20: Madoșă E.1 , Velicevici Giancarla1*, Ciulca S.1 , Avădanei C.1 , Ciulca Adriana1 , Sărac I.1 , Sasu Lavinia,Studies on the variability of some morphological characters in the "de Vinga" onions landrace,JOURNAL of Horticulture, Forestry and Biotechnology, Volume 24(1), 1 - 5, 2020 | E20: https://journal-hfb.usab-tm.ro/2020/JHFB%202020%20Vol%20I/01Madosa%20E%20et%20al%20publihing.pdf | F20: scopus, google scholar | G20: 15 | H20: 7.5 | I20: Antofie Mihaela
A21: Pop M.R, Sand C, Bobiț D, Antofie M.M, Barbu H, Pavel P.B, Muntean L, Savatti M. | B21: FSAA2 | C21: 2010 Studies concerning the production of volatile oil, rhizomes and roots, to different genotypes of Valeriana officinalis L. | D21: Diyanat, M., & Baziar, S. (2020). The effect of weed control on growth, yield and physicochemical properties of valerian (Valeriana officinalis L.). Journal of Research in Weed Science, 3(4), 420-435. | E21: http://www.jrweedsci.com/article_103976.html | F21: Googlescholar | G21: 15 | H21: 1.88 | I21: Antofie Mihaela
A22: Antonie Iuliana | B22: ȘAIPA | C22: The biodiversity of the melliferous plants in the surroundings of the town sebes (alba county) and their economical importance Scientific Papers Series Management, Economic Engineering in Agriculture and Rural Development 14(4), 13-18. | D22: İlginç KIZILPINAR TEMİZER, Aytaç GÜDER, Birol BAŞER, DETERMINATION OF SEVERAL BITLIS HONEYS BASED ON THEIR BOTANIC AND BIOCHEMICAL PROFILES, J. Fac. Pharm. Ankara / Ankara Ecz. Fak. Derg., 44(3): 494-505, 2020 | E22: http://journal.pharmacy.ankara.edu.tr/wp-content/uploads/sites/246/2020/11/44_3_2020.pdf | F22: Doi: 10.33483/jfpau.767197 | G22: 50 | H22: 50 | I22: Antonie Iuliana
A23: Stanciu, M., Ciortea, G., Sand, C., Vlad, I., Antonie, I., Tanase, M., Blaj, R. | B23: ȘAIPA | C23: Assessments regarding sustainable development on ecoeconomic and bioeconomic principles, of the local communities in the sheep breeding villages from “Drumul Regelui” (King's Road), Scientific Papers Series Management, Economic Engineering in Agriculture and Rural Development Vol.12(3), 167-174 | D23: Alina MARCUTA, Liviu MARCUTA, Agatha POPESCU, Cristina TINDECHE, Valentina TUDOR, Dragos SMEDESCU, POSSIBILITIES OF DEVELOPMENT OF THE SLOW TOURISM CONCEPT IN ROMANIA, Scientific Papers Series Management, Economic Engineering in Agriculture and Rural Development Vol. 20, Issue 4, 331-338, 2020 | E23: http://managementjournal.usamv.ro/pdf/vol.20_4/Art40.pdf | F23: WOS | G23: 50 | H23: 7.14 | I23: Antonie Iuliana
A24: Antonie Iuliana, Manole Traian, Stanciu Mirela, Sand Camelia | B24: ȘAIPA | C24: The Impact of the Agricultural Technology upon the Biodiversity of the Arthropods Present in the Corn Culture in Sibiu County. JOURNAL of Horticulture, Forestry and Biotechnology, 16(3), pp. 7-12, 2012 | D24: Dincă Lucian, CHARACTERISTICS OF FOREST SOILS FROM SIBIU COUNTY, Scientific Study & Research - Biology, Volume 29, No. 1, 27-30, (2020) | E24: http://pubs.ub.ro/?pg=revues&rev=scsb&num=202001&vol=29 | F24: Zoological Record- Master Journal List ISI Thomson Reuters (http://scientific.thomsonreuters.com/cgi-bin/jrnlst/jlresults.cgi?PC=MASTER&ISSN=1224-919X) | G24: 15 | H24: 3.75 | I24: Antonie Iuliana
A25: Antonie Iuliana, Pavel Petronela | B25: ȘAIPA | C25: The analysis of the heavy metals in the corn agricultural ecosystem in the Axente Sever-Copsa Mica area (Sibiu County). Revista Economica, 65(1), 2013 | D25: Dincă Lucian, CHARACTERISTICS OF FOREST SOILS FROM SIBIU COUNTY, Scientific Study & Research - Biology, Volume 29, No. 1, 27-30, (2020) | E25: http://pubs.ub.ro/?pg=revues&rev=scsb&num=202001&vol=29 | F25: Zoological Record- Master Journal List ISI Thomson Reuters (http://scientific.thomsonreuters.com/cgi-bin/jrnlst/jlresults.cgi?PC=MASTER&ISSN=1224-919X) | G25: 15 | H25: 7.5 | I25: Antonie Iuliana
A26: Mărculescu, A., Vlase, L., Hanganu, D., Drăgulescu, C., Antonie, I., Neli-Kinga | B26: ȘAIPA | C26: Polyphenols analysis from Thymus species. Proc Rom Acad Ser B. 2007;3:117-121. | D26: R HARIKRISHNAN, C BALASUNDARAM, Potential of herbar extracts and bioactive compounds for human healthcare, in: The Role of Phytoconstitutents in Health Care, Apple Academic Press, 3-158, 2020 | E26: file:///C:/Users/40722/Downloads/TheRoleofPhytoconstitutentsinHealthCare_authorcopy%20(5).pdf | F26: Carte | G26: 15 | H26: 2.5 | I26: Antonie Iuliana
A27: Vlad-Antonie Iuliana, Ciobanu Rodica | B27: ȘAIPA | C27: Der Arzt Viktor Weindel als Insektenkundler (1887-1966), Siebenbürgisch Sächsische Naturwissenschaftler. Lucian Blaga University of Sibiu Press, pp. 139-143. | D27: Stancă Moise Cristina, FOREST AND AGRICULTURAL ECOSYSTEMS PESTS (LEPIDOPTERA), PRESERVED IN THE ENTOMOLOGICAL COLLECTIONS OF THE NATURAL, Analele Universităţii din Oradea, Fascicula Biologie HISTORY MUSEUM IN SIBIU, Tom. XXVII, Issue: 2, 2020, pp. 224-232 | E27: http://olteniastudiisicomunicaristiintelenaturii.ro/v36_2.html | F27: ZOOR, http://olteniastudiisicomunicaristiintelenaturii.ro/cont/36_2/III.%20ANIMAL%20BIOLOGY%20III.a.%20INVERTEBRATES%20VARIOUS/12Moise.pdf | G27: 50 | H27: 25 | I27: Antonie Iuliana
A28: Stanciu, M., Tanase, M., Vlad, I., Antonie, I.,Gaureanu, M., | B28: ȘAIPA | C28: Organic dairy sheep farms in Sibiu county, Romania: typologies according to livestock management. | D28: SCIENTIFIC BASICS AND PROSPECTS OF DEVELOPMENT OF PRODUCTION OF ORGANIC ANIMAL PRODUCTS IN RUSSIA By: Chernyaev, Anatoliy Alekseevich; Serdobintsev, Dmitriy Valerevich; Kudryashova, Ekaterina Vladimirovna SCIENTIFIC PAPERS-SERIES MANAGEMENT ECONOMIC ENGINEERING IN AGRICULTURE AND RURAL DEVELOPMENT Volume: ‏ 20 Issue: ‏ 2 Pages: ‏ 117-125 Published: ‏2020 | E28: http://managementjournal.usamv.ro/pdf/vol.20_2/Art15.pdf | F28: wos | G28: 50 | H28: 10 | I28: Antonie Iuliana
A29: Petronela-Bianca Pavel (ULBS) Ellena Diacu (Politehnica, București) Constantin Horia Barbu (ULBS), MarkusPuschenreiter (BOKU, Viena) Walter W.Wenzel (BOKU, Viena) | B29: FSAA2 | C29: Aided phytostabilization using Miscanthus sinensis x giganteus on heavy metal-contaminated soils. Science of the Total Environment, 479, 2014, 125–131. | D29: Liuwei Wang,Deyi Hou,Zhengtao Shen,Jin Zhu,Xiyue Jia,Yong Sik Ok,Filip M. G. Tack &Jörg Rinklebe, Field trials of phytomining and phytoremediation: A critical review of influencing factors and effects of additives, Critical Reviews in Environmental Science and Technology Volume 50, 2020, Pages 2724-2774 DA | E29: https://www.tandfonline.com/doi/full/10.1080/10643389.2019.1705724 | F29: WOS:000503930200001 | G29: 50 | H29: 16.67 | I29: Barbu Horia
A30: Petronela-Bianca Pavel (ULBS) Ellena Diacu (Politehnica, București) Constantin Horia Barbu (ULBS), MarkusPuschenreiter (BOKU, Viena) Walter W.Wenzel (BOKU, Viena) | B30: FSAA2 | C30: Aided phytostabilization using Miscanthus sinensis x giganteus on heavy metal-contaminated soils. Science of the Total Environment, 479, 2014, 125–131. | D30: Zhong, X; Chen, ZW; Li, YY, Ding, KB; Liu, WS, Qiu, RL, Factors influencing heavy metal availability and risk assessment of soils at typical metal mines in Eastern China, Journal of Hazardous Materials Volume 400, 5 December 2020, 123289 DA | E30: https://www.sciencedirect.com/science/article/abs/pii/S0304389420312784?via%3Dihub | F30: WOS:000572111400004 | G30: 50 | H30: 16.67 | I30: Barbu Horia
A31: Petronela-Bianca Pavel (ULBS) Ellena Diacu (Politehnica, București) Constantin Horia Barbu (ULBS), MarkusPuschenreiter (BOKU, Viena) Walter W.Wenzel (BOKU, Viena) | B31: FSAA2 | C31: Aided phytostabilization using Miscanthus sinensis x giganteus on heavy metal-contaminated soils. Science of the Total Environment, 479, 2014, 125–131. | D31: Manhattan Lebrun,Reinhart Van Poucke, Florie Miard, Gabriella Scippa, Sylvain Bourgerie, Domenico Morabito, F. Tack Effects of carbon-based materials and redmuds on metal(loid) immobilization and growth of Salix dasyclados Wimm. on a former mine Technosol contaminated by arsenic and lead July 2020Land Degradation and Development 32(1) | E31: https://onlinelibrary.wiley.com/doi/10.1002/ldr.3726 DOI: 10.1002/ldr.3726 | F31: WOS:000566814400001 | G31: 50 | H31: 16.67 | I31: Barbu Horia
A32: Petronela-Bianca Pavel (ULBS) Ellena Diacu (Politehnica, București) Constantin Horia Barbu (ULBS), MarkusPuschenreiter (BOKU, Viena) Walter W.Wenzel (BOKU, Viena) | B32: FSAA2 | C32: Aided phytostabilization using Miscanthus sinensis x giganteus on heavy metal-contaminated soils. Science of the Total Environment, 479, 2014, 125–131. | D32: Kharytonov M. M., Martynova N. V., Babenko M. G., Rula I. V, ENVIRONMENTALLY COMPATIBLE UTILIZATION OF RECLAIMED MINELANDS FOR SUSTAINABLE PRODUCTION FOOD AND BIOENERGY FEEDSTOCK, 43-Chapter | E32: DOI https://doi.org/10.30525/978-9934-588-45-7.30 http://baltijapublishing.lv/omp/index.php/bp/catalog/download/43/824/1645-1 | F32: Google Scholar | G32: 15 | H32: =G32/3 -> 5 | I32: Barbu Horia
A33: Petronela-Bianca Pavel (ULBS) Ellena Diacu (Politehnica, București) Constantin Horia Barbu (ULBS), MarkusPuschenreiter (BOKU, Viena) Walter W.Wenzel (BOKU, Viena) | B33: FSAA2 | C33: Aided phytostabilization using Miscanthus sinensis x giganteus on heavy metal-contaminated soils. Science of the Total Environment, 479, 2014, 125–131. | D33: Sameena P.P. &Jos T. Puthur, Heavy Metal Phytoremediation by Bioenergy Plants and Associated Tolerance Mechanisms, Soil and Sediment Contamination: An International Journal, December 2020 | E33: https://www.tandfonline.com/doi/full/10.1080/15320383.2020.1849017 | F33: WOS:000600737400001 | G33: 50 | H33: 16.67 | I33: Barbu Horia
A34: Petronela-Bianca Pavel (ULBS) Ellena Diacu (Politehnica, București) Constantin Horia Barbu (ULBS), MarkusPuschenreiter (BOKU, Viena) Walter W.Wenzel (BOKU, Viena) | B34: FSAA2 | C34: Aided phytostabilization using Miscanthus sinensis x giganteus on heavy metal-contaminated soils. Science of the Total Environment, 479, 2014, 125–131. | D34: Author links open overlay panelHuangYuaXiafeiZhengaWanlinWengaXizheYanaPuboChenaXingyuLiuaTaoPenga Synergistic effects of antimony and arsenic contaminations on bacterial, archaeal and fungal communities in the rhizosphere of Miscanthus sinensis: Insights for nitrification and carbon mineralization, Journal of Hazardous Materials, Volume 411, 5 June 2020, 125094 | E34: https://doi.org/10.1016/j.jhazmat.2021.125094 | F34: WoS TR | G34: 50 | H34: 16.67 | I34: Barbu Horia
A35: Petronela-Bianca Pavel (ULBS) Ellena Diacu (Politehnica, București) Constantin Horia Barbu (ULBS), MarkusPuschenreiter (BOKU, Viena) Walter W.Wenzel (BOKU, Viena) | B35: FSAA2 | C35: Aided phytostabilization using Miscanthus sinensis x giganteus on heavy metal-contaminated soils. Science of the Total Environment, 479, 2014, 125–131. | D35: Ben Fradj, N; Rozakis, S; Borzecka, M; Matyka, M, Miscanthus in the European bio-economy: A network analysis, INDUSTRIAL CROPS AND PRODUCTS, Volume: 148, Article Number: 112281, Published: JUN 2020 | E35: https://reader.elsevier.com/reader/sd/pii/S0926669020301977?token=F780A1E73AE57B3F9CF32DBAB3800705ABBB57295DEF2576327F566C7EE5FD8291D8B7730F2A338E1A1636F0F410035F | F35: WOS:000527912200024 | G35: 50 | H35: 16.67 | I35: Barbu Horia
A36: Petronela-Bianca Pavel (ULBS) Ellena Diacu (Politehnica, București) Constantin Horia Barbu (ULBS), MarkusPuschenreiter (BOKU, Viena) Walter W.Wenzel (BOKU, Viena) | B36: FSAA2 | C36: Aided phytostabilization using Miscanthus sinensis x giganteus on heavy metal-contaminated soils. Science of the Total Environment, 479, 2014, 125–131. | D36: Marie Hechelski,Brice Louvel,Pierrick Dufrénoy,Alina Ghinet and Christophe Waterlot, Toward a New Way for the Valorization of Miscanthus Biomass Produced on Metal-Contaminated Soils Part 1: Mesocosm and Field Experiments, Sustainability 2020, 12(22), 9370; | E36: DOI: 10.1016/j.indcrop.2020.112281, https://www.mdpi.com/2071-1050/12/22/9370/htm | F36: WOS:000594611300001 https://doi.org/10.3390/su12229370 | G36: 50 | H36: 16.67 | I36: Barbu Horia
A37: Petronela-Bianca Pavel (ULBS) Ellena Diacu (Politehnica, București) Constantin Horia Barbu (ULBS), MarkusPuschenreiter (BOKU, Viena) Walter W.Wenzel (BOKU, Viena) | B37: FSAA2 | C37: Aided phytostabilization using Miscanthus sinensis x giganteus on heavy metal-contaminated soils. Science of the Total Environment, 479, 2014, 125–131. | D37: Zeljka Zgorelec, Nikola Bilandzija, Kristina Knez, MarijaGalic & Silva Zuzul, Cadmium and Mercury phytostabilization from soil using Miscanthus × giganteus, Scientific Reports (Nature Publisher Group); SCIENTIFIC REPORTS, Volume: 10 Issue: 1 Article Number: 6685, APR 21 2020 | E37: DOI: 10.1038/s41598-020-63488-5 https://search.proquest.com/openview/3b595cb51ae5d03316efba9590cdbd40/1?pq-origsite=gscholar&cbl=2041939 | F37: WOS:000559762800009 , | G37: 50 | H37: 16.67 | I37: Barbu Horia
A38: Petronela-Bianca Pavel (ULBS) Ellena Diacu (Politehnica, București) Constantin Horia Barbu (ULBS), MarkusPuschenreiter (BOKU, Viena) Walter W.Wenzel (BOKU, Viena) | B38: FSAA2 | C38: Aided phytostabilization using Miscanthus sinensis x giganteus on heavy metal-contaminated soils. Science of the Total Environment, 479, 2014, 125–131. | D38: Grzegorska, A; Rybarczyk, P, Rogala, A; Zabrocki, D, Phytoremediation—From Environment Cleaning to Energy Generation—Current Status and Future Perspectives, Energies 2020, 13(11), 2905; | E38: https://www.mdpi.com/1996-1073/13/11/2905/htm | F38: WOS:000545401100232 | G38: 50 | H38: 16.67 | I38: Barbu Horia
A39: Pavel, Petronela-Bianca (ULBS); Diacu, E (Politehnica, București; Barbu, CH (ULBS) | B39: FSAA2 | C39: Long-term Effects on the Fractionation and Mobility of Heavy Metals in a Polluted Soil Treated with Bauxite Residues | D39: Al Shamari, YMG; Alwarthan, AA; Wabaidur, SM; Khan, MA; Alqadami, AA; Siddiqui, MR, New Ultra Performance liquid chromatography-mass spectrometric method for the determination of allura red in soft drinks using corncob as solid phase extraction sorbent: Analysis and food waste management approach, JOURNAL OF KING SAUD UNIVERSITY SCIENCE Volume: 32 Issue: 1 Pages: 1135-1141 Published: JAN 2020 | E39: DOI: 10.1016/j.jksus.2019.10.011 https://www.researchgate.net/publication/337140655 | F39: WOS:000506167000163 | G39: 50 | H39: 16.67 | I39: Barbu Horia
A40: Blaj R, Stanciu M, Sand C, Barbu H, Ciortea G | B40: FSAA2 | C40: (2013). Pollution effects on forest vegetation and ecological reconstruction in Copsa Mica, Romania. International Multidisciplinary Scientific GeoConference: SGEM 1:735 | D40: ADEA, S. L., IONETE, R. E., COSTINEL, D., NECHITA, C., BOTU, M., & BOTORAN, O. R. (2020). Changes of carbon-isotope ratios in soil organic matter relative to parent vegetation and site specificity. Notulae Botanicae Horti Agrobotanici Cluj-Napoca, 48(4), 2085-2094. | E40: https://doi.org/10.15835/nbha48412138 | F40: WoS | G40: 50 | H40: =G40/5 -> 10 | I40: Barbu Horia
A41: CH Barbu, BP Pavel, C Sand, B Grama, MR Pop | B41: FSAA2 | C41: Miscanthus sinensis x giganteus cultivated on soils polluted with heavy metals–a valuable replacement for coal | D41: Violina ANGELOVA, Phytoremediation Potential Of Miscanthus X Giganteus In Soil Contaminated With Heavy Metals, Scientific Papers. Series E. Land Reclamation, Earth Observation & Surveying, Environmental Engineering. Vol. IX, 2020 Print ISSN 2285-6064, CD-ROM ISSN 2285-6072, Online ISSN 2393-5138, ISSN-L 2285-606 | E41: http://landreclamationjournal.usamv.ro/pdf/2020/Art4.pdf | F41: WOS:000574608100004 | G41: 50 | H41: =G41/5 -> 10 | I41: Barbu Horia
A42: Barbu, C.H., Pavel, B.P., Sand, C., Pop, M.R | B42: FSAA2 | C42: Miscanthus sinensis gigantheus’ behaviour on soils polluted with heavy metals. | D42: Violina ANGELOVA, Phytoremediation Potential Of Miscanthus X Giganteus In Soil Contaminated With Heavy Metals, Scientific Papers. Series E. Land Reclamation, Earth Observation & Surveying, Environmental Engineering. Vol. IX, 2020 Print ISSN 2285-6064, CD-ROM ISSN 2285-6072, Online ISSN 2393-5138, ISSN-L 2285-606 | E42: http://landreclamationjournal.usamv.ro/pdf/2020/Art4.pdf | F42: WOS:000574608100004 | G42: 50 | H42: =G42/4 -> 12.5 | I42: Barbu Horia
A43: CH Barbu, Bianca Petronela Pavel, C Sand, MR Pop | B43: FSAA2 | C43: Miscanthus sinensis giganteus behavour on soil polluted with heavy metals: Metal Elements in Environment, Medicine and Biology | D43: Zeljka Zgorelec, Nikola Bilandzija, Kristina Knez, MarijaGalic & Silva Zuzul, Cadmium and Mercury phytostabilization from soil using Miscanthus × giganteus, Scientific Reports (Nature Publisher Group); SCIENTIFIC REPORTS, Volume: 10 Issue: 1, Article Number: 6685, Published: APR 21 2020 | E43: DOI: 10.1038/s41598-020-63488-5 https://search.proquest.com/openview/3b595cb51ae5d03316efba9590cdbd40/1?pq-origsite=gscholar&cbl=2041939 | F43: WOS:000559762800009 | G43: 50 | H43: =G43/4 -> 12.5 | I43: Barbu Horia
A44: Marculescu, A., C. Sand, C. Barbu, H.D. Babit and D. Hanganu | B44: FSAA2 | C44: Possibilities of influencing the biosynthesis and accumulation of the active principals in Chrysanthemum balsamita L. specie Roum. Biotech. Lett., 7 (1): 2002 | D44: Nutrient Management Options For Improving Growth, Yield And Quality Of Snap Bean (Phaseolus Vulgaris L.) In Embu County DN Kondo – 2019 teza de doctorat. | E44: http://erepository.uonbi.ac.ke/bitstream/handle/11295/108450/Kondo_Nutrient%20Management%20Options%20For%20Improving%20Growth%2C%20Yield%20And%20Quality%20Of%20Snap%20Bean%20%28Phaseolus%20Vulgaris%20L.%29%20In%20Embu%20County.pdf?sequence=1&isAllowed=y | F44: Google Scholar | G44: 15 | H44: 3 | I44: Barbu Horia
A45: Marculescu, A., C. Sand, C. Barbu, H.D. Babit and D. Hanganu | B45: FSAA2 | C45: Possibilities of influencing the biosynthesis and accumulation of the active principals in Chrysanthemum balsamita L. specie Roum. Biotech. Lett., 7 (1): 2002 | D45: Hoda I. Ahmed, Improving Snap Bean Yield and Quality Through Organic Fertilizer additives and Citric Acid Spraying under Newly Reclaimed Land Conditions Journal of Plant Production, Volume 11, Issue 2, February 2020, Page 113-118 | E45: DOI: 10.21608/jpp.2020.79104 | F45: WoS TR | G45: 50 | H45: 10 | I45: Barbu Horia
A46: Ruth N Hull (Canada), Constantin-Horia Barbu, Nadezhda Goncharova (Belarus) | B46: FSAA2 | C46: Strategies to Enhance Environmental Security in Transition Countries, 2007 | D46: Xiuge Zhao, Zhenglei Li, Yan Tao, Danlu Wang, Ju Huang, Feiyang Qiao, Limin Lei, Qian Xing, Distribution characteristics, source appointment, and health risk assessment of Cd exposure via household dust in six cities of China, Building and Environment, Volume 172, 2020, ISSN 0360-1323, | E46: https://doi.org/10.1016/j.buildenv.2020.106728. (https://www.sciencedirect.com/science/article/pii/S036013232030086X) | F46: WoSTR | G46: 50 | H46: 50 | I46: Barbu Horia
A47: T. Vintila, A. Negrea, H. Barbu, R. Sumalan, and K. Kovacs (Univ. Szeged - HU) | B47: FSAA2 | C47: Metal distribution in the process of lignocellulosic ethanol production from heavy metal contaminated sorghum biomass. J Chem Technol Biotechnol., 2016 | D47: Xiang, C., Tian, D., Wang, W. et al. Fates of Heavy Metals in Anaerobically Digesting the Stover of Grain Sorghum Harvested from Heavy Metal-Contaminated Farmland. Waste Biomass Valorization 11, 1239–1250 (2020). | E47: https://doi.org/10.1007/s12649-018-0455-y | F47: WoSTR | G47: 50 | H47: 12.5 | I47: Barbu Horia
A48: T. Vintila, A. Negrea, H. Barbu, R. Sumalan, and K. Kovacs (Univ. Szeged - HU) | B48: FSAA2 | C48: Metal distribution in the process of lignocellulosic ethanol production from heavy metal contaminated sorghum biomass. J Chem Technol Biotechnol., 2016 | D48: Shili Shen, Jinquan Chen, Junjun Chang & Beicheng Xia (2020) Using bioenergy crop cassava (Manihot esculenta) for reclamation of heavily metal-contaminated land, International Journal of Phytoremediation, 22:12, 1313-1320, | E48: DOI: 10.1080/15226514.2020.1768512 | F48: WoSTR | G48: 50 | H48: 12.5 | I48: Barbu Horia
A49: T. Vintila, A. Negrea, H. Barbu, R. Sumalan, and K. Kovacs (Univ. Szeged - HU) | B49: FSAA2 | C49: Metal distribution in the process of lignocellulosic ethanol production from heavy metal contaminated sorghum biomass. J Chem Technol Biotechnol., 2016 | D49: V. Garcia-Montoto. Speciation analysis in renewable feedstocks and petroleum heavy oil fractions. Analytical chemistry. Université de Pau et des Pays de l'Adour, 2020. | E49: https://tel.archives-ouvertes.fr/tel-03007872/ | F49: Google Scholar | G49: 15 | H49: 3.75 | I49: Barbu Horia
A50: Mihai Radu POP, Camelia Sand, Dana BOBIŢ, Maria Mihaela ANTOFIE, C Horea BARBU, Bianca-Petronela PAVEL, Leon MUNTEAN, Mircea SAVATTI | B50: FSAA2 | C50: Studies Concerning The Production Of Volatile Oil, Rhizomes And Roots, To Different Genotypes Of Valeriana Officinalis | D50: Marjan Diyanat Sara Baziar , The effect of weed control on growth, yield and physicochemical properties of valerian (Valeriana officinalis L.), Journal of Research in Weed Science Volume 3 Issue 4 (2020), pp 420-435 | E50: http://www.jrweedsci.com/article_103976_d8ed1bd9b1a9e7cff6844198d97c0ad4.pdf | F50: WoS TR | G50: 15 | H50: 1.67 | I50: Barbu Horia
A51: MR POP* , C. SAND* , H. BARBU* , M. BALAN**, A. GRUSEA*** , H. BOERIU**, A. POPA* | B51: FSAA2 | C51: Correlations between productivity elements in Lolium perenne L. species for new varieties resistant to drought , Analele Univ. Oradea, 2010 | D51: Vigor inicial de cuatro variedades de trigo (Triticum aestivum L.) y su incidencia en la habilidad competitiva de ryegrass perenne (Lolium perenne L.) resistente a glifosato M Sánchez - 2020 - sedici.unlp.edu.ar | E51: https://doi.org/10.35537/10915/101503 | F51: Google Scholar | G51: 15 | H51: 2.1 | I51: Barbu Horia
A52: MR POP* , C. SAND* , H. BARBU* , M. BALAN**, A. GRUSEA*** , H. BOERIU**, A. POPA* | B52: FSAA2 | C52: Correlations between productivity elements in Lolium perenne L. species for new varieties resistant to drought , Analele Univ. Oradea, 2010 | D52: GALUSSI, Alberto Aníbal et al. Atributos de la inflorescencia y disemínulos de Chascolytrum subaristatum (Lam.) Desv. Pastos y Forrajes [online]. 2020, vol.43, n.2 [citado 2021-02-13], pp.129-135. >. ISSN 0864-0394. | E52: <http://scielo.sld.cu/scielo.php?script=sci_arttext&pid=S0864-03942020000200129&lng=es&nrm=iso | F52: Google Scholar | G52: 15 | H52: 2.1 | I52: Barbu Horia
A53: Ruth N Hull (Canada), Constantin-Horia Barbu, Nadezhda Goncharova (Belarus) | B53: FSAA2 | C53: Strategies to Enhance Environmental Security in Transition Countries, 2007 | D53: [1] IVANČÍK, R., BARIČIČOVÁ, Ľ. 2020 Gnozeologické pramene skúmania bezpečnosti v 21. storočí. APZ Bratislava: Policajná teoria a prax 2/2020. ISBN 1335-1370. EAN. 1335-1370 | E53: https://www.akademiapz.sk/sites/default/files/PTP/2-2020/003%20%20IVAN%C4%8C%C3%8DK%2C%20BARI%C4%8CI%C4%8COV%C3%81%20%20Gnozeologick%C3%A9%20pramene%20sk%C3%BAmania%20bezpe%C4%8Dnosti%20v%2021.%20storo%C4%8D%C3%AD_EDITED_2.pdf | F53: Google Scholar | G53: 15 | H53: 15 | I53: Barbu Horia
A54: Marculescu, A., C. Sand, C. Barbu, H.D. Babit and D. Hanganu | B54: FSAA2 | C54: Possibilities of influencing the biosynthesis and accumulation of the active principals in Chrysanthemum balsamita L. specie Roum. Biotech. Lett., 7 (1): 577-548, 2002 | D54: Portnyagina N.V., Punegov V.V., Echishvili E.E., et al. Morphological features of the plant Pyrethrum majus (Desf.) Tzvel. and variability of the component composition of essential oil during introduction in the North-East of the European part of Russia // Samara Journal of Science. - 2020. - Vol. 9. - N. 4. - P. 142-148. | E54: doi: 10.17816/snv202094121 | F54: Google Scholar | G54: 15 | H54: 3 | I54: Barbu Horia
A55: MM Antofie, I Barbu, CS Sand, R Blaj | B55: FSAA2 | C55: Traditional orchards in Romania: case study Fântânele, Sibiu County | D55: H Žarnovičan, J Kollár, V Falťan, F Petrovič, M Gábo | E55: https://scholar.google.com/scholar?as_ylo=2020&hl=ro&as_sdt=2005&sciodt=0,5&cites=3228349483860251177&scipsc= | F55: WWW.GOOGLEACADEMIC.COM | G55: 15 | H55: 12.5 | I55: Barbu Ion
... A65: Blaj Robert | B65: FSAA2 | C65: 2013, Green economy - the economy of the future. Scientific Papers Series Management, Economic Engineering in Agriculture and Rural Development, 13 (4):63-68. | D65: Elena DELIAN, STOMATA-A KEY FACTOR WITH MULTIPLE FUNCTIONS IN THE CONDITIONS OF GLOBAL CLIMATE CHANGE: A BRIEF OVERVIEW, Scientific Papers Series Management, Economic Engineering in Agriculture and Rural Development Vol. 20, Issue 1, 2020, 151-160 | E65: http://managementjournal.usamv.ro/pdf/vol.20_1/Art21.pdf | F65: WoS | G65: 50 | H65: 50 | I65: Blaj Robert
A66: E VECHIU(INCDS), L DINCĂ (INCDS), I BRATU (Univ. "Lucian Blaga") | B66: FSAA2 | C66: The characteristics of Polygonum plants present in the Alexandru Beldie Herbarium. | D66: CURIOSITIES ABOUT THE ARTEMISIA COLLECTIONS FROM “ALEXANDRU BELDIE” HERBARIUM. ILIE-COSMIN CÂNTAR, MARIA DINCĂ, Annals of the University of Craiova - Agriculture, Montanology, Cadastre Series | E66: http://anale.agro-craiova.ro/index.php/aamc/article/view/921 | F66: EBSCO, IndexCopernicus | G66: 15 | H66: =G66/3 -> 5 | I66: Bratu Alexandru
A67: E VECHIU(INCDS), L DINCĂ (INCDS), I BRATU (Univ. "Lucian Blaga") | B67: FSAA2 | C67: The characteristics of Polygonum plants present in the Alexandru Beldie Herbarium. | D67: HERBORIZED PLANTS FROM ARCTIUM GENUS, RALUCA ENESCU, MARIA DINCA, Annals of the University of Craiova - Agriculture, Montanology, Cadastre Series, 2020 | E67: http://anale.agro-craiova.ro/index.php/aamc/article/view/924 | F67: EBSCO, IndexCopernicus | G67: 15 | H67: =G67/3 -> 5 | I67: Bratu Alexandru
A68: I Blada, Ş Tănasie, C Dinu, I Bratu | B68: FSAA2 | C68: Plantaţia experimentală cu Pinus cembra şi P. mugo de pe Halda Dumitrelul din Munţii Călimani, 2013 Jurnal Revista de Silvicultură şi Cinegetică, Anul XVIII Numărul 32, P.110-116 | D68: CERTAN CORINA PARTICULARITĂȚILE RESTABILIRII ECOSISTEMULUI PETROFIT (PE EXEMPLUL CARIEREI DE CALCAR „LAFARGE CIMENT” (MOLDOVA) S.A.) | E68: http://www.cnaa.md/files/theses/2020/56410/corina_certan_thesis.pdf | F68: Google Scholar | G68: 15 | H68: 3.75 | I68: Bratu Alexandru
A69: VECHIU E., DINCĂ L., BRATU I., | B69: FSAA2 | C69: The characteristics of Polygonum plants present in the Alexandru Beldie Herbarium. | D69: ASTER Genus in “ALEXANDRU BELDIE” Herbarium from “MARIN DRĂCEA” National Institute for Research and Development in Forestry Ciontu C. I.1 *, DINCĂ Maria, JOURNAL of Horticulture, Forestry and Biotechnology, Volume 24(4), 2020 | E69: https://journal-hfb.usab-tm.ro/2020/JHFB%202020%20Vol%20IV/03Ciontu%20C.I.%20Maria%20Dinca%20publishing.pdf | F69: Copernicus, Google Scholar | G69: 15 | H69: 5 | I69: Bratu Alexandru
A70: E VECHIU(INCDS), L DINCĂ (INCDS), I BRATU (Univ. "Lucian Blaga") | B70: FSAA2 | C70: The characteristics of Polygonum plants present in the Alexandru Beldie Herbarium. | D70: THE PRESENCE OF ASPLENIUM GENUS IN “ALEXANDRU BELDIE” HERBARIUM FROM “MARIN DRĂCEA” NATIONAL INSTITUTE FOR RESEARCH AND DEVELOPMENT IN FORESTRY, Ciontu CI, Dinca M., Research Journal of Agricultural Science, 2020 | E70: https://www.rjas.ro/paper_detail/3161 | F70: EBSCO, IndexCopernicus | G70: 15 | H70: =G70/3 -> 5 | I70: Bratu Alexandru
A71: Bratu Iulian (Univ. Lucian Blaga) | B71: FSAA2 | C71: Open source solutions to improve the quality of sustainable forest management | D71: THE MAIN CHARACTERISTICS OF AGRICULTURE AND RURAL DEVELOPMENT IN THE CENTRAL REGION OF ROMANIA, M.caratus, Scientific Papers Series Management, Economic Engineering in Agriculture and Rural Development, 2020 Scientific Papers: Management, Economic Engineering in Agriculture & Rural Development | E71: https://apps.webofknowledge.com/full_record.do?product=WOS&search_mode=GeneralSearch&qid=16&SID=D3F1TwXx17lJ8tMpHaE&page=1&doc=1 | F71: WoS | G71: 50 | H71: 50 | I71: Bratu Alexandru
A72: Blaj R, Stanciu M, Sand C, Barbu H, Ciortea G | B72: FSAA2 | C72: Pollution effects on forest vegetation and ecological reconstruction in Copsa Mica, Romania. | D72: Changes of carbon-isotope ratios in soil organic matter relative to parent vegetation and site specificity By: Badea, Silviu L.; Ionete, Roxana E.; Costinel, Diana; et al. NOTULAE BOTANICAE HORTI AGROBOTANICI CLUJ-NAPOCA Volume: ‏ 48 Issue: ‏ 4 Pages: ‏ 2085-2094 Published: ‏ OCT-DEC 2020 | E72: https://www.notulaebotanicae.ro/index.php/nbha/article/view/12138 | F72: WoS/SCOPUS | G72: 50 | H72: 10 | I72: Caratus Mirela
A73: Antonie I., Stanciu M., Sand C., Blaj R., | B73: FSAA2 | C73: 2012 - The researches regarding the biodiversity of the entomologic of the corn cultures in the Sibiu county. Scientific Papers, Series Management, Economy. Engineering. in Agriculture and Rural Development, 12 (1):5-10 | D73: RESULTS CONCERNING TANYMECUS DILATICOLLIS CONTROL IN A COMMERCIAL FARM FROM THE SOUTH-EAST OF ROMANIA, IN THE CONDITIONS OF THE YEAR 2020 Emil GEORGESCU1 , Alina CRETU2 , Cristina RADU2 , Lidia CANA, Lucrări Ştiinţifice – vol. 63(2)/2020, seria Agronomie | E73: https://repository.uaiasi.ro/xmlui/bitstream/handle/20.500.12811/1102/LSA_v.63_nr.2_Results....pdf?sequence=1 | F73: google academic | G73: 15 | H73: 3.75 | I73: Caratus Mirela
A74: Vidu L., Băcilă V., Udroiu A., Popa R., Popa D., Stanciu M., Tudorache M., Custură I., | B74: FSAA2 | C74: 2014: Study regarding the production performance of Montbeliarde dairy cows in the southern area of Romania, Scientific Papers. Series D. Animal Science, LVII, 216-220. | D74: QUALITY OF RAW MILK OBTAINED FROM BROWN BREED EXPLOITED IN VRANCEA COUNTY P. Avram1 , C.E. Nistor2*, B.V. Avarvarei2 , A., Usturoi2 , I. Gîlcă2, Scientific Papers-Animal Science Series: Lucrări Ştiinţifice - Seria Zootehnie, vol. 73 | E74: https://repository.uaiasi.ro/xmlui/bitstream/handle/20.500.12811/1125/LSZ_v.73_Quality%20of.pdf?sequence=1 | F74: GOOGLE ACADEMIC | G74: 15 | H74: 1.88 | I74: Caratus Mirela
A75: Cărătuș Stanciu Mirela | B75: FSAA2 | C75: ASPECTS OF SUSTAINABLE RURAL TOURISM - FARMERS' MARKETS AND FARM VISITS | D75: Kinga Xenia HAVADI-NAGY, FOOD IN TOURISM. RELEVANT RESEARCH ANGLES AND TOPICS, TERRITORIAL IDENTITY AND DEVELOPMENT, Volume 5 / No. 1, Spring 2020, p. 21-36 | E75: http://territorial-identity.ro/wp-content/uploads/2020/09/2_Havadi-Nagy_TID_1_2020.pdf | F75: gogle academic | G75: 15 | H75: 15 | I75: Caratus Mirela
A76: Cărătuș Stanciu Mirela | B76: FSAA2 | C76: ASPECTS OF SUSTAINABLE RURAL TOURISM - FARMERS' MARKETS AND FARM VISITS | D76: Farmers' markets and tourism: Identifying tensions that arise from balancing dual roles as community events and tourist attractions By: Thompson, Michelle JOURNAL OF HOSPITALITY AND TOURISM MANAGEMENT Volume: ‏ 45 Pages: ‏ 1-9 Published: ‏ DEC 2020 | E76: https://www.sciencedirect.com/science/article/abs/pii/S1447677020301698 | F76: WoS | G76: 50 | H76: 50 | I76: Caratus Mirela
A77: Stanciu, M., Tanase, M., Vlad, I., Antonie, I.,Gaureanu, M., | B77: FSAA2 | C77: Organic dairy sheep farms in Sibiu county, Romania: typologies according to livestock management. | D77: SCIENTIFIC BASICS AND PROSPECTS OF DEVELOPMENT OF PRODUCTION OF ORGANIC ANIMAL PRODUCTS IN RUSSIA By: Chernyaev, Anatoliy Alekseevich; Serdobintsev, Dmitriy Valerevich; Kudryashova, Ekaterina Vladimirovna SCIENTIFIC PAPERS-SERIES MANAGEMENT ECONOMIC ENGINEERING IN AGRICULTURE AND RURAL DEVELOPMENT Volume: ‏ 20 Issue: ‏ 2 Pages: ‏ 117-125 Published: ‏2020 | E77: http://managementjournal.usamv.ro/pdf/vol.20_2/Art15.pdf | F77: WoS | G77: 50 | H77: 10 | I77: Caratus Mirela
A78: Găureanu M.E., Cărătuş Stanciu M., Cocîrcă D.I., Vidu L., Vlad I., | B78: FSAA2 | C78: Technical aspects regarding the classification of pig carcasses in Romania. Scientific Papers Series Management, Economic Engineering in Agriculture and Rural Development, 17(3):139-146 | D78: THE INFLUENCE OF TREATMENTS WITH SYNTHETIC HORMONES ON THE REPRODUCTIVE PERFORMANCE OF YOUNG SOWS EXPLOITED FOR THE PRODUCTION OF BACON By: Arsinte, Paul Rares; Hoha, Gabriel Vasile; Nistor, Catalin Emilian; et al. SCIENTIFIC PAPERS-SERIES D-ANIMAL SCIENCE Volume: ‏ 63 Issue: ‏ 1 Pages: ‏ 297-300 Published: ‏ 2020 | E78: http://animalsciencejournal.usamv.ro/pdf/2020/issue_1/Art42.pdf | F78: WOS | G78: 50 | H78: 8.33 | I78: Caratus Mirela
A79: Găureanu M.E., Cărătuş Stanciu M., Cocîrcă D.I., Vidu L., Vlad I., | B79: FSAA2 | C79: Technical aspects regarding the classification of pig carcasses in Romania. Scientific Papers Series Management, Economic Engineering in Agriculture and Rural Development, 17(3):139-146 | D79: CURRENT PERSPECTIVES FOR MANGALICA AND BAZNA PIGS BREEDING FOR EFFICIENT BIODIVERSITY MANAGEMENT, GENETIC CONSERVATION AND ANIMAL IMPROVEMENT IN ROMANIA By: Sonea, C. G.; Socol, Claudia Terezia; Criste, Florin-Leontin REVISTA ROMANA DE MEDICINA VETERINARA Volume: ‏ 30 Issue: ‏ 1 Pages: ‏ 29-33 Published: ‏ 2020 | E79: https://agmv.ro/wp-content/uploads/2020/03/29_33_Sonea_5_compressed.pdf | F79: Wos | G79: 50 | H79: 10 | I79: Caratus Mirela
A80: Cărătuș Stanciu Mirela, Găureanu Monica, Burtea Carmen, Vidu Livia, Vlad I., Cărătuș N. | B80: FSAA2 | C80: THE DYNAMICS OF PIG CARCASSES CLASSIFICATION IN ROMANIA BETWEEN 2009-2015, BY MANUAL METHOD THE ZWEI PUNKTE, SCIENTIFIC PAPERS-SERIES MANAGEMENT ECONOMIC ENGINEERING IN AGRICULTURE AND RURAL DEVELOPMENt, Volume: 17 Issue: 4 Pages: 85-89 Published: 2017 | D80: CURRENT PERSPECTIVES FOR MANGALICA AND BAZNA PIGS BREEDING FOR EFFICIENT BIODIVERSITY MANAGEMENT, GENETIC CONSERVATION AND ANIMAL IMPROVEMENT IN ROMANIA By: Sonea, C. G.; Socol, Claudia Terezia; Criste, Florin-Leontin REVISTA ROMANA DE MEDICINA VETERINARA Volume: ‏ 30 Issue: ‏ 1 Pages: ‏ 29-33 Published: ‏ 2020 | E80: https://agmv.ro/wp-content/uploads/2020/03/29_33_Sonea_5_compressed.pdf | F80: Wos | G80: 50 | H80: 8.33 | I80: Caratus Mirela
A81: Cărătuș Stanciu Mirela, Găureanu Monica, Burtea Carmen, Vidu Livia, Vlad I., Cărătuș N. | B81: FSAA2 | C81: THE DYNAMICS OF PIG CARCASSES CLASSIFICATION IN ROMANIA BETWEEN 2009-2015, BY MANUAL METHOD THE ZWEI PUNKTE, SCIENTIFIC PAPERS-SERIES MANAGEMENT ECONOMIC ENGINEERING IN AGRICULTURE AND RURAL DEVELOPMENt, Volume: 17 Issue: 4 Pages: 85-89 Published: 2017 | D81: THE INFLUENCE OF TREATMENTS WITH SYNTHETIC HORMONES ON THE REPRODUCTIVE PERFORMANCE OF YOUNG SOWS EXPLOITED FOR THE PRODUCTION OF BACON By: Arsinte, Paul Rares; Hoha, Gabriel Vasile; Nistor, Catalin Emilian; et al. SCIENTIFIC PAPERS-SERIES D-ANIMAL SCIENCE Volume: ‏ 63 Issue: ‏ 1 Pages: ‏ 297-300 Published: ‏ 2020 | E81: http://animalsciencejournal.usamv.ro/pdf/2020/issue_1/Art42.pdf | F81: WOS | G81: 50 | H81: 8.33 | I81: Caratus Mirela
A82: Cărătuș Stanciu Mirela | B82: FSAA2 | C82: Analysis of the behavior and motivation of consumers towards short food supply chains. Scientific Papers Series Management, Economic Engineering in Agriculture and Rural Development, 18(4): 73-77. | D82: CONSUMERS' PREFERENCES FOR PLACES TO PURCHASE LOCAL DAIRY PRODUCTS By: Kusz, Bozena; Kilar, Janusz AGROLIFE SCIENTIFIC JOURNAL Volume: ‏ 9 Issue: ‏ 1 Pages: ‏ 198-204 Published: ‏ JUN 2020 | E82: http://agrolifejournal.usamv.ro/pdf/vol.IX_1/Art26.pdf | F82: WOS | G82: 50 | H82: 50 | I82: Caratus Mirela
... A87: I. Vlad P. Nistoreanu, Marinela Ghereș, Gh. Săvoiu, Mariana Bănuță, Raluca Ciornea, V. Crăciuneanu, Victoria Firescu, Alexandra Grozan, R. Hornoiu, F.L. Isac, I. Plăiaș, Iuliana Pop, S. Rusu, Mirela Stanciu, M. Țaicu, M.O. Tănase, D. Ungureanu | B87: FSAA2 | C87: Turism rural. Tratat. Editura C.H. Beck, București, 2010. | D87: Petelca, Oleg; Garbuz, Veronica, Social and economic effects of rural tourism on the development of rural areas, CES Working Papers; Volume XII, Issue 2, p. 123-143, Iasi, 2020. https://search.proquest.com/docview/2452330348/fulltextPDF/EFB91AD342644B3PQ/1?accountid=8083 | E87: https://search.proquest.com/docview/2452330348/fulltextPDF/E3BF27DA72C04344PQ/1?accountid=8083 | F87: google academic | G87: 15 | H87: 0.83 | I87: Caratus Mirela
A88: Cărătuș Stanciu Mirela | B88: FSAA2 | C88: Research regarding consumers attitude, in relation with poultry meat purchase and consumption. Case study Sibiu, Romania Scientific Papers SeriesManagement, Economic Engineering in Agriculture and Rural Development Vol. 20, Issue 1, 2020, p. 125-130 | D88: 1035.[Анализ потребительского поведения покупателей мяса птицы в жудеце Сибиу, Румыния]. Stanciu M. Research regarding consumers attitude, in … АН Дунаев - Пищевая и перерабатывающая промышленность …, 2020 - elibrary.ru Дунаев А.Н.//Пищевая и перерабатывающая промышленность. Реферативный журнал, 2020. | F88: google academic | G88: 15 | H88: 15 | I88: Caratus Mirela
A89: Cărătuș Stanciu Mirela | B89: FSAA2 | C89: Research regarding consumers attitude, in relation with poultry meat purchase and consumption. Case study Sibiu, Romania Scientific Papers SeriesManagement, Economic Engineering in Agriculture and Rural Development Vol. 20, Issue 1, 2020, p. 125-130 | D89: 766.[Анализ потребительского поведения покупателей мяса птицы в жудеце Сибиу, Румыния]. Stanciu M. Research regarding consumers attitude, in … АН Дунаев - Экономика сельского хозяйства. Реферативный …, 2020 - elibrary.ru Дунаев А.Н.//Экономика сельского хозяйства. Реферативный журнал, 2020. | F89: google academic | G89: 15 | H89: 15 | I89: Caratus Mirela
A90: Stanciu, M., Ciortea, G., Sand, C., Vlad, I., Antonie, I., Tanase, M., Blaj, R., | B90: FSAA2 | C90: Assessments regarding sustainable development on ecoeconomic and bioeconomic principles, of the local communities in the sheep breeding villages from “Drumul Regelui” (King's Road), Scientific Papers Series Management, Economic Engineering in Agriculture and Rural Development Vol.12(3), 167-174., 2012 | D90: POSSIBILITIES OF DEVELOPMENT OF THE SLOW TOURISM CONCEPT IN ROMANIA Alina MARCUTA, Liviu MARCUTA, Agatha POPESCU, Cristina TINDECHE, Valentina TUDOR, Dragos SMEDESCU, Scientific Papers Series Management, Economic Engineering in Agriculture and Rural Development Vol. 20, Issue 4, 2020 | E90: http://www.managementjournal.usamv.ro/pdf/vol.20_4/Art40.pdf | F90: WOS | G90: 50 | H90: 7.14 | I90: Caratus Mirela
A91: Mirela STANCIU | B91: FSAA2 | C91: Analysis of touristic development potential of some Natura 2000 sites. Data publicării 2014/1/1 Jurnal Scientific Papers: Management, Economic Engineering in Agriculture & Rural Development Volumul 14, Numărul 1 | D91: Tourism development in Natura 2000 areas: lessons for Turkey. Gök, Ayhan Dalarna University, School of Technology and Business Studies, Tourism Studies. 2020 (English) | E91: https://www.diva-portal.org/smash/record.jsf?pid=diva2%3A1507896&dswid=-8959 | F91: google academic | G91: 15 | H91: 15 | I91: Caratus Mirela
A92: Răducuţă, I., Marmandiu, A., Stanciu, M., Cristian, C. | B92: FSAA2 | C92: (2007). The evolution of livestock, milk and goat cheese production in the European countries. Acta Universitatis Cibiniensis, Agricultural Sciences, 1 (7), 127‒134. | D92: DYNAMIC OF BODY WEIGHT EVOLUTION OF CARPATHIAN KIDS GOAT AND KIDS BREED GOAT (♂SAANEN X ♀CARPATHIAN) FROM BIRTH TO WEANING Alexandra MARINA, Stelian DĂRĂBAN, Radu CONSTANTINESCU, Daniel COCAN, Camelia RĂDUCU, Călin LAŢIU, Paul UIUIU, Cătălin AVRAM, Vioara MIREŞAN, Scientific Papers. Series D. Animal Science. Vol. LXIII, No. 1, 2020 | E92: http://animalsciencejournal.usamv.ro/pdf/2020/issue_1/Art44.pdf | F92: WOS | G92: 50 | H92: 12.5 | I92: Caratus Mirela
A93: Antonie Iuliana, T Manole, Stanciu Mirela, Sand Camelia | B93: FSAA2 | C93: The Impact of the Agricultural Technology upon the Biodiversity of the Arthropods Present in the Corn Culture in Sibiu County, JOURNAL of Horticulture, Forestry and Biotechnology, Volumul 16, Numărul 3, 7-12, 2012 | D93: CHARACTERISTICS OF FOREST SOILS FROM SIBIU COUNTY Lucian Dincă, Studii şi Cercetări Martie 2020 Biologie 29/1 27-30 Universitatea”Vasile Alecsandri” din Bacău, | E93: file:///C:/Users/cnick_hpylj2x/Downloads/SCSB202001V29S01A0004.pdf | F93: google academic | G93: 15 | H93: 3.75 | I93: Caratus Mirela
A94: Chicea D., Indrea E., Crețu C.M. | B94: FSAA2 | C94: Assesing Fe3O4 nanoparticle size by DLS, XRD and AFM, Journal of Optoelectronics and Advanced Materials, 14(5-6), 2012, 460-466 | D94: Garces Guamba N.B., Morillo Morales B.A.,Estudio de la adsorcion de cinc mediante el uso del composito magnetita/oxido de grafeno para su remocion en aguas sinteticas, bib digital.epn.edu.ec, 2020 | E94: https://bibdigital.epn.edu.ec/handle/15000/20660 | F94: http://scholar.google.ro | G94: 15 | H94: 5 | I94: Cretu Monica
A95: Chicea D., Indrea E., Crețu C.M. | B95: FSAA2 | C95: Assesing Fe3O4 nanoparticle size by DLS, XRD and AFM, Journal of Optoelectronics and Advanced Materials, 14(5-6), 2012, 460-466 | D95: Nayak B., Misra P.K., Exploration of the structural and dielectric characteristics of a potent hydroxyapatite coated gallium bioceramics for the forthcoming biomedical and orthopedic applications, Materials Chemistry and Physics, 239, 2020. | E95: https://apps-webofknowledge-com.am.e-nformation.ro/full_record.do?product=WOS&search_mode=CitingArticles&qid=12&SID=C5P49fKGb4NolmiCD2Z&page=1&doc=2 | F95: https://webofknowledge.com | G95: 50 | H95: 16.67 | I95: Cretu Monica
A96: Chicea D., Goncea (Cretu) C.M. | B96: FSAA2 | C96: On aqueous Fe3O4 nanofluid in room temperature synthesis and physical properties, Optoelectronics and Advanced Materials, 3(3), 2009, 185-189 | D96: Abbaspour N., Haghshenasfard M., Talaei M.R., Amini H., Experimental investigation of using nanofluids in the gas absorption in a venturi scrubber equipped with a magnetic field, Journal of Molecular Liquids, 303, 2020. | E96: https://apps-webofknowledge-com.am.e-nformation.ro/full_record.do?product=WOS&search_mode=CitingArticles&qid=3&SID=C5P49fKGb4NolmiCD2Z&page=1&doc=1 | F96: https://webofknowledge.com | G96: 50 | H96: 16.67 | I96: Cretu Monica
A97: Letiţia Oprean, Ecaterina Lengyel and Ramona Iancu | B97: FSAA2 | C97: Monitoring and Evaluation of Timiş River (Banat, Romania) Water Quality Based on Physicochemical and Microbiological Analysis | D97: Ana-Maria Pană, Valentin Ordodi, Gerlinde Rusu, Vasile Gherman, Geza Bandur, Lucian-Mircea Rusnac andGabriela-Alina Dumitrel, Biodegradation Pattern of Glycopolymer Based on D-Mannose Oligomer and Hydroxypropyl Acrylate, Polymers 2020, 12(3), 704; https://doi.org/10.3390/polym12030704 | E97: https://www.mdpi.com/2073-4360/12/3/704 | F97: WOS | G97: 50 | H97: 16.66 | I97: Cristea Ramona
A98: Ramona IANCU, Letitia OPREAN, Viorela CODOI | B98: FSAA2 | C98: ORGANIC BEEKEEPING AND BEE PRODUCTS | D98: Ademe Mihiretu, Agazhe Tsegaye, Pedro González-Redondo, Efficiency of some common treatments on infestation level with wax moths, colony strength and honey yield in Northeast Ethiopia: Participatory and comparative analysis, Cogent Food & Agriculture Volume 6, 2020 - Issue 1, https://doi.org/10.1080/23311932.2020.1783172 | E98: https://www.tandfonline.com/doi/full/10.1080/23311932.2020.1783172 | F98: WOS | G98: 50 | H98: 16.66 | I98: Cristea Ramona
A99: RM Iancu | B99: FSAA2 | C99: The influence of microbiological quality of water resources in dairy goat farms | D99: Aileen Niroumand, Seyed Alireza Taghavi Razavizadeh, Abdollah Jamshidi, Jafar Attarbashi Moghadam, A Survey on Drinking Water Contamination to Indicator Bacteria in Dairy Farms of Mashhad Suburb, Volume 14, Issue 3, Summer 2020, Pages 251-259, DOI 10.22059/IJVM.2020.292106.1005041 | E99: https://ijvm.ut.ac.ir/article_78512.html | F99: BDI Index | G99: 15 | H99: 15 | I99: Cristea Ramona
A100: Oancea, S. (ULBS), Drǎghici, O.(ULBS) | B100: FSAA2 | C100: PH and thermal stability of anthocyanin-based optimised extracts of romanian red onion cultivars | D100: Mohamed Z. M. Salem, Ibrahim H. M. Ibrahim, Hayssam M. Ali Hany M. Helmy; Assessment of the Use of Natural Extracted Dyes and Pancreatin Enzyme for Dyeing of Four Natural Textiles: HPLC Analysis of Phytochemicals; Processes; 8, 1 | E100: https://www.mdpi.com/2227-9717/8/1/59/htm | F100: WOS:000516825300012 | G100: 50 | H100: =G100/2 -> 25 | I100: Draghici Olga
A101: S. Oancea, O. Draghici, O. Ketney | B101: FSAA2 | C101: Changes in total anthocyanin content and antioxidant activity in sweet cherries during frozen storage, and air-oven and infrared drying | D101: Faienza MF, Corbo F, Carocci A, Catalano A, Clodoveo ML, Grano M, Wang D Q-H, D'Amato G, Muraglia M, Franchini C, Brunetti G, Portincasa P; Novel insights in health-promoting properties of sweet cherries; Journal of Functional Foods 69 (2020) | E101: https://www.sciencedirect.com/science/article/pii/S1756464620301699?via%3Dihub | G101: 50 | H101: 16.67 | I101: Draghici Olga
A102: Oancea, S. (ULBS), Drǎghici, O.(ULBS) | B102: FSAA2 | C102: PH and thermal stability of anthocyanin-based optimised extracts of romanian red onion cultivars | D102: Jakkapon Phanthuwongpakdeeab, Sandhya Babela, Kritapas Laohhasurayotinc, Suchinda Sattayapornd, Tatsuo Kanekob; Anthocyanin based agricultural wastes as bio-adsorbents for scavenging radioactive iodide from aqueous environment; Journal of Environmental Chemical Engineering Volume 8, Issue 5, October 2020, 104147 | E102: https://www.sciencedirect.com/science/article/abs/pii/S2213343720304954 | G102: 50 | H102: 25 | I102: Draghici Olga
A103: Oancea, S. (ULBS), Drǎghici, O.(ULBS) | B103: FSAA2 | C103: PH and thermal stability of anthocyanin-based optimised extracts of romanian red onion cultivars | D103: A Omar, MS Ali, N Abd Rahim, Electron transport properties analysis of titanium dioxide dye-sensitized solar cells (TiO2-DSSCs) based natural dyes using electrochemical impedance spectroscopy concept: A review,Solar Energy 207 (2020) 1088–1121 | E103: https://www.sciencedirect.com/science/article/abs/pii/S0038092X2030760X | G103: 50 | H103: 25 | I103: Draghici Olga
A104: Oancea, S. (ULBS), Drǎghici, O.(ULBS) | B104: FSAA2 | C104: PH and thermal stability of anthocyanin-based optimised extracts of romanian red onion cultivars | D104: Punyachareonnon Ph.; Deerattrakul V.; Luepong K. The Influence of pH, Temperature and Time on Dyeing of Silk Fabric by Black Bean Anthocyanin-rich Extract as Colorant The Progress in Color, Colorants and Coatings 14(3), Page 179-187 | E104: http://pccc.icrc.ac.ir/article_81715_4135cea1bfd66786884d91a7083c4e73.pdf | G104: 50 | H104: =G104/2 -> 25 | I104: Draghici Olga
A105: S. Oancea, O. Draghici, O. Ketney | B105: FSAA2 | C105: Changes in total anthocyanin content and antioxidant activity in sweet cherries during frozen storage, and air-oven and infrared drying | D105: Василишина О.В., ОЦІНКА ЯКОСТІ ХАРЧОВИХ ПРОДУКТІВ ЗА АНТИОКСИДАНТНОЮ АКТИВНІСТЮ МЕТОДОМ FRAP, УНУС, 7.04.2020, pg.45 | E105: https://tzppo.udau.edu.ua/assets/files/1/zbirnik-konf.-7.04.2020-unus-thp.pdf#page=44 | G105: 15 | H105: =G105/3 -> 5 | I105: Draghici Olga
A106: O Drăghici, ML Păcală, S Oancea | B106: FSAA2 | C106: Kinetic studies on the oxidative stabilization effect of red onion skins anthocyanins extract on parsley (Petroselinum crispum) seed oil | D106: Jie Cai, Fansen Zeng, Shiyu Zheng, Xiaoxue Huang, Jingyi Zhang, Ping Zhang, and Peng Fei, Preparation of Lipid-Soluble Bilberry Anthocyanins through Acylation with Cinnamic Acids and their Antioxidation Activities, J. Agric. Food Chem. 2020, 68, 28, 7467–7473 | E106: https://www.scopus.com/results/citedbyresults.uri?sort=plf-f&cite=2-s2.0-85047560295&src=s&imp=t&sid=04869d0b0af40a00999345354642936c&sot=cite&sdt=a&sl=0&origin=inward&editSaveSearch=&txGid=faf5775260723163b0af2f21361683e5 | G106: 50 | H106: 16.67 | I106: Draghici Olga
A107: S. Oancea, O. Draghici | B107: FSAA2 | C107: Assessment of primary and secondary oxidation products during storage and heating of linseed oil enriched with natural extract Oxid. Commun., 40 (2017), pp. 138-148 | D107: Nupur Nagavekar, Rekha S.Singhal, Simultaneous extraction of flaxseed spice blend using supercritical carbon dioxide: Process optimization, bioactivity profile, and application as a functional seasoning, Separation and Purification Technology 248 (2020) 117030 | E107: https://www-sciencedirect-com.am.e-nformation.ro/science/article/pii/S1383586620315045?via%3Dihub | F107: WOS:000538827600041 | G107: 50 | H107: =G107/2 -> 25 | I107: Draghici Olga
A108: Aurelia Magdalena Pisoschi, Aneta POP, Universitate de Stiinte Agricole si medicina Veterninara, Bucuresti, Cecilia Georgescu, ULBS, Violeta Turcus, Neli Kinga Olah,Universitatea de Vest Vasile Goldis, Endre Mathe, Universitatea din Debrecen | B108: FSAA2 | C108: An overview of natural antimicrobials role in food | D108: INTERNATIONAL JOURNAL OF FOOD MICROBIOLOGY, Vol. 335, By:Yang, S; Li, J; Aweya, JJ; Yuan, ZJ; Weng, WY; Zhang, YL; Liu, GM; Antimicrobial mechanism of Larimichthys crocea whey acidic protein-derived peptide (LCWAP) against Staphylococcus aureus and its application in milk | E108: https://www.sciencedirect.com/science/article/abs/pii/S0168160520303858 | F108: WoS | G108: 50 | H108: 10 | I108: Georgescu Cecilia
A109: Aurelia Magdalena Pisoschi, Aneta POP, Universitate de Stiinte Agricole si medicina Veterninara, Bucuresti, Cecilia Georgescu, ULBS, Violeta Turcus, Neli Kinga Olah,Universitatea de Vest Vasile Goldis, Endre Mathe, Universitatea din Debrecen | B109: FSAA2 | C109: An overview of natural antimicrobials role in food | D109: Fractionation and Hydrolyzation of Avocado Peel Extract: Improvement of Antibacterial Activity, December 2020, Antibiotics 10(1):23, Igor A. Trujillo-Mayol,Nidia Casas Forero, Edgar Pastene | E109: https://www.researchgate.net/publication/348089719_Fractionation_and_Hydrolyzation_of_ | F109: WoS | G109: 50 | H109: 10 | I109: Georgescu Cecilia
A110: Aurelia Magdalena Pisoschi, Aneta POP, Universitate de Stiinte Agricole si medicina Veterninara, Bucuresti, Cecilia Georgescu, ULBS, Violeta Turcus, Neli Kinga Olah,Universitatea de Vest Vasile Goldis, Endre Mathe, Universitatea din Debrecen | B110: FSAA2 | C110: An overview of natural antimicrobials role in food | D110: Pyroligneous acid from Mimosa tenuiflora and Eucalyptus urograndis as an antimicrobial in dairy goats, December 2020Journal of Applied Microbiology, W.N.C. Soares, G.P.O. Lira, C.S. Santos, G.N. Dias, A.S. Pimenta, A.F. Pereira, L.D.M. Ben ıcio,G.S.O. Rodrigues, S.S.A. Amora, N.D. Alvesand F.M.C. Feij | E110: https://www.researchgate.net/publication/347776206_Pyroligneous_acid_from_Mimosa_tenuiflora_and_Eucalyptus_urograndis_as_an_antimicrobial_in_dairy_goats [accessed Mar 05 2021]. | F110: WoS | G110: 50 | H110: 10 | I110: Georgescu Cecilia
A111: Aurelia Magdalena Pisoschi, Aneta POP, Universitate de Stiinte Agricole si medicina Veterninara, Bucuresti, Cecilia Georgescu, ULBS, Violeta Turcus, Neli Kinga Olah,Universitatea de Vest Vasile Goldis, Endre Mathe, Universitatea din Debrecen | B111: FSAA2 | C111: An overview of natural antimicrobials role in food | D111: CRITICAL REVIEWS IN FOOD SCIENCE AND NUTRITION, By:Ahmed, S; Sameen, DE; Lu, R; Li, R; Dai, JW; Qin, W; Liu, YW; Research progress on antimicrobial materials for food packaging | E111: https://www.tandfonline.com/doi/abs/10.1080/10408398.2020.1863327 | F111: WoS | G111: 50 | H111: 10 | I111: Georgescu Cecilia
A112: Aurelia Magdalena Pisoschi, Aneta POP, Universitate de Stiinte Agricole si medicina Veterninara, Bucuresti, Cecilia Georgescu, ULBS, Violeta Turcus, Neli Kinga Olah,Universitatea de Vest Vasile Goldis, Endre Mathe, Universitatea din Debrecen | B112: FSAA2 | C112: An overview of natural antimicrobials role in food | D112: CRITICAL REVIEWS IN FOOD SCIENCE AND NUTRITION, By:Bensid, A; El Abed, N; Houicher, A; Regenstein, JM; Ozogul, F Antioxidant and antimicrobial preservatives: Properties, mechanism of action and applications in food - a review | E112: https://www.tandfonline.com/doi/abs/10.1080/10408398.2020.1862046 | F112: WoS | G112: 50 | H112: 10 | I112: Georgescu Cecilia
A113: Aurelia Magdalena Pisoschi, Aneta POP, Universitate de Stiinte Agricole si medicina Veterninara, Bucuresti, Cecilia Georgescu, ULBS, Violeta Turcus, Neli Kinga Olah,Universitatea de Vest Vasile Goldis, Endre Mathe, Universitatea din Debrecen | B113: FSAA2 | C113: An overview of natural antimicrobials role in food | D113: FOOD CONTROL, V 118, By:Bancalari, E ; Martelli, F; Bernini, V; Neviani, E; Gatti, M; Bacteriostatic or bactericidal? Impedometric measurements to test the antimicrobial activity of Arthrospira platensis extract | E113: https://www.sciencedirect.com/science/article/abs/pii/S0956713520302966 | F113: WoS | G113: 50 | H113: 10 | I113: Georgescu Cecilia
A114: Aurelia Magdalena Pisoschi, Aneta POP, Universitate de Stiinte Agricole si medicina Veterninara, Bucuresti, Cecilia Georgescu, ULBS, Violeta Turcus, Neli Kinga Olah,Universitatea de Vest Vasile Goldis, Endre Mathe, Universitatea din Debrecen | B114: FSAA2 | C114: An overview of natural antimicrobials role in food | D114: INTERNATIONAL JOURNAL OF BIOLOGICAL MACROMOLECULES, V 164, p. 845-854, By:Qiao, Z; Sun, HM; Zhou, QQ; Yi, LH; Wang, X; Shan, YY; Yi, YL; Liu, BF; Zhou, Y; Lu, X; Characterization and antibacterial action mode of bacteriocin BMP32r and its application as antimicrobial agent for the therapy of multidrug-resistant bacterial infection | E114: https://www.sciencedirect.com/science/article/abs/pii/S0141813020339489 | F114: WoS | G114: 50 | H114: 10 | I114: Georgescu Cecilia
A115: Aurelia Magdalena Pisoschi, Aneta POP, Universitate de Stiinte Agricole si medicina Veterninara, Bucuresti, Cecilia Georgescu, ULBS, Violeta Turcus, Neli Kinga Olah,Universitatea de Vest Vasile Goldis, Endre Mathe, Universitatea din Debrecen | B115: FSAA2 | C115: An overview of natural antimicrobials role in food | D115: FOOD RESEARCH INTERNATIONAL, V. 137, By:Chauhan, R; Singh, N; Pal, GK; Goel, G; Trending biocontrol strategies against Cronobacter sakazakii: A recent updated review | E115: https://www.sciencedirect.com/science/article/pii/S0963996920304105?casa_token=V6Sw208NvasAAAAA:ku-tAXhPW6yWpGuKc_GAZ-Zm3eTxfjFyFve_fAVEtqmtBY4voDB4H_yjeeY0Y3c46y6tKbtfM3Q | F115: WoS | G115: 50 | H115: 10 | I115: Georgescu Cecilia
A116: Aurelia Magdalena Pisoschi, Aneta POP, Universitate de Stiinte Agricole si medicina Veterninara, Bucuresti, Cecilia Georgescu, ULBS, Violeta Turcus, Neli Kinga Olah,Universitatea de Vest Vasile Goldis, Endre Mathe, Universitatea din Debrecen | B116: FSAA2 | C116: An overview of natural antimicrobials role in food | D116: PLANTS-BASEL, Vol. 9(11), By: Radulescu, C; Buruleanu, LC; Nicolescu, CM; Olteanu, RL; Bumbac, M; Holban, GC; Simal-Gandara, J; Phytochemical Profiles, Antioxidant and Antibacterial Activities of Grape (Vitis vinifera L.) Seeds and Skin from Organic and Conventional Vineyards | E116: https://www.mdpi.com/2223-7747/9/11/1470 | F116: WoS | G116: 50 | H116: 10 | I116: Georgescu Cecilia
...

Sheet I.10
A2: I10 - Brevete OSIM/ internaţionale/ triadice
A4: Se va anexa documentul doveditor (înregistrarea în buletinul oficial aferent) şi înregistrarea la Serviciul CD / CTC HPI-ULBS; respectiv dovada indexării ȋn TR.
A5: * Punctaje de referință: • Brevet OSIM = 1000 puncte • Brevet internaţional = 2000 puncte • Brevet triadic = 3000 puncte • Cerere de brevet indexată în TR = 100 puncte Punctajul se împarte la numărul de autori cu afiliere la instituţiile de învăţământ şi cercetare din România, inclusiv la doctoranzi / studenţi; pentru autorii din străinătate sau autorii din mediul de afaceri, se menţionează în paranteză instituţia.
A8: Titlul brevetului/ Numărul brevetului | B8: Numele și prenumele inventatorilor (se menționează în paranteză afilierea) | C8: Cod Departament | D8: Data înregistrării în buletinul oficial / Data indexarii cererii de brevet in TR | E8: Punctaj de referință* | F8: Punctaj individual | G8: Numele și prenumele Declarant
A9: Preparing hemp oil enriched with Hibiscus extract, by preparing natural extract from dried petals of Hibiscus by cold maceration, followed by filtration and centrifugation, and adding anthocyanin and soy lecithin to cold-pressed hemp oil | B9: OANCEA R S, DRAGHICI O, PERJU M | C9: FSAA2 | D9: Cerere de brevet OSIM RO133811-A0 indexata in Thomson Reuters (TR) | E9: 100 | F9: 33.33 | G9: Draghici Olga
A10: Preparing hemp oil enriched with Hibiscus extract, by preparing natural extract from dried petals of Hibiscus by cold maceration, followed by filtration and centrifugation, and adding anthocyanin and soy lecithin to cold-pressed hemp oil | B10: OANCEA R S, DRAGHICI O, PERJU M | C10: FSAA2 | D10: Cerere de brevet OSIM RO133811-A0 indexata in Thomson Reuters (TR) | E10: 100 | F10: 33.33 | G10: Oancea Simona
A29: TOTAL | F29: =SUM(F9:F28) -> 66.66
A31: Informațiile incomplete / incorecte vor conduce la neluarea în calcul a indicatorului respectiv

Sheet I.11
A2: I11 - Modele de utilitate (micul brevet)
A4: Se va anexa documentul doveditor pentru modelul de utilitate (înregistrarea în buletinul oficial aferent) şi înregistrarea la Serviciul CD / CTC HPI-ULBS.
A5: * Punctaje de referință: • Model de utilitate = 300 puncte Plafon anual: maxim 600 puncte / declarant. Punctajul se împarte la numărul de autori cu afiliere la instituţiile de învăţământ şi cercetare din România, inclusiv la doctoranzi / studenţi; pentru autorii din străinătate sau autorii din mediul de afaceri, se menţionează în paranteză instituţia.
A7: Titlul modelului de utilitate / Numărul modelului de utilitate | B7: Numele și prenumele inventatorilor (se menționează în paranteză afilierea) | C7: Cod Departament | D7: Data înregistrării în buletinul oficial | E7: Punctaj de referință* | F7: Punctaj individual | G7: Numele și prenumele Declarant
A28: TOTAL | F28: =SUM(F8:F27) -> 0
A30: Informațiile incomplete / incorecte vor conduce la neluarea în calcul a indicatorului respectiv

Sheet I.12
A2: I12 - Evenimente artistice (doar pentru domeniul Artele spectacolului), expoziţii (doar pentru domeniul Arte vizuale) şi concerte de muzică religioasă (doar pentru domeniul Teologie)
A4: Se va verifica existenţa siglei ULBS pe materialele promoţionale ale evenimentului respectiv.
A5: Se va anexa documentul doveditor evenimentului (site / pagina Facebook, afiş, promovare în mass media, cronică de spectacol, link www etc.).
A6: Expozitiile trebuie să facă dovada existenţei unei pagini web, a unui catalog şi a unor documente care să ateste abordarea lor din perspectivă critică.
A7: *Punctaje de referință: A. Evenimente artistice şi expoziţii (domeniul artele spectacolului): Organizare eveniment artistic: • 200 puncte / echipă organizatorică, pentru fiecare spectacol în cadrul unui festival, turneu, în străinătate • 100 puncte / echipă organizatorica, pentru fiecare spectacol în cadrul unui festival, expozitie, turneu în ţară • 40 puncte / echipă organizatorică, pentru fiecare reprezentaţie a unui spectacol de la sediul TNRS, expozitie in Sibiu Punctajul se acorda managerului de spectacol. Acesta poate decide distribuirea punctajului între membrii echipei. Rol în spectacol / film: • 800 puncte = rol în film • 80 puncte = rol in scurt metraj video • 180 puncte = rol în spectacol nou • 50 puncte = pentru rol în reprezentaţia unui spectacol de la sediul TNRS (se raportează o singură dată pe anul calendaristic, indiferent de numărul de reprezentaţii) • 50 puncte = fiecare rol în reprezentația unui spectacol în cadrul unui festival/ turneu naţional • 100 puncte = fiecare rol în reprezentația unui spectacol în cadrul unui festival/ turneu în străinătate și în cadrul FITS Producţie artistică: • Regie spectacol: 300 puncte în străinătate / 50 puncte în ţară • Asistenţă regie spectacol: 40 puncte în străinătate / 20 puncte în ţară • Producţie scurt metraj video: 200 puncte • Workshop artistic: 60 puncte în străinătate / 40 puncte în ţară • Coordonare muzicală spectacol: 40 puncte în străinătate / 20 puncte în ţară. • Coordonare mişcare scenică: 40 puncte în străinătate / 20 puncte în ţară. • Concept video: 40 puncte în străinătate / 20 puncte în ţară B. Expoziţii (domeniul arte vizuale): - expoziţie personală în străinătate – 200 puncte / eveniment - expoziţie personală în ţară – 100 puncte / eveniment - participare la expoziţie internaţională: 50 puncte / eveniment - participare la expoziţie naţională: 30 puncte / eveniment Plafoane maxime anual, cerinţe cumulative: 1000 puncte / declarant C. Concerte internationale / naţionale de muzică religioasă (domeniul teologie): • 50 / 20 puncte / concert. Plafon maxim: 100 puncte / declarant.
A9: Numele și prenumele | B9: Cod Departament | C9: Titlu eveniment | D9: Tipul evenimentului | E9: Data evenimentului | F9: Link-ul către site-ul evenimentului/ catolog/ pagină de FB etc. | G9: Punctaj de referință* | H9: Punctaj individual | I9: Numele și prenumele Declarant
A60: TOTAL | H60: =SUM(H10:H59) -> 0
A62: Informațiile incomplete / incorecte vor conduce la neluarea în calcul a indicatorului respectiv

Sheet I.13
A2: I13 - Evenimente sportive (doar pentru domeniul Sport)
A4: Se va verifica existenţa siglei ULBS pe materialele promoţionale ale evenimentului respectiv.
A5: Se va anexa documentul doveditor evenimentului (site / pagina Facebook, afiş, promovare în mass media etc.).
A6: Caracterul competiţiei / campionatului se dovedește cu o listă de participanţi înscrişi în concurs, afişată pe site-un evenimentului. • Competiţie internaţională = minim 50% din participanţi sunt din străinătate • Competiţie naţională = minim 50% din participanţi sunt din alte judeţe • Competiţie locala = minim 50% din participanţi sunt din judeţul Sibiu
A7: *Punctaje de referință: Organizare eveniment sportiv: • 500 puncte / echipa organizatorică, pentru fiecare competiţie internatională • 300 puncte / echipa organizatorică, pentru fiecare competiţie naţională • 100 puncte / echipa organizatorică, pentru fiecare competiţie locală Punctajul se acordă organizatorului principal. Acesta poate decide distribuirea punctajului între membrii echipei. Se va verifica apartenenţa persoanei la comitetul de organizare. Performanța sportivă a cadrului didactic afiliat la ULBS: • 800 puncte = participare la competiţii de nivel internaţional • 300 puncte = participare competiţii de nivel naţional • 100 puncte = participare la competiţii de nivel regional Punctajul pentru performanţa sportivă se acordă pentru cadrul didactic (şi nu pentru studenţi).
A8: Plafoane maxime anual, cerinţe cumulative: 1000 puncte / declarant.
A10: Numele și prenumele | B10: Cod Departament | C10: Titlu eveniment | D10: Tipul evenimentului | E10: Data evenimentului | F10: Link-ul către site-ul evenimentului/ catolog/ pagină de FB etc. | G10: Punctaj de referință* | H10: Punctaj individual | I10: Numele și prenumele Declarant
A61: TOTAL | H61: =SUM(H11:H60) -> 0
A63: Informațiile incomplete / incorecte vor conduce la neluarea în calcul a indicatorului respectiv

Sheet I.14
A2: I14 - Membru în comitetul editorial al unei reviste ştiinţifice indexate BDI
A4: Se verifica prin lista comitetului editorial al revistei, afişată pe site-ul revistei.
A5: În cazul în care activitatea editorului implică muncă de recenzare / calitatea de membru în comitetul ştiinţific, raportarea se face doar la indicatorul I15.
A6: În lista comitetului editorial se precizează afilierea la ULBS a declarantului.
A7: * Punctaje de referință: • Revistă indexată WoS = 200 puncte • Revistă indexată în Scopus: 100 puncte • Revistă indexată în cel puţin două BDI = 50 puncte Pentru revistele ULBS indexate în minim 2 BDI: max 400 puncte / revistă, pentru tot comitetul editorial. Punctajul individual se acordă pe baza unei adrese semnate de Editorul şef. Plafoane maxime anuale: 200 puncte / declarant, indiferent de numărul de reviste declarate.
A9: Numele și prenumele | B9: Cod Departament | C9: Denumirea revistei | D9: Baza de date în care e idexată revista (WoS, Scopus, minim două BDI) | E9: Site www al revistei (link-ul unde este menționată componența comitetului editorial) | F9: Punctaj de referință* | G9: Punctaj individual | H9: Numele și prenumele Declarant
A10: Antofie MM | B10: FSAA2 | C10: Analele Universităţii din Oradea, Fascicula Biologie | D10: WoS, Scopus | E10: https://www.bioresearch.ro/revistaen.html | F10: 200 | G10: 200 | H10: Antofie Mihaela
A11: Georgescu Cecilia | B11: FSAA2 | C11: Business and Service Technologies | D11: Google, Science Index, WorldCat, etc. | E11: http://rrbusiness.ru/en/editorial-board/ | F11: 50 | G11: 50 | H11: Georgescu Cecilia
A12: Georgescu Cecilia | B12: FSAA2 | C12: International Journal of Pharmacology, Phytochemistry and Ethnomedicine | D12: Google Scholar, Chemical Abstract Services, Open-J Gate, CAB, etc.. | E12: https://www.scipress.com/IJPPE/editorial-board | F12: 50 | G12: 50 | H12: Georgescu Cecilia
A13: Georgescu Cecilia | B13: FSAA2 | C13: Advances in Pharmacology & Clinical Trials (APCT) | D13: Google Scholar Citation, Index Copernicus, Publons, Scilit, etc. | E13: https://medwinpublishers.com/APCT/editorial-board.php | F13: 50 | G13: 50 | H13: Georgescu Cecilia
A14: Iagaru Romulus | B14: FSAA2 | C14: Lucrări Stiintifice. Management Agricol. | D14: EBSCO, CABI Full Text | E14: http://www.lsma.ro/index.php/lsma/about/editorialTeam | F14: 50 | G14: =F14 -> 50 | H14: Iagaru Romulus
A15: Mironescu Monica | B15: FSAA2 | C15: Acta Universitatis Cibiniensis. Series E: Food Technology | D15: DOAJ, CABI, Publons, EBSCO, CAS, google scholar, … | E15: https://content.sciendo.com/view/journals/aucft/aucft-overview.xml?tab_body=editorialContent-68844 | F15: 400 | G15: 200 | H15: Mironescu Monica
A16: Oancea Simona | B16: FSAA2 | C16: ACTA UNIVERSITATIS CIBINIENSIS, Series E: Food Technology (Editată international de Editura deGruyter) - revista ULBS | D16: BDI (CABI Database, Food Science Central FSTA - Food Science and technology Abstracts, Chemical Abstracts CAS (CODEN AUCSD5), EBSCO (Food Science Source), Reed Elsevier India Pvt. Ltd.) | E16: http://www.degruyter.com/view/j/aucft | F16: 400 | G16: 100 | H16: Oancea Simona
A17: Sava C | B17: FSAA2 | C17: Analele Universităţii din Oradea, Fascicula Biologie | D17: WoS, Scopus | E17: https://www.bioresearch.ro/revistaen.html | F17: 200 | G17: 200 | H17: Sava Camelia
A18: TIŢA Mihaela | B18: FSAA2 | C18: SCIREA Journal of Food | D18: Gogle scholar, J-Gate,TDNet | E18: http://www.scirea.org/journal/EditorialBoard?JournalID=55000 | F18: 50 | G18: 50 | H18: Tita Mihaela
A19: TIŢA Mihaela | B19: FSAA2 | C19: Journal of Biochemical and Microbial Toxicology | D19: Digital Object Identifier (DOI), CrossRef. | E19: https://www.omicsonline.org/editorialboard-journal-biochemical-microbial-toxicology | F19: 50 | G19: 50 | H19: Tita Mihaela
A20: TIŢA Mihaela | B20: FSAA2 | C20: International Journal of Food Science and Biotechnology | D20: WordCat, Crossref, ResearchBib, ESJI | E20: http://www.ijfsb.org/editorialboard | F20: 50 | G20: 50 | H20: Tita Mihaela
A21: TITA Ovidiu, editor șef | B21: FSAA2 | C21: Acta Universitatis Cibiniensis, seria E, Food Technology | D21: AGRICOLA , Baidu Scholar, CABI, Chemical Abstracts Service (CAS) – SciFinder, CNKI Scholar, CNPIEC, DOAJ, EBSCO, EBSCO Discovery Service, Elsevier – Compendex, Elsevier - Engineering Village, FSTA - Food Science & Technology Abstracts, Genamics JournalSeek, Google Scholar, Japan Science and Technology Agency (JST), J-Gate, JournalTOCs, KESLI-NDSL (Korean National Discovery for Science Leaders), Microsoft Academic, Naviga (Softweco), Primo Central (ExLibris), Publons, ReadCube, Sherpa/RoMEO, Summon (Serials Solutions/ProQuest), TDNet, Ulrich's Periodicals Directory/ulrichsweb, WanFang Data, WorldCat (OCLC) | E21: http://saiapm.ulbsibiu.ro/ACTA_E/AUCFT.html | F21: 400 | G21: 100 | H21: Tita Ovidiu
A22: TITA Ovidiu | B22: FSAA2 | C22: International Journal of Pharmacognosy and Chinese Medicine (ISSN: 2576-4772). | D22: Google Scholar, academic Resource Index, Advanced Sciences Index, Index Copernicus, Publons, Scilit ICMJE - International Comitte Medical Jurnal Editors | E22: https://medwinpublishers.com/IPCM/editorial-board.php | F22: 50 | G22: 50 | H22: Tita Ovidiu
A23: TITA Ovidiu | B23: FSAA2 | C23: Editura EUROSTAMPA - Ingineria mecanica si stiinta materialelor. | D23: http://www.eurostampa.ro/ | E23: http://www.eurostampa.ro/ | F23: 50 | G23: 50 | H23: Tita Ovidiu
A61: TOTAL | G61: =SUM(G10:G60) -> 1250
A63: Informațiile incomplete / incorecte vor conduce la neluarea în calcul a indicatorului respectiv

Sheet I.15
A2: I15 - Referent ştiinţific al unei reviste indexate în minim 2 BDI sau al unei conferinţe internaţionale
A4: Calitatea de referent ştiinţific se dovedeşte prin raportul de recenzare (corespondenţa de recenzare).
A5: Revista trebuie sa fie indexată în minim 2 BDI.
A6: O conferinţă este considerata internaţională dacă îndeplineşte cumulativ următoarele criterii: (a) are vizibilitate internaţională, dovedită printr-o pagina web de prezentare într-o limbă străină de circulaţie internaţională (engleză, franceză, germană sau spaniolă); (b) peste 50% dintre membrii incluşi în comitetul ştiinţific au afiliere instituţională în străinătate, conform listei comitetului ştiinţific de pe pagina web a conferinţei; (c) programul ştiinţific, precum şi proceedings-urile sau rezumatele sunt publicate în format tipărit sau electronic într-o limbă străină de circulaţie internaţională; (d) lucrările conferinţei sunt desfăşurate exclusiv într-o limbă străină de circulaţie internaţională; (e) minim 25% dintre participanţi sau minim 25 participanţi cu lucrări înscrise au afiliere instituţională în străinătate, conform programului ştiinţific de pe pagina web a conferinţei.
A7: *Punctaje de referință: • Revistă indexată WoS = 50 puncte • Revistă indexată în cel puţin două BDI / conferinţă internaţională = 25 puncte Plafoane maxime anual: 200 puncte / declarant, indiferent de numărul de reviste, conferinţe sau articole recenzate declarate.
A9: Numele și prenumele | B9: Cod Departament | C9: Numele revistei / Numele conferinței | D9: Site-ul revistei / site-ul conferinței internaționale | E9: Data raportului de recenzare | F9: Punctaj de referință* | G9: Punctaj individual | H9: Numele și prenumele Declarant
A10: Antofie MM | B10: FSAA2 | C10: Analele Universităţii din Oradea, Fascicula Biologie | D10: https://www.bioresearch.ro/revistaen.html | E10: august | F10: 50 | G10: 50 | H10: Antofie Mihaela
A11: Antofie MM | B11: FSAA2 | C11: ROMANIAN BIOTECHNOLOGICAL LETTERS | D11: https://www.rombio.org/ | E11: decembrie | F11: 50 | G11: 50 | H11: Antofie Mihaela
A12: Crețu C.M. | B12: FSAA2 | C12: Micron, Impact factor/2019=1,726, revista indexată WoS | D12: https://www.journals.elsevier.com/micron/editorial-board | E12: 43847 | F12: 50 | G12: 50 | H12: Cretu Monica
A13: Crețu C.M. | B13: FSAA2 | C13: Micron, Impact factor/2019=1,726, revista indexată WoS | D13: https://www.journals.elsevier.com/micron/editorial-board | E13: 44086 | F13: 50 | G13: 50 | H13: Cretu Monica
A14: Drăghici Olga | C14: Journal of Applied Phycology | D14: https://www.springer.com/journal/10811 | E14: 43952 | F14: 50 | G14: =F14 -> 50 | H14: Draghici Olga
A15: Drăghici Olga | C15: African Journal of Pure and Applied Chemistry | D15: www.ms.academicjournals.org | E15: 44169 | F15: 25 | G15: =F15 -> 25 | H15: Draghici Olga
A16: Georgescu Cecilia | B16: FSAA2 | C16: Food and Nutrition Sciences | D16: https://www.scirp.org/journal/FNS/ | E16: 03.04.2020 | F16: 25 | G16: 25 | H16: Georgescu Cecilia
A17: Georgescu Cecilia | B17: FSAA2 | C17: Food and Nutrition Sciences | D17: https://www.scirp.org/journal/FNS/ | E17: 6.06.2020 | F17: 25 | G17: 25 | H17: Georgescu Cecilia
A18: Georgescu Cecilia | B18: FSAA2 | C18: Acta Universitatis Cibiniensis, Seria E: Food Technology | D18: https://content.sciendo.com/view/journals/aucft/aucft-overview.xml | E18: 30.05.2020 | F18: 25 | G18: 25 | H18: Georgescu Cecilia
A19: Georgescu Cecilia | B19: FSAA2 | C19: Acta Universitatis Cibiniensis, Seria E: Food Technology | D19: https://content.sciendo.com/view/journals/aucft/aucft-overview.xml | E19: 31.03.2020 | F19: 25 | G19: 25 | H19: Georgescu Cecilia
A20: Georgescu Cecilia | B20: FSAA2 | C20: Scientific Study & Research Chemistry & Chemical Engineering, Biotechnology, Food Industry | D20: Scientific Publications - University of Bacau [News] (scientific reviews, abstracts and articles) | E20: 16.09.2020 | F20: 50 | G20: 50 | H20: Georgescu Cecilia
A21: Georgescu Cecilia | B21: FSAA2 | C21: Zeitschrift für Naturforschung C: A Journal of Biosciences | D21: https://publons.com/journal/61744/zeitschrift-fur-naturforschung-c-a-journal-of-bios/ | E21: 5.07.2020 | F21: 50 | G21: 50 | H21: Georgescu Cecilia
A22: Iagăru Pompilica | B22: FSAA2 | C22: Scientific Papers Agricultural Management | D22: http://www.lsma.ro/index.php/lsma | E22: 24.09.2020 1807-5269-1-RV | F22: 25 | G22: =F22 -> 25 | H22: Iagaru Pompilica
A23: Iagăru Pompilica | B23: FSAA2 | C23: Scientific Papers Agricultural Management | D23: http://www.lsma.ro/index.php/lsma | E23: 24.09.2020 1808-5271-1-RV | F23: 25 | G23: =F23 -> 25 | H23: Iagaru Pompilica
A24: Iagăru Pompilica | B24: FSAA2 | C24: Scientific Papers Agricultural Management | D24: http://www.lsma.ro/index.php/lsma | E24: 24.09.2020 1809-5289-1-RV | F24: 25 | G24: =F24 -> 25 | H24: Iagaru Pompilica
A25: Iagăru Romulus | B25: FSAA2 | C25: Scientific Papers Agricultural Management | D25: http://www.lsma.ro/index.php/lsma | E25: 24.09.2020 1769-5275-1-SP | F25: 25 | G25: =F25 -> 25 | H25: Iagaru Romulus
A26: Iagăru Romulus | B26: FSAA2 | C26: Scientific Papers Agricultural Management | D26: http://www.lsma.ro/index.php/lsma | E26: 24.09.2020 1773-5287-1-SP | F26: 25 | G26: =F26 -> 25 | H26: Iagaru Romulus
A27: Iagăru Romulus | B27: FSAA2 | C27: Scientific Papers Agricultural Management | D27: http://www.lsma.ro/index.php/lsma | E27: 24.09.2020 1786-5212-1-SP | F27: 25 | G27: =F27 -> 25 | H27: Iagaru Romulus
A28: Iagăru Romulus | B28: FSAA2 | C28: Scientific Papers Agricultural Management | D28: http://www.lsma.ro/index.php/lsma | E28: 24.09.2020 1792-5259-1-SP | F28: 25 | G28: =F28 -> 25 | H28: Iagaru Romulus
A29: Iagăru Romulus | B29: FSAA2 | C29: Scientific Papers Agricultural Management | D29: http://www.lsma.ro/index.php/lsma | E29: 24.09.2020 1805-5262-1-RV | F29: 25 | G29: =F29 -> 25 | H29: Iagaru Romulus
A30: Iancu Maria Lidia | B30: FSAA2 | C30: Acta Universitatis Cibiensis. Serie E: Food Technology | D30: https://content.sciendo.com/view/journals/aucft/aucft-overview.xml | E30: 43916 | F30: 25 | G30: 25 | H30: Iancu Maria
A31: Ketney Otto | B31: FSAA2 | C31: Food Control/Aflatoxin M1 in UHT and Powder Milk marketed in the Northern area of Morocco | D31: https://ees.elsevier.com/foodcont/ | E31: 43846 | F31: 50 | G31: 50 | H31: Ketney Otto
A32: Ketney Otto | B32: FSAA2 | C32: Food Control/Title: Mycotoxins in teas and medicinal plants destined to prepare infusions in Portugal | D32: https://ees.elsevier.com/foodcont/ | E32: 43878 | F32: 50 | G32: 50 | H32: Ketney Otto
A33: Ketney Otto | B33: FSAA2 | C33: Food Research International/Burden of disease associated with dietary exposure to carcinogenic aflatoxins in Portugal: a human biomonitoring approach | D33: https://ees.elsevier.com/foodres/ | E33: 43887 | F33: 50 | G33: 50 | H33: Ketney Otto
A34: Ketney Otto | B34: FSAA2 | C34: Food Control/A multi-technique approach for fraud detection in milk, cheeses and vegetable drinks | D34: https://ees.elsevier.com/foodcont/ | E34: 43914 | F34: 50 | G34: 50 | H34: Ketney Otto
A35: Mironescu Ion Dan | B35: FSAA2 | C35: International Journal Bioautomation | D35: http://biomed.bas.bg/bioautomation/ | E35: 25.05.2020 | F35: 50 | G35: =F35 -> 50 | H35: Mironescu Ion
A36: Mironescu Ion Dan | B36: FSAA2 | C36: Periodica Polytechnica Chemical Engineering | D36: https://pp.bme.hu/ch | E36: 24.04.2020 | F36: 50 | G36: =F36 -> 50 | H36: Mironescu Ion
A37: Mironescu Ion Dan | B37: FSAA2 | C37: Processes | D37: https://www.mdpi.com/journal/processes | E37: 20.09.2020 | F37: 50 | G37: =F37 -> 50 | H37: Mironescu Ion
A38: Mironescu Ion Dan | B38: FSAA2 | C38: Acta Universitatis Cibiniensis. Series E: Food Technology | D38: https://content.sciendo.com/view/journals/aucft/aucft-overview.xml | E38: 12.01.2020 | F38: 25 | G38: =F38 -> 25 | H38: Mironescu Ion
A39: Mironescu Ion Dan | B39: FSAA2 | C39: Acta Universitatis Cibiniensis. Series E: Food Technology | D39: https://content.sciendo.com/view/journals/aucft/aucft-overview.xml | E39: 15.08.2020 | F39: 25 | G39: =F39 -> 25 | H39: Mironescu Ion
A40: Mironescu Monica | B40: FSAA2 | C40: Applied Sciences | D40: https://www.mdpi.com/journal/applsci | E40: 05.05.2020 | F40: 50 | G40: =F40 -> 50 | H40: Mironescu Monica
A41: Mironescu Monica | B41: FSAA2 | C41: Applied Sciences | D41: https://www.mdpi.com/journal/applsci | E41: 07.10.2020 | F41: 50 | G41: =F41 -> 50 | H41: Mironescu Monica
A42: Mironescu Monica | B42: FSAA2 | C42: Molecules | D42: https://www.mdpi.com/journal/molecules | E42: 12.01.2020 | F42: 50 | G42: =F42 -> 50 | H42: Mironescu Monica
A43: Mironescu Monica | B43: FSAA2 | C43: Processes | D43: https://www.mdpi.com/journal/processes | E43: 08.11.2020 | F43: 50 | G43: =F43 -> 50 | H43: Mironescu Monica
A44: Claudia Felicia OGNEAN | B44: FSAA2 | C44: Acta Universitatis Cibiniensis. Series E: Food Technology (articol recenzat: NUTRITIONAL PROPERTIES OF SAKADA PRODUCED FROM BLENDS OF CASSAVA AND AFRICAN YAM BEAN FLOURS) | D44: https://content.sciendo.com/configurable/contentpage/journals$002faucft$002faucft-overview.xml | E44: 1.09.2020 | F44: 25 | G44: 25 | H44: Ognean Claudia
A45: Mihai OGNEAN | B45: FSAA2 | C45: Acta Universitatis Cibiniensis. Series E: Food Technology (articol recenzat: CHARACTERISTICS OF TECHNOLOGICAL PROPERTIES OF GRAIN AND FLOUR FROM ANCIENT VARIETIES OF WHEAT (EINKORN, EMMER AND SPELT) | D45: https://content.sciendo.com/configurable/contentpage/journals$002faucft$002faucft-overview.xml | E45: 27.10.2020 | F45: 25 | G45: 25 | H45: Ognean Mihai
A46: Mihai OGNEAN | B46: FSAA2 | C46: Acta Universitatis Cibiniensis. Series E: Food Technology (articol recenzat: BISCUITS FROM FERMENTED ROASTED BUCKWHEAT FLOUR - PHENOLICS PROFILE AND BIOACCESSIBLE ANGIOTENSIN CONVERTING ENZYME INHIBITORY ACTIVITY) | D46: https://content.sciendo.com/configurable/contentpage/journals$002faucft$002faucft-overview.xml | E46: 05.08.2020 | F46: 25 | G46: 25 | H46: Ognean Mihai
A47: PACALA Mariana-Liliana | B47: FSAA2 | C47: Acta Universitatis Cibiniensis. Series E: Food Technology | D47: https://content.sciendo.com/view/journals/aucft/aucft-overview.xml | E47: 03 aprilie 2020 | F47: 25 | G47: 25 | H47: Pacala Mariana
A48: PACALA Mariana-Liliana | B48: FSAA2 | C48: Acta Universitatis Cibiniensis. Series E: Food Technology | D48: https://content.sciendo.com/view/journals/aucft/aucft-overview.xml | E48: 12 octombrie 2020 | F48: 25 | G48: 25 | H48: Pacala Mariana
A49: Sava C | B49: FSAA2 | C49: Analele Universităţii din Oradea, Fascicula Biologie | D49: https://www.bioresearch.ro/revistaen.html | E49: august | F49: 50 | G49: 50 | H49: Sava Camelia
A50: Sava C | B50: FSAA2 | C50: ROMANIAN BIOTECHNOLOGICAL LETTERS | D50: https://www.rombio.org/ | E50: decembrie | F50: 50 | G50: 50 | H50: Sava Camelia
A51: Sava C | B51: FSAA2 | C51: Asian Journal of Research in Crop Science | D51: https://www.journalajrcs.com/index.php/AJRCS/abstracting-indexing | E51: septembrie | F51: 25 | G51: 25 | H51: Sava Camelia
A52: Şipoş Anca | B52: FSAA2 | C52: SN Applied Sciences | D52: https://www.springer.com/journal/42452/ | E52: 10 Noiembrie 2020 | F52: 50 | G52: 50 | H52: Sipos Anca
A53: Şipoş Anca | B53: FSAA2 | C53: Acta Universitatis Cibiniensis. Series E: Food Technology | D53: https://content.sciendo.com/view/journals/aucft/aucft-overview.xml | E53: 25 Mai 2020 | F53: 25 | G53: 25 | H53: Sipos Anca
A54: Spânu Simona | B54: FSAA2 | C54: Sustainability | D54: https://susy.mdpi.com/user/reviewer/status/finished | E54: 13.04.2020 | G54: 50 | H54: Spanu Simona
A55: Spânu Simona | B55: FSAA2 | C55: Atmosphere | D55: https://susy.mdpi.com/user/reviewer/status/finished | E55: 25.05.2020 | G55: 50 | H55: Spanu Simona
A56: Spânu Simona | B56: FSAA2 | C56: Sustainability | D56: https://susy.mdpi.com/user/reviewer/status/finished | E56: 02.07.2020 | G56: 50 | H56: Spanu Simona
A57: Spânu Simona | B57: FSAA2 | C57: Sustainability | D57: https://susy.mdpi.com/user/reviewer/status/finished | E57: 11.08.2020 | G57: 50 | H57: Spanu Simona
A58: TIŢA Mihaela | B58: FSAA2 | C58: Bulletin of the Transilvania University of Braşov , Series II: Forestry • Wood Industry • Agricultural Food Engineering, | D58: http://webbut.unitbv.ro/bulletin/Series%20II/Series%20II.html | E58: 43927 | F58: 50 | G58: 50 | H58: Tita Mihaela
A59: TIŢA Mihaela | B59: FSAA2 | C59: Bulletin of the Transilvania University of Braşov , Series II: Forestry • Wood Industry • Agricultural Food Engineering, | D59: http://webbut.unitbv.ro/bulletin/Series%20II/Series%20II.html | E59: 43970 | F59: 50 | G59: 50 | H59: Tita Mihaela
A60: TIŢA Mihaela | B60: FSAA2 | C60: Bulletin of the Transilvania University of Braşov , Series II: Forestry • Wood Industry • Agricultural Food Engineering, | D60: http://webbut.unitbv.ro/bulletin/Series%20II/Series%20II.html | E60: 44112 | F60: 50 | G60: 50 | H60: Tita Mihaela
A61: TIŢA Mihaela | B61: FSAA2 | C61: Bulletin of the Transilvania University of Braşov , Series II: Forestry • Wood Industry • Agricultural Food Engineering, | D61: http://webbut.unitbv.ro/bulletin/Series%20II/Series%20II.html | E61: 44144 | F61: 50 | G61: 50 | H61: Tita Mihaela
A62: TITA Ovidiu | B62: FSAA2 | C62: Animals | D62: https://www.mdpi.com/journal/animals | E62: 44042 | F62: 50 | G62: 50 | H62: Tita Ovidiu
A63: TITA Ovidiu | B63: FSAA2 | C63: Patogens | D63: https://www.mdpi.com/journal/pathogens | E63: 44151 | F63: 50 | G63: 50 | H63: Tita Ovidiu
A64: TITA Ovidiu | B64: FSAA2 | C64: Dairy | D64: https://www.mdpi.com/journal/dairy | E64: 43878 | F64: 25 | G64: 25 | H64: Tita Ovidiu
A65: TITA Ovidiu | B65: FSAA2 | C65: 48th Actual Tasks on Agricultural Engineering | D65: atae.agr.hr | E65: 44174 | F65: 50 | G65: 50 | H65: Tita Ovidiu
G69: =SUM(G10:G68) -> 2200
A71: Informațiile incomplete / incorecte vor conduce la neluarea în calcul a indicatorului respectiv

Sheet I.16
A2: I16 - Organizator principal / Membru în comitetul organizatoric al unei conferinţe internaţionale / naţionale
A4: Calitatea de membru în comitetul de organizare se dovedeşte prin lista comitetului organizatoric publicată pe site-ul conferinţei.
A5: O conferinţă este considerată internaţională dacă îndeplineşte cumulativ următoarele criterii: (a) are vizibilitate internaţională, dovedită printr-o pagina web de prezentare într-o limbă străină de circulaţie internaţională (engleză, franceză, germană sau spaniolă); (b) peste 50% dintre membrii incluşi în comitetul ştiinţific au afiliere instituţională în străinătate; (c) programul ştiinţific este publicat în format tipărit sau electronic într-o limbă străină de circulaţie internaţională; (d) lucrările conferinţei sunt desfăşurate exclusiv într-o limbă străină de circulaţie internaţională; (e) peste 25% sau 25 de participanţii cu lucrări înscrise în programul ştiinţific al conferinţei au afiliere instituţională în străinătate. Conferinţă care nu îndeplineşte criteriile minimale pentru a fi încadrata astfel are statutul de conferinţă naţională. Criterii pentru conferinţa naţională, cel puţin: pagina web; program ştiinţific; volum al conferintei.
A6: *Punctaj de referință: • 100 puncte / conferinţă internaţională, în calitate de organizator principal • 50 puncte / conferinţă internaţională, în calitate de membru în comitetul organizatoric • 50 puncte / conferinţă naţională, în calitate de organizator principal • 25 puncte / conferinţă naţională, în calitate de membru în organizatoric Plafoane maxime anual: • 100 puncte / declarant
A8: Numele și prenumele | B8: Cod Departament | C8: Denumirea conferinței | D8: Tipul conferinței (internațională / națională) | E8: Site-ul conferinței | F8: Funcția în cadrul comitetului organizatoric (organizator principal sau membru) | G8: Data conferinței | H8: Punctaj de referință* | I8: Punctaj individual | J8: Numele și prenumele Declarant
A9: Antonie Iuliana | B9: FSAA2 | C9: Simpozionul național ”Agricultura si implicatia ei in activitatea si santatea omului” - on-line | D9: națională | E9: http://saiapm.ulbsibiu.ro/index.php/ciaiaso-2020/ | F9: organizator principal | G9: 8 octombrie 2020 | H9: 50 | I9: 50 | J9: Antonie Iuliana
A10: Georgescu Cecilia | B10: FSAA2 | C10: II International Symposium "Innovations in Life Sciences" | D10: Internationala | E10: II International Symposium "Innovations in Life Sciences" Committees (bsu.edu.ru) | F10: membru | G10: 19-20.05. 2020 | H10: 50 | I10: 50 | J10: Georgescu Cecilia
A11: MOISE George | B11: FSAA | C11: Agricultura si implicatia ei in activitatea si santatea omului | D11: nationala | E11: http://saiapm.ulbsibiu.ro/index.php/ciaiaso-2020/ | F11: organizator principal | G11: 8 octombrie 2020 | H11: 50 | I11: 50 | J11: Moise George
A12: Stanca Moise Cristina | B12: FSAA | C12: Agricultura si implicatia ei in activitatea si santatea omului | D12: nationala | E12: http://saiapm.ulbsibiu.ro/index.php/ciaiaso-2020/ | F12: membru in comitetul de organizare | G12: 8 octombrie 2020 | H12: 50 | I12: 50 | J12: Moise Cristina
A13: Sava Camelia | B13: FSAA2 | C13: Simpozionul Național „Agricultura și implicațiile ei în alimentația și sănătatea omului” | D13: Națională | E13: http://saiapm.ulbsibiu.ro/index.php/ciaiaso-2020/ | F13: Organizator principal | G13: 8 oct. 2020 | H13: 50 | I13: 10 | J13: Sava Camelia
A59: TOTAL | I59: =SUM(I9:I58) -> 210
A62: Informațiile incomplete / incorecte vor conduce la neluarea în calcul a indicatorului respectiv

Sheet I. 17.
A2: I17 - Proiecte derulate cu terţii în evidenţa financiară a ULBS
A4: Se iau în calcul doar proiectele pentru care există la Serviciul CD / CTC-HPI ULBS o copie a contractului de colaborare, precum şi o copie a raportului anual de activitate.
A5: Evidenţa financiară a proiectelor se face pe baza listei sumelor încasate de la Serviciul Financiar Contabil ULBS.
A6: *Punctaj de referință: • 100 puncte = pentru referinţă 10.000 lei sume încasate / an. Punctajul se acordă directorului de proiect. La decizia directorului, pe baza unei adrese scrise şi semnate, punctajul poate fi împărţit între director şi membrii proiectului. Se acceptă şi proiecte cu valoare mai mică sau mai mare de 10.000 lei, cu diminuarea respectiv majorarea proporţională a punctajului. În cazul proiectelor multianuale, punctajul anual se acorda proportional cu suma incasata anual.
A7: Proiectele instituționale (contracte ESAYEP-SEE, POCU, Erasmus+ KA1, contracte FDI, contracte ROSE, proiecte depuse la Primărie, proiecte depuse la Consiliul Județean etc.) nu se raportează.
A8: Contractele de sponsorizare nu se iau în considerare la raportarea SIEPAS.
A9: Aplicațiile la proiectele de cercetare (inclusiv proiecte Erasmusm+ KA2) se raportează la I18. Nu se raportează niciun fel de proiecte aflate în derulare pentru care aplicația/contractul s-a punctat în anii precedenți la I.18.
A10: Plafon maxim anual: 450 puncte / proiect.
A12: Numele și prenumele | B12: Denumire proiect | C12: Finanțator | D12: Director de proiect | E12: Cod Departament | F12: Durata contractului (lună/an - lună/an) | G12: Suma contractului | H12: Suma încasată în anul de referință | I12: *Punctaj de referință | J12: Punctaj individual | K12: Numele și prenumele Declarant
A13: Mironescu Monica | B13: Cercetări privind optimizarea producției și asigurarea calității în unitățile de procesare a mierii | C13: Asociatia Procesatorilor si Exportatorilor de Miere din Romania APEMAR | D13: Mironescu Monica | E13: FSAA2 | F13: 01.01.2021-31.03.2021 | G13: 11000 | H13: 11000 | I13: 110 | J13: 110 | K13: Mironescu Monica
A63: TOTAL | J63: =SUM(J13:J62) -> 110
A66: Informațiile incomplete / incorecte vor conduce la neluarea în calcul a indicatorului respectiv

Sheet I. 18
A2: I18 - Aplicaţii la competiţii de cercetare
A4: Aplicaţia la proiect trebuie efectuată în numele ULBS şi trebuie notificată la Serviciul CD.
A5: Punctajul se acordă în momentul afişării rezultatului competiţiei – mimin 60% din punctajul maxim. După caz, pot fi ataşate alte dovezi dacă nu există liste cu punctaje afişate.
A6: Punctajul se acordă directorului de proiect. La decizia directorului, pe baza unei adrese scrise şi semnate, punctajul poate fi împărţit între director şi membrii proiectului, fără a se depăși punctajul maxim admis / aplicație.
A7: Proiectul de cercetare-dezvoltare este identificat cel puţin prin următoarele elemente: scopul proiectului, domeniul de cercetare-dezvoltare, obiective, activităţi de cercetare-dezvoltare, perioada de desfăşurare, tipul sursei de finanţare, bugetul proiectului cu precizarea explicită a cheltuielilor cu salariile, categoria rezultatului, caracterul de noutate şi/sau inovativ al rezultatului.
A8: Proiectele de mobilitate de tip MC / MCD (https://www.uefiscdi.ro/p1-dezvoltarea-sistemului-national-de-cd) se raporteaza la I17.
A9: Proiectele instituționale (contracte ESAYEP-SEE, POCU, Erasmus+ KA1, contracte FDI, contracte ROSE, proiecte depuse la Primărie, proiecte depuse la Consiliul Județean, etc) nu se raportează.
A10: Un proiect se punctează o singură dată (aplicația la proiect), nu se punctează proiectele în derulare.
A11: *Punctaj de referință: Aplicatie la proiecte H2020: • În calitate de beneficiar / coordonator = 1000 puncte / aplicatie • În calitate de partener = 500 puncte / aplicaţie Se acordă un coeficient de multiplicare de 1.5 pentru proiectele câstigate. Aplicatie la alte proiecte de cercetare (ERASMUS+ şi SEE (doar proiectele de cercetare), PN3, alte proiecte administrate de UEFISCDI, Academia Română, ANCS etc): • În calitate de beneficiar = 300 puncte / aplicatie • În calitate de partener = 100 puncte / aplicaţie Se acordă un coeficient de multiplicare de 1.5 pentru proiectele câstigate.
A13: Numele și prenumele | B13: Denumire proiect | C13: Denumire competiție | D13: Calitate ULBS (Beneficiar / coordonator) | E13: Director de proiect | F13: Cod Departament | G13: Site www cu rezultatele competiției | H13: Data la care s-au afișat rezultatele | I13: *Punctaj de referință | J13: Punctaj individual | K13: Numele și prenumele Declarant
A14: Mironescu Ion Dan | B14: PHoEBUS - Development of Professional competencies and competencies through Higher Education and BUSiness cooperation | C14: Erasmus+ KA2 – Cooperation for innovation and the exchange of good practices – Capacity Building in the field of Higher Education | D14: Partener | E14: Mironescu Ion Dan | F14: FSAA2 | G14: https://eacea.ec.europa.eu/erasmus-plus/selection-results/capacity-building-in-field-higher-education-2020_en | H14: 17.08.2020 | I14: 100 | J14: 100 | K14: Mironescu Ion
A15: Mironescu Monica | B15: ECOLOGICAL AND SUSTAINABLE STARCH-BASED ACTIVE FILM TO BE USED AS ADVANCED FOOD PACKAGING | C15: PED Competitivitate prin cercetare, dezvoltare şi inovare – Proiect experimental - demonstrativ | D15: Beneficiar | E15: Mironescu Monica | F15: FSAA2 | G15: https://uefiscdi.gov.ro/resource-829447-d4_finale.pdf | H15: 19.05.2020 | I15: 300 | J15: 300 | K15: Mironescu Monica
A16: Mironescu Monica | B16: Entrepreneurship and E-Learning as New Practices for Promoting Tunisian Higher Education Graduates Employability (4EDU-PRO) | C16: Erasmus+ KA2 – Cooperation for innovation and the exchange of good practices – Capacity Building in the field of Higher Education | D16: Partener | E16: Mironescu Monica | F16: FSAA2 | G16: https://eacea.ec.europa.eu/erasmus-plus/selection-results/capacity-building-in-field-higher-education-2020_en | H16: 17.08.2020 | I16: 100 | J16: 100 | K16: Mironescu Monica
A17: Oancea Simona | B17: PN-III-P4-ID-PCE2020-0164, Cercetări privind potențialul bioantioxidanților vegetali și fungici pentru stabilizarea oxidativă a produselor cu nutrienți termosensibili | C17: programul PNIII - PROIECTE DE CERCETARE EXPLORATORIE (PCE 2020) | D17: beneficiar | E17: Oancea Simona | F17: FSAA2 | G17: https://uefiscdi.gov.ro/resource-825880-pce2020_rezultate-finale_biotehnologii.pdf?&wtok=&wtkps=XU5broIwEN1LvxU7rYUy/LgCY+IKKuVqE146iKBh77aNyb3XrzlzXjkGM3wRSmTkLCsIlUBmQM2STzQ85zFvemN1e53K7pzPPc9SWevLaTutBRlKxzXQ1IIbQhaQuXB9hU4/YOcV45VXlJu/j/c61MDzYlnihNJSoLZahLIMmbV9ezhuZMaFFporHUt99JdZCQAlASTIOEHF1P4rAxzZf6Of9qgCkB41nb3XVdLdzsm9+nFUWpeMrnok5ja4sqtZsbwB&wchk=d33b458a3b53d0da36560abcb6375b9fb0adaad3 | H17: 29.12.2020 | I17: 300 | J17: 300 | K17: Oancea Simona
A18: OGNEAN Mihai | B18: FROM FUNCTIONAL TO TAILOR-MADE FOODS - E-LEARNING TOOLS TO ASSURE SUSTAINABILITY AND INNOVATION” FROM FUNCTIONAL TO TAILOR-MADE FOODS - E-LEARNING TOOLS TO ASSURE SUSTAINABILITY AND INNOVATION” ESI-TaimFoods | C18: ERASMUS+ KA203 - Strategic Partnerships for higher education | D18: partener | E18: George Kostov (Bulgaria) Mihai OGNEAN (ULBS) | F18: FSAA2 | G18: http://hrdc.bg/wp-content/uploads/2020/08/Results_KA2_203_24.03.2020%D0%B3.23.04.2020%D0%B3..xlsx | H18: septembrie 2020 | I18: 100 | J18: 63.5 | K18: Ognean Mihai
A64: TOTAL | J64: =SUM(J14:J63) -> 863.5
A67: Informațiile incomplete / incorecte vor conduce la neluarea în calcul a indicatorului respectiv

Sheet I.19
A2: I19 - Articol ştiințific în revistă neindexată BDI
A4: * Punctaj de referință: • Articol = 20 puncte Punctajul se împarte la numărul de autori cu afiliere la instituţiile de învăţământ şi cercetare din România, inclusiv la doctoranzi / studenţi; pentru autorii din străinătate sau autorii din mediul de afaceri, se menţionează în paranteză instituţia. Plafoane maxime anual: • 60 puncte / declarant
A6: Titlul articolului | B6: Numele și prenumele autorilor | C6: Cod departament | D6: Titlul revistei | E6: Volum / număr | F6: Site-ul revistei | G6: Paginile articolului (de la … până la …) | H6: Anul publicării | I6: ISSN-ul revistei | J6: Punctaj de referință* | K6: Punctaj individual | L6: Numele și prenumele Declarant
A57: TOTAL | K57: =SUM(K7:K56) -> 0
A60: Informațiile incomplete / incorecte vor conduce la neluarea în calcul a indicatorului respectiv

Sheet I.20
A2: I20 - Lucrări / experimente / demonstraţii / inovaţii prezentate sau publicate în volumul unor manifestări ştiinţifice
A4: *Punctaj de referință: • Lucrare = 40 / 20 puncte pentru conferinţă în străinătate / ţară • Experiment / demonstraţie / inovaţie etc = 20 puncte / eveniment (indiferent de numărul standurilor de prezentare în cadrul evenimentului). Punctajul se împarte la numărul de autori / numărul de membri în echipă, cu afiliere la instituţiile de învăţământ şi cercetare din România, inclusiv la doctoranzi / studenţi; pentru autorii din străinătate sau autorii din mediul de afaceri, se menţionează în paranteză instituţia. Plafoane maxime anual: • 60 puncte / declarant
A7: Titlul articolului / Denumirea experimentului | B7: Numele și prenumele autorilor | C7: Cod Departament | D7: Titlul conferinței / Denumirea evenimentului | E7: Site www al conferinței / evenimentului | F7: Data evenimentului | G7: Punctaj de referință* | H7: Punctaj individual | I7: Numele și prenumele Declarant
A8: Resursele genetice pentru alimentație și agricultură din zona montană: valori ale patrimoniului cultural | B8: Antofie MM, Sava C | C8: FSAA2 | D8: ZIUA INTERNAȚIONALĂ A MUNTELUI” – 2020 | E8: http://www.ce-mont.ro/media/attachments/2020/12/09/ziua-internationala-a-muntelui---invitatie-program---11-dec-2020.pdf | F8: 44176 | G8: 20 | H8: 10 | I8: Antofie Mihaela
A9: Aparate, analize și tehnică de cercetare în protecția mediului | B9: Antofie MM | C9: FSAA2 | D9: Noaptea Cercetătorilor | E9: http://cercetare.ulbsibiu.ro/NC_program2020.html | F9: 44162 | G9: 20 | H9: 20 | I9: Antofie Mihaela
A10: Preparate culinare locale | B10: Mirela Cărătuș, Robert Blaj, Iuliana Antonie, Stud. Teodora Conțiu, Stud. Dan Gâdea, Stud. Manuela Mașca, Stud. Adela Maier | C10: ȘAIPA | D10: Noaptea Cercetătorilor 2020 | E10: http://cercetare.ulbsibiu.ro/nc.html | F10: 27.11.2020 | G10: 20 | H10: 20 | I10: Antonie Iuliana
A11: NOI DATE PRIVIND „EXPERIMENTUL GUȘTERIȚA” (JUDEȚUL SIBIU) – FAUNA DE COLEOPTERE | B11: Antonie Iuliana | C11: ȘAIPA | D11: Simpozionul național ”Agricultura si implicatia ei in activitatea si santatea omului” on-line | E11: https://brukenthalnaturale.wordpress.com/2020/10/07/simpozionul-agricultura-si-implicatiile-ei-in-alimentatia-si-sanatatea-omului/ | F11: 08.10.2020 | G11: 20 | H11: 20 | I11: Antonie Iuliana
A12: Aparate, analize și tehnică de cercetare în protecția mediului | B12: Barbu C.H. | C12: FSAA2 | D12: Noaptea cercetatorilor 2020 | E12: http://cercetare.ulbsibiu.ro/NoapteaCercetatorilor/NC2019/ProgramNC2019lung.pdf | F12: 27.11.2020 | G12: 20 | H12: 20 | I12: Barbu Horia
A13: Preparate culinare locale | B13: Mirela Cărătuș, Robert Blaj, Iuliana Antonie, Stud. Teodora Conțiu, Stud. Dan Gâdea, Stud. Manuela Mașca, Stud. Adela Maier | C13: FSAA2 | D13: Noaptea cercetătorilor 2020 | E13: http://cercetare.ulbsibiu.ro/NC_program2020.html | F13: 44162 | G13: 20 | H13: 20 | I13: Blaj Robert
A14: Grădina digitală | B14: Bratu Iulian Alexandru | C14: FSAA2 | D14: Noaptea cercetătorilor | E14: http://cercetare.ulbsibiu.ro/nc.html | F14: 43796 | G14: 20 | H14: 20 | I14: Bratu Alexandru
A15: Preparate culinare locale | B15: Mirela Cărătuș, Robert Blaj, Iuliana Antonie, Stud. Teodora Conțiu, Stud. Dan Gâdea, Stud. Manuela Mașca, Stud. Adela Maier | C15: FSAA2 | D15: Noaptea cercetătorilor 2020 | E15: http://cercetare.ulbsibiu.ro/NC_program2020.html | F15: 44162 | G15: 20 | H15: 20 | I15: Caratus Mirela
A16: Analiza emulsiilor alimentare ulei/apă și apă/ulei | B16: Crețu C.M. | C16: FSAA2 | D16: Noaptea Cercetătorilor | E16: http://cercetare.ulbsibiu.ro/NC_program2020.html | F16: 44162 | G16: 20 | H16: 20 | I16: Cretu Monica
A17: Cum să creștem sănătos? | B17: Cristea Ramona | C17: FSAA2 | D17: NOAPTEA CERCETĂTORILOR | E17: http://cercetare.ulbsibiu.ro/NC_program2020.html | F17: 27 noiembrie 2020 | G17: 20 | H17: 20 | I17: Cristea Ramona
A18: Drojdii de vin | B18: Cristea Ramona | C18: FSAA2 | D18: Noaptea cercetătorilor | E18: http://cercetare.ulbsibiu.ro/NC_program2020.html | F18: 27 nov 2020 | G18: 20 | H18: 20 | I18: Cristea Ramona
A19: Aparate, analize și tehnica de cercetare în protecția mediului | B19: Barbu H., Moise C., Moise G., Gaspar E. | C19: FSAA2 | D19: Universitatea "Lucian Blaga" Noaptea Cercetătorilor | E19: http://cercetare.ulbsibiu.ro/nc.html | F19: 44162 | G19: 20 | H19: 20 | I19: Gaspar Eniko
A20: A comparative study on the chemical composition and antioxidant activity of two species of herbs Melissa officinalis L. and Melittis melissophyllum L. | B20: Lidia-Ioana, Virchea, Felicia Gabriela, Gligor, Adina, Frum, Monica, Mironescu, Cecilia, Georgescu | C20: FSSA2 | D20: Biotechnology and Food Biotechnology Conference | E20: http://bft-conf.com/scientific-committee/ | F20: 27-29 Octombrie 2020 | G20: 40 | H20: 8 | I20: Georgescu Cecilia
A21: Designing novel bioactive hard candy enriched with beta-glucans and essential oils | B21: Mironescu Monica, Danil Terentyev, Georgescu Cecilia, Mark Shamtsyan | C21: FSSA2 | D21: Biotechnology and Food Biotechnology Conference | E21: http://bft-conf.com/scientific-committee/ | F21: 27-29 Octombrie 2020 | G21: 40 | H21: 20 | I21: Georgescu Cecilia
A22: Comparative analysis and antimicrobial action of some essential oils from plants | B22: Monica Mironescu, Nina I. Myachikova and Cecilia Georgescu | C22: FSSA2 | D22: INNОVATIОNS IN LIFE SСIENСES | E22: http://ils2020.bsu.edu.ru/ils2020/ | F22: 19-20 Mai, 2020 | G22: 40 | H22: 20 | I22: Georgescu Cecilia
A23: Ceaiuri de poveste si dulceta bunicii | B23: Iagaru Romulus, Iagaru Pompilica | C23: FSAA2 | D23: Noaptea cercetatorilor | E23: http://cercetare.ulbsibiu.ro/NC_program2020.html | F23: 27 noiembrie 2020 | G23: 20 | H23: 0 | I23: Iagaru Pompilica
A24: Sistem aerian de monitorizare a culturilor agricole | B24: Iagaru Romulus, Iagaru Pompilica, Bratu Iulian, Barbu Ion, Pășcănuț Ioan | C24: FSAA2 | D24: Noaptea cercetatorilor | E24: http://cercetare.ulbsibiu.ro/NC_program2020.html | F24: 27 noiembrie 2020 | G24: 20 | H24: 20 | I24: Iagaru Pompilica
A25: Ceaiuri de poveste si dulceta bunicii | B25: Iagaru Romulus, Iagaru Pompilica | C25: FSAA2 | D25: Noaptea cercetatorilor | E25: http://cercetare.ulbsibiu.ro/NC_program2020.html | F25: 27 noiembrie 2020 | G25: 20 | H25: 0 | I25: Iagaru Romulus
A26: Sistem aerian de monitorizare a culturilor agricole | B26: Iagaru Romulus, Iagaru Pompilica, Bratu Iulian, Barbu Ion, Pășcănuț Ioan | C26: FSAA2 | D26: Noaptea cercetatorilor | E26: http://cercetare.ulbsibiu.ro/NC_program2020.html | F26: 27 noiembrie 2020 | G26: 20 | H26: 20 | I26: Iagaru Romulus
A27: Rulouri de sfecla roșie | B27: Iancu Maria Lidia | C27: FSAA2 | D27: Noaptea cercetătorilor | E27: http://cercetare.ulbsibiu.ro/NC_program2020.html | F27: 44162 | G27: 20 | H27: 20 | I27: Iancu Maria
A28: DECONTAMINATION REACTOR OF AFLATOXIN M IN MILK | B28: Otto KETNEY, Aurel - Mihail TITU | C28: FSAAA2 | D28: EUROINVENT 2020 | E28: https://www.euroinvent.org/ | F28: 21-23.03.2020 | G28: 20 | H28: =G28/2 -> 10 | I28: Ketney Otto
A29: One of the major problems facing humanity | B29: Doina Roncea, (biolog pensionar) Ecaterina Lengyel | C29: FSAA2 | D29: ”Anthropology of communication”, Proceedings of the 5th International Conference, Sibiu, 147-157, ISBN 978-606-733-290-2 | E29: https://lobbyart-anthropology.ro/Anthropology--and--Communication.php | F29: 44105 | G29: 20 | H29: 20 | I29: Lengyel Ecaterina
A30: Drojdii de vin | B30: Lengyel Ecaterina | C30: FSAA2 | D30: Noaptea cercetătorilor | E30: http://cercetare.ulbsibiu.ro/NC_program2020.html | F30: 27 nov 2020 | G30: 20 | H30: 20 | I30: Lengyel Ecaterina
A31: A comparative study on the chemical composition and antioxidant activity of two species of herbs Melissa officinalis L. and Melittis melissophyllum L. | B31: Lidia-Ioana Virchea, Felicia Gabriela Gligor, Adina Frum, Monica Mironescu, Cecilia Georgescu | C31: FSSA2 | D31: Biotechnology and Food Biotechnology Conference | E31: http://bft-conf.com/scientific-committee/ | F31: 27-29 Octombrie 2020 | G31: 40 | H31: 8 | I31: Mironescu Monica
A32: Comparative analysis of the chemical composition and antioxidant activity of fruits and berries from Romania and Russia | B32: Anastasiia Sumacheva, Adina Frum, Mark Shamtsyan, Endre Mathe, Monica Mironescu, Cecilia Georgescu | C32: FSSA2 | D32: Biotechnology and Food Biotechnology Conference | E32: http://bft-conf.com/scientific-committee/ | F32: 27-29 Octombrie 2020 | G32: 40 | H32: 10 | I32: Mironescu Monica
A33: Designing novel bioactive hard candy enriched with beta-glucans and essential oils | B33: Mironescu Monica, Danil Terentyev, Georgescu Cecilia, Mark Shamtsyan | C33: FSSA2 | D33: Biotechnology and Food Biotechnology Conference | E33: http://bft-conf.com/scientific-committee/ | F33: 27-29 Octombrie 2020 | G33: 40 | H33: 20 | I33: Mironescu Monica
A34: Comparative analysis and antimicrobial action of some essential oils from plants | B34: Monica Mironescu, Nina I. Myachikova and Cecilia Georgescu | C34: FSSA2 | D34: INNОVATIОNS IN LIFE SСIENСES | E34: http://ils2020.bsu.edu.ru/ils2020/ | F34: 19-20 Mai, 2020 | G34: 40 | H34: 20 | I34: Mironescu Monica
A35: Aparate, analize și tehnică de cercetare în protecția mediului | B35: Camelia Sava, Cristina Moise, Horia Barbu, Mihaela Antofie, George Moise, Eniko Gaspar, Alexandra Nagy, Petronela Vecerdea, Stud. Ana Maria Marinescu, Stud. Claudia Căta, Stud. Roxana Rusu | C35: FSAA | D35: Noaptea cercetatorilor | E35: http://cercetare.ulbsibiu.ro/nc.html | F35: 27 Noiembrie 2020 | G35: 20 | H35: 20 | I35: Moise George
A36: SUPRAFAȚA ANTROPICĂ, UN INDICATOR AL DEZECHILIBRULUI CLIMATIC PLANETAR | B36: Moise George | C36: FSAA | D36: PROGRAMUL SIMPOZIONULUI ȘTIINȚIFIC ANUAL – 2020, Simpozionul AGRICULTURA ȘI IMPLICAȚIILE EI ÎN ALIMENTAȚIA ȘI SĂNĂTATEA OMULUI | E36: http://saiapm.ulbsibiu.ro/index.php/ciaiaso-2020/ | F36: 8 octombrie 2020 | G36: 20 | H36: 20 | I36: Moise George
A37: Aparate, analize și tehnică de cercetare în protecția mediului | B37: Camelia Sava, Cristina Moise, Horia Barbu, Mihaela Antofie, George Moise, Eniko Gaspar, Alexandra Nagy, Petronela Vecerdea, Stud. Ana Maria Marinescu, Stud. Claudia Căta, Stud. Roxana Rusu | C37: FSAA | D37: Noaptea cercetatorilor | E37: http://cercetare.ulbsibiu.ro/nc.html | F37: 27 Noiembrie 2020 | G37: 20 | H37: 20 | I37: Moise Cristina
A38: SOME LEPIDOPTERA SPECIES AS A PEST OF THE FOREST AND AGRICULTURAL ECOSYSTEMS, PRESERVED IN THE ENTOMOLOGICAL COLLECTIONS OF THE NATURAL HISTORY MUSEUM IN SIBIU | B38: Stanca Moise Cristina | C38: FSAA | D38: PROGRAMUL SIMPOZIONULUI ȘTIINȚIFIC ANUAL – 2020, Simpozionul AGRICULTURA ȘI IMPLICAȚIILE EI ÎN ALIMENTAȚIA ȘI SĂNĂTATEA OMULUI | E38: http://saiapm.ulbsibiu.ro/index.php/ciaiaso-2020/ | F38: 8 octombrie 2020 | G38: 20 | H38: 20 | I38: Moise Cristina
A39: Pâinea între tradiție și necesitate | B39: Ognean Mihai, Ognean Claudia Felicia | C39: FSAA2 | D39: Noaptea cercetătorilor | E39: http://cercetare.ulbsibiu.ro/NC_program2020.html | F39: 27 Noiembrie 2020 | G39: 20 | H39: 20 | I39: Ognean Claudia
A40: SOURDOUGH INITIATION: EFFECTS OF TEMPERATURE AND FLOUR TYPE | B40: Ognean Mihai, Ognean Claudia Felicia | C40: FSAA2 | D40: International Scientific Conference “Biotechnology and Food Technology” BFT – 2020 | E40: http://bft-conf.com/. | F40: 27-29 October, 2020 Saint Petersburg, Russi | G40: 40 | H40: 20 | I40: Ognean Claudia
A41: Pâinea între tradiție și necesitate | B41: Ognean Mihai, Ognean Claudia Felicia | C41: FSAA2 | D41: Noaptea cercetătorilor | E41: http://cercetare.ulbsibiu.ro/NC_program2020.html | F41: 27 Noiembrie 2020 | G41: 20 | H41: 20 | I41: Ognean Mihai
... A44: Grădina digitală | B44: Bratu Iulian, Pășcănuț Ioan, Pop Mihail, Savatie Mircea | C44: FSAA3 | D44: Noaptea Cercetatorilor | E44: http://cercetare.ulbsibiu.ro/NC_program2020.html | F44: 28 noiembrie 2020 | G44: 20 | H44: 0 | I44: Pascanut Ioan
A45: Grădina digitală | B45: Pop Mihai Radu | C45: FSAA2 | D45: Noaptea cercetătorilor | E45: http://cercetare.ulbsibiu.ro/nc.html | F45: 43796 | G45: 20 | H45: 20 | I45: Pop Mihai
A46: Analiza emulsiilor alimentare ulei/apă și apă/ ulei | B46: Crețu Monica, Șandru Daniela Maria | C46: FSAA2 | D46: NOAPTEA CERCETĂTORILOR | E46: http://cercetare.ulbsibiu.ro/nc.html | F46: 44162 | G46: 20 | H46: 20 | I46: Sandru Daniela
A47: SAR-COV-2 percepții la nivel mondial | B47: Lengyel Ecaterina, Cristea Ramona, Ș andru Daniela Maria | C47: FSAA2 | D47: NOAPTEA CERCETĂTORILOR | E47: http://cercetare.ulbsibiu.ro/nc.html | F47: 44162 | G47: 20 | H47: 0 | I47: Sandru Daniela
A48: Resursele genetice pentru alimentație și agricultură din zona montană: valori ale patrimoniului cultural | B48: Antofie MM, Sava C | C48: FSAA2 | D48: ZIUA INTERNAȚIONALĂ A MUNTELUI” – 2020 | E48: http://www.ce-mont.ro/media/attachments/2020/12/09/ziua-internationala-a-muntelui---invitatie-program---11-dec-2020.pdf | F48: 44176 | G48: 20 | H48: 10 | I48: Sava Camelia
A49: Aparate, analize și tehnică de cercetare în protecția mediului | B49: Sava C | C49: FSAA2 | D49: Noaptea Cercetătorilor | E49: http://cercetare.ulbsibiu.ro/NC_program2020.html | F49: 44162 | G49: 20 | H49: 20 | I49: Sava Camelia
A50: Grădina digitală | B50: Pop Mihai Radu | C50: FSAA2 | D50: Noaptea cercetătorilor | E50: http://cercetare.ulbsibiu.ro/nc.html | F50: 43796 | G50: 20 | H50: 20 | I50: Savatie Mircea
A51: Anintegrated approach for walnutsindustrial processing | B51: Cristina Popovici (Technical University of Moldova, Republic of Moldova ), Mihaela Adriana Tița (ULBS), Alexei Baerle (Technical University of Moldova, Republic of Moldova ), | C51: FSSA2 | D51: 59thScience Conference of Ruse University,Bulgaria, p.486 | E51: http://conf.uni-ruse.bg/bg/docs/Booklet%20SC%2720.pdf | F51: noiembrie | G51: 40 | H51: 40 | I51: Tita Mihaela
A52: Research on the production of cream cheese from buffalo milk with the addition of pumpkin peel | B52: Mihaela Adriana Tita (ULBS), Loreta Tamošaitienė( Klaipeda State University of Applied Sciences, Lithuania)), Vijole Bradauskiene ( Klaipeda State University of Applied Sciences, Lithuania), Adelina Constantinescu (ULBS), Mădălina Moga (Liceul tehnologic de Industrie Alimentara Sibiu) | C52: FSSA2 | D52: International Scientific Conference “Biotechnology and Food Technology”BFT – 2020, p.107 | F52: octombrie | G52: 40 | H52: 20 | I52: Tita Mihaela
A53: THE ANTIOXIDANT AND PRESERVATIVE POTENTIAL OF FOODS ESSENTIAL OILS. | B53: Tiberius OPRȚA1, Adelina Constantinescu2, Mădălin Marian AMZA3, Valentina Mădălina MOGA4, Ovidiu TIȚA5 1 Solina Romania SRL (Solina Group), Alba Iulia, Romania; 2 Lucian Blaga University of Sibiu, Romania; 3 Moara Cibin Sibiu, Romania; 4 Technical College of Food Industry "Terezianum" Sibiu, Romania; 5 Lucian Blaga University of Sibiu, Romania | C53: FSAA2 | D53: International Scientific Conference “Biotechnology and Food Technology” BFT – 2020 | E53: https://www.e3s-conferences.org/articles/e3sconf/abs/2020/75/contents/contents.html | F53: 27-29 October, 2020 Saint Petersburg, Russia | G53: 40 | H53: 13.33 | I53: Tita Ovidiu
A54: PRIORITIES IN ENSURING QUALITY WINES | B54: Corina CIUCURE1, Diana RAȚĂ2, Anca ONACHE3, Ovidiu TIȚA4, 1 National Research and Development Institute for Cryogenics and Isotopic Technologies – ICSI Rm. Valcea, Romania, 2 SC ADEFARM Plus SRL, Sibiu, Romania, 3 National Research & Development Institute for Biotechnology in Horticulture Stefanesti - Arges, Romania, 4 Lucian Blaga University of Sibiu, Romania | C54: FSAA2 | D54: International Scientific Conference “Biotechnology and Food Technology” BFT – 2020 | E54: https://www.e3s-conferences.org/articles/e3sconf/abs/2020/75/contents/contents.html | F54: 27-29 October, 2020 Saint Petersburg, Russia | G54: 40 | H54: 13.33 | I54: Tita Ovidiu
A55: IDENTIFICATION AND QUANTIFICATION OF GRAPE TERPENIC COMPOUNDS, WINE AUTHENTICATION MARKER | B55: Adelina CONSTANTINESCU1, Anca ONACHE2, Diana RAȚĂ3, Tiberius OPRȚA4, , Mădălin Marian AMZA5, Valentina Mădălina MOGA6, Ovidiu TIȚA1, 1 Lucian Blaga University of Sibiu, Romania, 2 National Research & Development Institute for Biotechnology in Horticulture Stefanesti - Arges, Romania, 3 SC ADEFARM Plus SRL, Sibiu, Romania, 4 Solina Romania SRL (Solina Group), Alba Iulia, Romania; 5 Moara Cibin Sibiu, Romania; 6 Technical College of Food Industry "Terezianum" Sibiu, Romania; | C55: FSAA2 | D55: International Scientific Conference “Biotechnology and Food Technology” BFT – 2020 | E55: https://www.e3s-conferences.org/articles/e3sconf/abs/2020/75/contents/contents.html | F55: 27-29 October, 2020 Saint Petersburg, Russia | G55: 40 | H55: 10 | I55: Tita Ovidiu
A56: Aparate, analize și tehnică de cercetare în protecția mediului | B56: Camelia Sava, Cristina Moise, Horia Barbu, Mihaela Antofie, George Moise, Eniko Gaspar, Alexandra Nagy, Petronela Vecerdea, Stud. Ana Maria Marinescu, Stud. Claudia Căta, Stud. Roxana Rusu | C56: FSAA2 | D56: Noaptea Cercetătorilor Sibiu | E56: http://cercetare.ulbsibiu.ro/NC_program2020.html | F56: 27 Noiembrie 2020 | G56: 20 | H56: 20 | I56: Vecerdea petronela
A57: O vizita in fabrica viitorului | B57: Mironescu Ion Dan | C57: FSAA2 | D57: Noaptea cercetătorilor | E57: https://noapteacercetatorilor.ro/nc/nc2020/sibiu/ https://www.youtube.com/watch?v=OS8fnCB_A6c | F57: 27.11.2020 | G57: 20 | H57: 20 | I57: Mironescu Ion
A58: Outdoor tourism in the context of climate changes | B58: Nicula V., Spânu Simona | C58: FSEC 3 | D58: 27th International Economic Conference – IECS 2019 | E58: https://easychair.org/smart-program/IECS2019/ | F58: octombrie 2020 | G58: 20 | H58: 10 | I58: Spanu Simona
A59: Diagnostic-strategic analysis of sustainable development of Brăila County | B59: Nicula V., Spânu Simona | C59: FSEC 3 | D59: 27th International Economic Conference – IECS 2019 | E59: https://easychair.org/smart-program/IECS2019/ | F59: octombrie 2020 | G59: 20 | H59: 10 | I59: Spanu Simona
A63: TOTAL | H63: =SUM(H8:H62) -> 872.66
A66: Informațiile incomplete / incorecte vor conduce la neluarea în calcul a indicatorului respectiv
